Workbook

Sheet Music_Festival_Data
A1: Festival_Name | B1: City | C1: Date | D1: Tour_Name | E1: Headlining_Artist | F1: Supporting_Artists | G1: Ticket_Price(Rs) | H1: Total_Attendance | I1: Merchandise_Sales (Rs) | J1: Outlier_Flag_for_Merchandise_Sales | K1: Sponsorship_Revenue (Rs) | L1: Outlier_Flag_for_Sponsorship_Revenue | M1: Total_Revenue (Rs) | N1: Data_Validation_Status
A2: NH7 Pune | B2: Kolkata | C2: 45303 | E2: Badshah | F2: DJ Snake, Honey Singh | G2: 1253 | H2: 6166 | I2: 1942290 | J2: =IF(OR(I2>'Missing Values & Outliers'!$K$8,I2<'Missing Values & Outliers'!$K$9),"O","NA") -> NA | K2: 3680408 | L2: =IF(OR(K2>'Missing Values & Outliers'!$K$15,K2<'Missing Values & Outliers'!$K$16),"O","NA") -> NA | M2: 13348696 | N2: Valid
A3: Ziro Festival Arunachal | B3: Delhi | C3: 45403 | E3: Honey Singh | F3: Bryan Adams, Martin Garrix, Mika Singh | G3: 1689 | H3: 40643 | I3: 16622987 | J3: =IF(OR(I3>'Missing Values & Outliers'!$K$8,I3<'Missing Values & Outliers'!$K$9),"O","NA") -> O | K3: 2589481 | L3: =IF(OR(K3>'Missing Values & Outliers'!$K$15,K3<'Missing Values & Outliers'!$K$16),"O","NA") -> NA | M3: 87858495 | N3: Valid
A4: NH7 Pune | B4: Bengaluru | C4: 45553 | D4: Classics Tour | E4: Bryan Adams | F4: Badshah, Arijit Singh, Martin Garrix, Diljit Dosanjh | G4: 6813.8 | H4: 17889.9 | I4: 7667100 | J4: =IF(OR(I4>'Missing Values & Outliers'!$K$8,I4<'Missing Values & Outliers'!$K$9),"O","NA") -> NA | K4: 640053 | L4: =IF(OR(K4>'Missing Values & Outliers'!$K$15,K4<'Missing Values & Outliers'!$K$16),"O","NA") -> NA | M4: 132693072 | N4: Valid
A5: VH1 Supersonic Delhi | B5: Goa | C5: 45353 | E5: Honey Singh | F5: Martin Garrix, Badshah, Ed Sheeran, Diljit Dosanjh | G5: 2144 | H5: 14688 | I5: 2350080 | J5: =IF(OR(I5>'Missing Values & Outliers'!$K$8,I5<'Missing Values & Outliers'!$K$9),"O","NA") -> NA | K5: 2712686 | L5: =IF(OR(K5>'Missing Values & Outliers'!$K$15,K5<'Missing Values & Outliers'!$K$16),"O","NA") -> NA | M5: 36553838 | N5: Valid
A6: Hornbill Festival Nagaland | B6: Nagpur | C6: 45454 | D6: Soulful Nights Tour | E6: Arijit Singh | F6: Martin Garrix, Badshah | G6: 1886 | H6: 35244 | I6: 6132456 | J6: =IF(OR(I6>'Missing Values & Outliers'!$K$8,I6<'Missing Values & Outliers'!$K$9),"O","NA") -> NA | K6: 1181193 | L6: =IF(OR(K6>'Missing Values & Outliers'!$K$15,K6<'Missing Values & Outliers'!$K$16),"O","NA") -> NA | M6: 73783833 | N6: Valid
A7: Ziro Festival Arunachal | B7: Jaipur | C7: 45437 | E7: Mika Singh | F7: Diljit Dosanjh, Mika Singh | G7: 3984 | H7: ='Missing Values & Outliers'!$E$13 -> 20798.88 | I7: 2252122 | J7: =IF(OR(I7>'Missing Values & Outliers'!$K$8,I7<'Missing Values & Outliers'!$K$9),"O","NA") -> NA | K7: 2302603 | L7: =IF(OR(K7>'Missing Values & Outliers'!$K$15,K7<'Missing Values & Outliers'!$K$16),"O","NA") -> NA | M7: 58605653 | N7: Valid
A8: Ziro Festival Arunachal | B8: Goa | C8: 45371 | D8: Classics Tour | E8: Bryan Adams | F8: Ed Sheeran, Mika Singh, Shreya Ghoshal, Bryan Adams | G8: ='Missing Values & Outliers'!$E$5 -> 2910.2168 | H8: 18778.2 | I8: 4828680 | J8: =IF(OR(I8>'Missing Values & Outliers'!$K$8,I8<'Missing Values & Outliers'!$K$9),"O","NA") -> NA | K8: 4948076 | L8: =IF(OR(K8>'Missing Values & Outliers'!$K$15,K8<'Missing Values & Outliers'!$K$16),"O","NA") -> NA | M8: 111635078 | N8: Valid
A9: NH7 Pune | B9: Nagpur | C9: 45462 | E9: Badshah | F9: Honey Singh, Badshah, Bryan Adams, Martin Garrix | G9: 840 | H9: 33535 | I9: 12206740 | J9: =IF(OR(I9>'Missing Values & Outliers'!$K$8,I9<'Missing Values & Outliers'!$K$9),"O","NA") -> NA | K9: 1201595 | L9: =IF(OR(K9>'Missing Values & Outliers'!$K$15,K9<'Missing Values & Outliers'!$K$16),"O","NA") -> NA | M9: 41577735 | N9: Valid
A10: Bollywood Music Project | B10: Delhi | C10: 45440 | E10: Shreya Ghoshal | F10: Ed Sheeran, Shreya Ghoshal, Bryan Adams, Badshah | G10: 4191 | H10: ='Missing Values & Outliers'!$E$13 -> 20798.88 | I10: 4279770 | J10: =IF(OR(I10>'Missing Values & Outliers'!$K$8,I10<'Missing Values & Outliers'!$K$9),"O","NA") -> NA | K10: 3427104 | L10: =IF(OR(K10>'Missing Values & Outliers'!$K$15,K10<'Missing Values & Outliers'!$K$16),"O","NA") -> NA | M10: 81824709 | N10: Valid
A11: Lollapalooza Mumbai | B11: Kolkata | C11: 45319 | E11: Honey Singh | F11: Honey Singh, Diljit Dosanjh | G11: 1823 | H11: 15513 | I11: 7539318 | J11: =IF(OR(I11>'Missing Values & Outliers'!$K$8,I11<'Missing Values & Outliers'!$K$9),"O","NA") -> NA | K11: 3948781 | L11: =IF(OR(K11>'Missing Values & Outliers'!$K$15,K11<'Missing Values & Outliers'!$K$16),"O","NA") -> NA | M11: 39768298 | N11: Valid
A12: Hornbill Festival Nagaland | B12: Jaipur | C12: 45462 | E12: DJ Snake | F12: Honey Singh, Diljit Dosanjh, Arijit Singh | G12: 3953.6 | H12: 21693 | I12: 9306297 | J12: =IF(OR(I12>'Missing Values & Outliers'!$K$8,I12<'Missing Values & Outliers'!$K$9),"O","NA") -> NA | K12: 4798020 | L12: =IF(OR(K12>'Missing Values & Outliers'!$K$15,K12<'Missing Values & Outliers'!$K$16),"O","NA") -> NA | M12: 75365349 | N12: Valid
A13: Sunburn Goa | B13: Goa | C13: 45649 | E13: Shreya Ghoshal | F13: Honey Singh, Badshah, Bryan Adams | G13: 2842 | H13: 24021 | I13: 5020389 | J13: =IF(OR(I13>'Missing Values & Outliers'!$K$8,I13<'Missing Values & Outliers'!$K$9),"O","NA") -> NA | K13: 2851905 | L13: =IF(OR(K13>'Missing Values & Outliers'!$K$15,K13<'Missing Values & Outliers'!$K$16),"O","NA") -> NA | M13: 76139976 | N13: Valid
A14: Supersonic Bengaluru | B14: Pune | C14: 45428 | D14: Born To Shine Tour | E14: Diljit Dosanjh | F14: Mika Singh, Ed Sheeran, Arijit Singh | G14: 528 | H14: 33241 | I14: 2659280 | J14: =IF(OR(I14>'Missing Values & Outliers'!$K$8,I14<'Missing Values & Outliers'!$K$9),"O","NA") -> NA | K14: 3167786 | L14: =IF(OR(K14>'Missing Values & Outliers'!$K$15,K14<'Missing Values & Outliers'!$K$16),"O","NA") -> NA | M14: 19328026 | N14: Valid
A15: Magnetic Fields Rajasthan | B15: Mumbai | C15: 45644 | E15: Martin Garrix | F15: Shreya Ghoshal, Ed Sheeran, Arijit Singh | G15: 1543 | H15: 19867 | I15: 2821114 | J15: =IF(OR(I15>'Missing Values & Outliers'!$K$8,I15<'Missing Values & Outliers'!$K$9),"O","NA") -> NA | K15: 2897760 | L15: =IF(OR(K15>'Missing Values & Outliers'!$K$15,K15<'Missing Values & Outliers'!$K$16),"O","NA") -> NA | M15: 36373655 | N15: Valid
A16: Hornbill Festival Nagaland | B16: Amritsar | C16: 45344 | E16: Shreya Ghoshal | F16: Bryan Adams, Badshah, Honey Singh | G16: 2188 | H16: 20603 | I16: 9559792 | J16: =IF(OR(I16>'Missing Values & Outliers'!$K$8,I16<'Missing Values & Outliers'!$K$9),"O","NA") -> NA | K16: 4600450 | L16: =IF(OR(K16>'Missing Values & Outliers'!$K$15,K16<'Missing Values & Outliers'!$K$16),"O","NA") -> NA | M16: 59239606 | N16: Valid
A17: VH1 Supersonic Delhi | B17: Kolkata | C17: 45581 | D17: Classics Tour | E17: Bryan Adams | F17: Ed Sheeran, Shreya Ghoshal | G17: 2217.6 | H17: 9504.6 | I17: 5892852 | J17: =IF(OR(I17>'Missing Values & Outliers'!$K$8,I17<'Missing Values & Outliers'!$K$9),"O","NA") -> NA | K17: 795307 | L17: =IF(OR(K17>'Missing Values & Outliers'!$K$15,K17<'Missing Values & Outliers'!$K$16),"O","NA") -> NA | M17: 28195711 | N17: Valid
A18: Lollapalooza Mumbai | B18: Delhi | C18: 45455 | D18: Classics Tour | E18: Bryan Adams | F18: Martin Garrix, Mika Singh, Bryan Adams | G18: 5397 | H18: 9158.1 | I18: 1687707 | J18: =IF(OR(I18>'Missing Values & Outliers'!$K$8,I18<'Missing Values & Outliers'!$K$9),"O","NA") -> NA | K18: 2188470 | L18: =IF(OR(K18>'Missing Values & Outliers'!$K$15,K18<'Missing Values & Outliers'!$K$16),"O","NA") -> NA | M18: 54311142 | N18: Valid
A19: Ziro Festival Arunachal | B19: Pune | C19: 45384 | D19: Mathematics Tour | E19: Ed Sheeran | F19: Honey Singh, Ed Sheeran | G19: 1601.6 | H19: 11790 | I19: 3030030 | J19: =IF(OR(I19>'Missing Values & Outliers'!$K$8,I19<'Missing Values & Outliers'!$K$9),"O","NA") -> NA | K19: 3635278 | L19: =IF(OR(K19>'Missing Values & Outliers'!$K$15,K19<'Missing Values & Outliers'!$K$16),"O","NA") -> NA | M19: 20153068 | N19: Valid
A20: Ziro Festival Arunachal | B20: Delhi | C20: 45531 | E20: Shreya Ghoshal | F20: Honey Singh, Mika Singh, Martin Garrix, Ed Sheeran | G20: 4564 | H20: 31755 | I20: 6890835 | J20: =IF(OR(I20>'Missing Values & Outliers'!$K$8,I20<'Missing Values & Outliers'!$K$9),"O","NA") -> NA | K20: 4732974 | L20: =IF(OR(K20>'Missing Values & Outliers'!$K$15,K20<'Missing Values & Outliers'!$K$16),"O","NA") -> NA | M20: 156553629 | N20: Valid
A21: Sunburn Goa | B21: Nagpur | C21: 45634 | D21: Classics Tour | E21: Bryan Adams | F21: Ed Sheeran, Mika Singh, Shreya Ghoshal, Honey Singh | G21: 3350.2 | H21: 2975.7 | I21: 1041495 | J21: =IF(OR(I21>'Missing Values & Outliers'!$K$8,I21<'Missing Values & Outliers'!$K$9),"O","NA") -> NA | K21: 3001940 | L21: =IF(OR(K21>'Missing Values & Outliers'!$K$15,K21<'Missing Values & Outliers'!$K$16),"O","NA") -> NA | M21: 14216078 | N21: Valid
A22: Sunburn Goa | B22: Delhi | C22: 45460 | E22: Badshah | F22: Shreya Ghoshal, Diljit Dosanjh, Arijit Singh | G22: 4045 | H22: 27719 | I22: 7539568 | J22: =IF(OR(I22>'Missing Values & Outliers'!$K$8,I22<'Missing Values & Outliers'!$K$9),"O","NA") -> NA | K22: 4670910 | L22: =IF(OR(K22>'Missing Values & Outliers'!$K$15,K22<'Missing Values & Outliers'!$K$16),"O","NA") -> NA | M22: 124333833 | N22: Valid
A23: Sunburn Goa | B23: Bengaluru | C23: 45425 | D23: Soulful Nights Tour | E23: Arijit Singh | F23: Honey Singh, Diljit Dosanjh, Badshah | G23: 1008 | H23: 21142 | I23: 2558182 | J23: =IF(OR(I23>'Missing Values & Outliers'!$K$8,I23<'Missing Values & Outliers'!$K$9),"O","NA") -> NA | K23: 1632574 | L23: =IF(OR(K23>'Missing Values & Outliers'!$K$15,K23<'Missing Values & Outliers'!$K$16),"O","NA") -> NA | M23: 25501892 | N23: Valid
A24: NH7 Pune | B24: Chandigarh | C24: 45474 | E24: Martin Garrix | F24: Honey Singh, Bryan Adams, DJ Snake | G24: 2334 | H24: 16842 | I24: 6905220 | J24: =IF(OR(I24>'Missing Values & Outliers'!$K$8,I24<'Missing Values & Outliers'!$K$9),"O","NA") -> NA | K24: 1067015 | L24: =IF(OR(K24>'Missing Values & Outliers'!$K$15,K24<'Missing Values & Outliers'!$K$16),"O","NA") -> NA | M24: 47281463 | N24: Valid
A25: Goa Tribal Festival | B25: Delhi | C25: 45299 | D25: Born To Shine Tour | E25: Diljit Dosanjh | F25: Ed Sheeran, Diljit Dosanjh, Shreya Ghoshal, Badshah | G25: ='Missing Values & Outliers'!$E$5 -> 2910.2168 | H25: 14456 | I25: 4603680 | J25: =IF(OR(I25>'Missing Values & Outliers'!$K$8,I25<'Missing Values & Outliers'!$K$9),"O","NA") -> NA | K25: 2403962 | L25: =IF(OR(K25>'Missing Values & Outliers'!$K$15,K25<'Missing Values & Outliers'!$K$16),"O","NA") -> NA | M25: 41090442 | N25: Valid
A26: Magnetic Fields Rajasthan | B26: Amritsar | C26: 45416 | E26: Badshah | F26: Mika Singh, Diljit Dosanjh, Martin Garrix | G26: 3977 | H26: 25243 | I26: 9238938 | J26: =IF(OR(I26>'Missing Values & Outliers'!$K$8,I26<'Missing Values & Outliers'!$K$9),"O","NA") -> NA | K26: 4689343 | L26: =IF(OR(K26>'Missing Values & Outliers'!$K$15,K26<'Missing Values & Outliers'!$K$16),"O","NA") -> NA | M26: 114319692 | N26: Valid
A27: Sunburn Goa | B27: Jaipur | C27: 45407 | E27: Honey Singh | F27: Bryan Adams, Diljit Dosanjh, Honey Singh, Mika Singh | G27: 3449 | H27: 13539 | I27: 5672841 | J27: =IF(OR(I27>'Missing Values & Outliers'!$K$8,I27<'Missing Values & Outliers'!$K$9),"O","NA") -> NA | K27: 3471436 | L27: =IF(OR(K27>'Missing Values & Outliers'!$K$15,K27<'Missing Values & Outliers'!$K$16),"O","NA") -> NA | M27: 55840288 | N27: Valid
A28: Hornbill Festival Nagaland | B28: Pune | C28: 45316 | E28: Badshah | F28: Martin Garrix, Bryan Adams, DJ Snake | G28: 3668 | H28: 36462 | I28: 5250528 | J28: =IF(OR(I28>'Missing Values & Outliers'!$K$8,I28<'Missing Values & Outliers'!$K$9),"O","NA") -> NA | K28: 2377592 | L28: =IF(OR(K28>'Missing Values & Outliers'!$K$15,K28<'Missing Values & Outliers'!$K$16),"O","NA") -> NA | M28: 141370736 | N28: Valid
A29: NH7 Pune | B29: Goa | C29: 45539 | E29: Badshah | F29: Arijit Singh, Diljit Dosanjh | G29: 3279 | H29: 32540 | I29: 13341400 | J29: =IF(OR(I29>'Missing Values & Outliers'!$K$8,I29<'Missing Values & Outliers'!$K$9),"O","NA") -> NA | K29: 2840750 | L29: =IF(OR(K29>'Missing Values & Outliers'!$K$15,K29<'Missing Values & Outliers'!$K$16),"O","NA") -> NA | M29: 122880810 | N29: Valid
A30: NH7 Pune | B30: Amritsar | C30: 45639 | E30: Honey Singh | F30: Diljit Dosanjh, Honey Singh, DJ Snake, Shreya Ghoshal | G30: 2948 | H30: 9316 | I30: 1266976 | J30: =IF(OR(I30>'Missing Values & Outliers'!$K$8,I30<'Missing Values & Outliers'!$K$9),"O","NA") -> NA | K30: 2704822 | L30: =IF(OR(K30>'Missing Values & Outliers'!$K$15,K30<'Missing Values & Outliers'!$K$16),"O","NA") -> NA | M30: 31435366 | N30: Valid
A31: NH7 Pune | B31: Delhi | C31: 45647 | E31: DJ Snake | F31: Bryan Adams, Mika Singh, Arijit Singh | G31: 2749.6 | H31: 17172 | I31: 7830432 | J31: =IF(OR(I31>'Missing Values & Outliers'!$K$8,I31<'Missing Values & Outliers'!$K$9),"O","NA") -> NA | K31: 3956927 | L31: =IF(OR(K31>'Missing Values & Outliers'!$K$15,K31<'Missing Values & Outliers'!$K$16),"O","NA") -> NA | M31: 45513167 | N31: Valid
A32: Ziro Festival Arunachal | B32: Bengaluru | C32: 45410 | E32: Honey Singh | F32: Arijit Singh, Honey Singh | G32: ='Missing Values & Outliers'!$E$5 -> 2910.2168 | H32: 16737 | I32: 6276375 | J32: =IF(OR(I32>'Missing Values & Outliers'!$K$8,I32<'Missing Values & Outliers'!$K$9),"O","NA") -> NA | K32: 2726932 | L32: =IF(OR(K32>'Missing Values & Outliers'!$K$15,K32<'Missing Values & Outliers'!$K$16),"O","NA") -> NA | M32: 85424449 | N32: Valid
A33: NH7 Pune | B33: Chandigarh | C33: 45392 | E33: Shreya Ghoshal | F33: Martin Garrix, Diljit Dosanjh, Badshah, Mika Singh | G33: 632 | H33: 35304 | I33: 10379376 | J33: =IF(OR(I33>'Missing Values & Outliers'!$K$8,I33<'Missing Values & Outliers'!$K$9),"O","NA") -> NA | K33: 1590737 | L33: =IF(OR(K33>'Missing Values & Outliers'!$K$15,K33<'Missing Values & Outliers'!$K$16),"O","NA") -> NA | M33: 34282241 | N33: Valid
A34: Goa Tribal Festival | B34: Kolkata | C34: 45360 | E34: Honey Singh | F34: DJ Snake, Arijit Singh, Badshah, Mika Singh | G34: 1932 | H34: 16841 | I34: 7713178 | J34: =IF(OR(I34>'Missing Values & Outliers'!$K$8,I34<'Missing Values & Outliers'!$K$9),"O","NA") -> NA | K34: 4738764 | L34: =IF(OR(K34>'Missing Values & Outliers'!$K$15,K34<'Missing Values & Outliers'!$K$16),"O","NA") -> NA | M34: 44988754 | N34: Valid
A35: Ziro Festival Arunachal | B35: Goa | C35: 45358 | D35: Classics Tour | E35: Bryan Adams | F35: Mika Singh, Diljit Dosanjh, Shreya Ghoshal | G35: 1598.8 | H35: 18210.5 | I35: 7336230 | J35: =IF(OR(I35>'Missing Values & Outliers'!$K$8,I35<'Missing Values & Outliers'!$K$9),"O","NA") -> NA | K35: 2229062 | L35: =IF(OR(K35>'Missing Values & Outliers'!$K$15,K35<'Missing Values & Outliers'!$K$16),"O","NA") -> NA | M35: 39274422 | N35: Valid
A36: NH7 Pune | B36: Delhi | C36: 45326 | D36: Born To Shine Tour | E36: Diljit Dosanjh | F36: Mika Singh, Ed Sheeran, Honey Singh, Diljit Dosanjh | G36: 1933 | H36: 58687.2 | I36: 16296984 | J36: =IF(OR(I36>'Missing Values & Outliers'!$K$8,I36<'Missing Values & Outliers'!$K$9),"O","NA") -> O | K36: 1120895 | L36: =IF(OR(K36>'Missing Values & Outliers'!$K$15,K36<'Missing Values & Outliers'!$K$16),"O","NA") -> NA | M36: 104681231 | N36: Valid
A37: Lollapalooza Mumbai | B37: Bengaluru | C37: 45395 | D37: Born To Shine Tour | E37: Diljit Dosanjh | F37: Diljit Dosanjh, DJ Snake, Honey Singh, Shreya Ghoshal | G37: ='Missing Values & Outliers'!$E$5 -> 2910.2168 | H37: 7559.5 | I37: 1913135 | J37: =IF(OR(I37>'Missing Values & Outliers'!$K$8,I37<'Missing Values & Outliers'!$K$9),"O","NA") -> NA | K37: 4680189 | L37: =IF(OR(K37>'Missing Values & Outliers'!$K$15,K37<'Missing Values & Outliers'!$K$16),"O","NA") -> NA | M37: 21654174 | N37: Valid
A38: VH1 Supersonic Delhi | B38: Bengaluru | C38: 45509 | E38: Martin Garrix | F38: DJ Snake, Honey Singh, Diljit Dosanjh | G38: 4452 | H38: 31745 | I38: 4412555 | J38: =IF(OR(I38>'Missing Values & Outliers'!$K$8,I38<'Missing Values & Outliers'!$K$9),"O","NA") -> NA | K38: 4091720 | L38: =IF(OR(K38>'Missing Values & Outliers'!$K$15,K38<'Missing Values & Outliers'!$K$16),"O","NA") -> NA | M38: 149833015 | N38: Valid
A39: Bollywood Music Project | B39: Mumbai | C39: 45555 | E39: Mika Singh | F39: Arijit Singh, DJ Snake, Martin Garrix | G39: 2716 | H39: 12688 | I39: 2486848 | J39: =IF(OR(I39>'Missing Values & Outliers'!$K$8,I39<'Missing Values & Outliers'!$K$9),"O","NA") -> NA | K39: 1413822 | L39: =IF(OR(K39>'Missing Values & Outliers'!$K$15,K39<'Missing Values & Outliers'!$K$16),"O","NA") -> NA | M39: 38361278 | N39: Valid
A40: Sunburn Goa | B40: Chandigarh | C40: 45507 | E40: Mika Singh | F40: DJ Snake, Badshah | G40: 2237 | H40: 20276 | I40: 9671652 | J40: =IF(OR(I40>'Missing Values & Outliers'!$K$8,I40<'Missing Values & Outliers'!$K$9),"O","NA") -> NA | K40: 4912334 | L40: =IF(OR(K40>'Missing Values & Outliers'!$K$15,K40<'Missing Values & Outliers'!$K$16),"O","NA") -> NA | M40: 59941398 | N40: Valid
A41: Bollywood Music Project | B41: Nagpur | C41: 45468 | E41: Badshah | F41: DJ Snake, Honey Singh, Diljit Dosanjh | G41: 1412 | H41: ='Missing Values & Outliers'!$E$13 -> 20798.88 | I41: 12753000 | J41: =IF(OR(I41>'Missing Values & Outliers'!$K$8,I41<'Missing Values & Outliers'!$K$9),"O","NA") -> NA | K41: 663225 | L41: =IF(OR(K41>'Missing Values & Outliers'!$K$15,K41<'Missing Values & Outliers'!$K$16),"O","NA") -> NA | M41: 61435521 | N41: Valid
A42: Bollywood Music Project | B42: Goa | C42: 45654 | D42: Born To Shine Tour | E42: Diljit Dosanjh | F42: Diljit Dosanjh, Shreya Ghoshal, Ed Sheeran | G42: 836 | H42: 56160 | I42: 14904000 | J42: =IF(OR(I42>'Missing Values & Outliers'!$K$8,I42<'Missing Values & Outliers'!$K$9),"O","NA") -> NA | K42: 4753926 | L42: =IF(OR(K42>'Missing Values & Outliers'!$K$15,K42<'Missing Values & Outliers'!$K$16),"O","NA") -> NA | M42: 55773126 | N42: Valid
A43: Bollywood Music Project | B43: Chandigarh | C43: 45527 | D43: Born To Shine Tour | E43: Diljit Dosanjh | F43: Bryan Adams, DJ Snake, Mika Singh, Shreya Ghoshal | G43: 625 | H43: 34043.1 | I43: 11705589 | J43: =IF(OR(I43>'Missing Values & Outliers'!$K$8,I43<'Missing Values & Outliers'!$K$9),"O","NA") -> NA | K43: 2483828 | L43: =IF(OR(K43>'Missing Values & Outliers'!$K$15,K43<'Missing Values & Outliers'!$K$16),"O","NA") -> NA | M43: 30556292 | N43: Valid
A44: Lollapalooza Mumbai | B44: Kolkata | C44: 45555 | E44: Badshah | F44: Mika Singh, Arijit Singh, Ed Sheeran | G44: 4629 | H44: 34318 | I44: 5113382 | J44: =IF(OR(I44>'Missing Values & Outliers'!$K$8,I44<'Missing Values & Outliers'!$K$9),"O","NA") -> NA | K44: 3030898 | L44: =IF(OR(K44>'Missing Values & Outliers'!$K$15,K44<'Missing Values & Outliers'!$K$16),"O","NA") -> NA | M44: 167002302 | N44: Valid
A45: Lollapalooza Mumbai | B45: Chandigarh | C45: 45524 | E45: Mika Singh | F45: Shreya Ghoshal, Badshah, Arijit Singh, Bryan Adams | G45: 3412 | H45: 22029 | I45: 7401744 | J45: =IF(OR(I45>'Missing Values & Outliers'!$K$8,I45<'Missing Values & Outliers'!$K$9),"O","NA") -> NA | K45: 4420985 | L45: =IF(OR(K45>'Missing Values & Outliers'!$K$15,K45<'Missing Values & Outliers'!$K$16),"O","NA") -> NA | M45: 86985677 | N45: Valid
A46: Hornbill Festival Nagaland | B46: Jaipur | C46: 45606 | D46: Born To Shine Tour | E46: Diljit Dosanjh | F46: Badshah, Arijit Singh, Mika Singh, Bryan Adams | G46: 2105 | H46: 52642.2 | I46: 15468708 | J46: =IF(OR(I46>'Missing Values & Outliers'!$K$8,I46<'Missing Values & Outliers'!$K$9),"O","NA") -> O | K46: 4334451 | L46: =IF(OR(K46>'Missing Values & Outliers'!$K$15,K46<'Missing Values & Outliers'!$K$16),"O","NA") -> NA | M46: 105043029 | N46: Valid
A47: Ziro Festival Arunachal | B47: Mumbai | C47: 45512 | D47: Born To Shine Tour | E47: Diljit Dosanjh | F47: Badshah, DJ Snake, Honey Singh, Mika Singh | G47: 737 | H47: 28345.2 | I47: 3292404 | J47: =IF(OR(I47>'Missing Values & Outliers'!$K$8,I47<'Missing Values & Outliers'!$K$9),"O","NA") -> NA | K47: 4566892 | L47: =IF(OR(K47>'Missing Values & Outliers'!$K$15,K47<'Missing Values & Outliers'!$K$16),"O","NA") -> NA | M47: 23928844 | N47: Valid
A48: Sunburn Goa | B48: Goa | C48: 45654 | E48: Mika Singh | F48: Honey Singh, Shreya Ghoshal | G48: 933 | H48: 31752 | I48: 5366088 | J48: =IF(OR(I48>'Missing Values & Outliers'!$K$8,I48<'Missing Values & Outliers'!$K$9),"O","NA") -> NA | K48: 1334941 | L48: =IF(OR(K48>'Missing Values & Outliers'!$K$15,K48<'Missing Values & Outliers'!$K$16),"O","NA") -> NA | M48: 36325645 | N48: Valid
A49: Ziro Festival Arunachal | B49: Bengaluru | C49: 45467 | D49: Soulful Nights Tour | E49: Arijit Singh | F49: Ed Sheeran, Arijit Singh, Badshah | G49: 4503 | H49: 7651 | I49: 1361878 | J49: =IF(OR(I49>'Missing Values & Outliers'!$K$8,I49<'Missing Values & Outliers'!$K$9),"O","NA") -> NA | K49: 2805968 | L49: =IF(OR(K49>'Missing Values & Outliers'!$K$15,K49<'Missing Values & Outliers'!$K$16),"O","NA") -> NA | M49: 38620299 | N49: Valid
A50: Supersonic Bengaluru | B50: Chandigarh | C50: 45423 | D50: Mathematics Tour | E50: Ed Sheeran | F50: DJ Snake, Mika Singh | G50: 2615.2 | H50: 6000 | I50: 2094000 | J50: =IF(OR(I50>'Missing Values & Outliers'!$K$8,I50<'Missing Values & Outliers'!$K$9),"O","NA") -> NA | K50: 3409793 | L50: =IF(OR(K50>'Missing Values & Outliers'!$K$15,K50<'Missing Values & Outliers'!$K$16),"O","NA") -> NA | M50: 16711793 | N50: Valid
A51: Supersonic Bengaluru | B51: Jaipur | C51: 45386 | D51: Born To Shine Tour | E51: Diljit Dosanjh | F51: Mika Singh, Ed Sheeran | G51: 4046 | H51: 32925.1 | I51: 4356244 | J51: =IF(OR(I51>'Missing Values & Outliers'!$K$8,I51<'Missing Values & Outliers'!$K$9),"O","NA") -> NA | K51: 1785594 | L51: =IF(OR(K51>'Missing Values & Outliers'!$K$15,K51<'Missing Values & Outliers'!$K$16),"O","NA") -> NA | M51: 108614880 | N51: Valid
A52: VH1 Supersonic Delhi | B52: Nagpur | C52: 45318 | D52: Classics Tour | E52: Bryan Adams | F52: Mika Singh, Badshah | G52: 4613 | H52: 9412.2 | I52: 5580090 | J52: =IF(OR(I52>'Missing Values & Outliers'!$K$8,I52<'Missing Values & Outliers'!$K$9),"O","NA") -> NA | K52: 4314798 | L52: =IF(OR(K52>'Missing Values & Outliers'!$K$15,K52<'Missing Values & Outliers'!$K$16),"O","NA") -> NA | M52: 54199458 | N52: Valid
A53: VH1 Supersonic Delhi | B53: Goa | C53: 45499 | D53: Soulful Nights Tour | E53: Arijit Singh | F53: Ed Sheeran, DJ Snake, Mika Singh | G53: 3437 | H53: 17457 | I53: 4800675 | J53: =IF(OR(I53>'Missing Values & Outliers'!$K$8,I53<'Missing Values & Outliers'!$K$9),"O","NA") -> NA | K53: 3816903 | L53: =IF(OR(K53>'Missing Values & Outliers'!$K$15,K53<'Missing Values & Outliers'!$K$16),"O","NA") -> NA | M53: 68617287 | N53: Valid
A54: Supersonic Bengaluru | B54: Jaipur | C54: 45543 | E54: Martin Garrix | F54: Martin Garrix, Badshah | G54: 2167 | H54: 23456 | I54: 8068864 | J54: =IF(OR(I54>'Missing Values & Outliers'!$K$8,I54<'Missing Values & Outliers'!$K$9),"O","NA") -> NA | K54: 4892379 | L54: =IF(OR(K54>'Missing Values & Outliers'!$K$15,K54<'Missing Values & Outliers'!$K$16),"O","NA") -> NA | M54: 63790395 | N54: Valid
A55: VH1 Supersonic Delhi | B55: Goa | C55: 45607 | D55: Classics Tour | E55: Bryan Adams | F55: Diljit Dosanjh, Badshah, Bryan Adams | G55: 2289 | H55: 12636.4 | I55: 5054560 | J55: =IF(OR(I55>'Missing Values & Outliers'!$K$8,I55<'Missing Values & Outliers'!$K$9),"O","NA") -> NA | K55: 11048770 | L55: =IF(OR(K55>'Missing Values & Outliers'!$K$15,K55<'Missing Values & Outliers'!$K$16),"O","NA") -> O | M55: 36779334 | N55: Valid
A56: Ziro Festival Arunachal | B56: Nagpur | C56: 45635 | E56: Honey Singh | F56: Arijit Singh, Honey Singh, Shreya Ghoshal, Ed Sheeran | G56: 2495 | H56: 26922 | I56: 12868716 | J56: =IF(OR(I56>'Missing Values & Outliers'!$K$8,I56<'Missing Values & Outliers'!$K$9),"O","NA") -> NA | K56: 4865146 | L56: =IF(OR(K56>'Missing Values & Outliers'!$K$15,K56<'Missing Values & Outliers'!$K$16),"O","NA") -> NA | M56: 339617008 | N56: Valid
A57: Magnetic Fields Rajasthan | B57: Nagpur | C57: 45304 | D57: Classics Tour | E57: Bryan Adams | F57: Arijit Singh, Diljit Dosanjh | G57: 1244.6 | H57: 23400.3 | I57: 10463277 | J57: =IF(OR(I57>'Missing Values & Outliers'!$K$8,I57<'Missing Values & Outliers'!$K$9),"O","NA") -> NA | K57: 1325646 | L57: =IF(OR(K57>'Missing Values & Outliers'!$K$15,K57<'Missing Values & Outliers'!$K$16),"O","NA") -> NA | M57: 41507304 | N57: Valid
A58: Sunburn Goa | B58: Pune | C58: 45509 | E58: Shreya Ghoshal | F58: DJ Snake, Shreya Ghoshal, Honey Singh, Diljit Dosanjh | G58: 4120 | H58: ='Missing Values & Outliers'!$E$13 -> 20798.88 | I58: 4873518 | J58: =IF(OR(I58>'Missing Values & Outliers'!$K$8,I58<'Missing Values & Outliers'!$K$9),"O","NA") -> NA | K58: 2422363 | L58: =IF(OR(K58>'Missing Values & Outliers'!$K$15,K58<'Missing Values & Outliers'!$K$16),"O","NA") -> NA | M58: 93103121 | N58: Valid
A59: Magnetic Fields Rajasthan | B59: Goa | C59: 45448 | E59: Shreya Ghoshal | F59: Martin Garrix, Badshah, Bryan Adams, Arijit Singh | G59: ='Missing Values & Outliers'!$E$5 -> 2910.2168 | H59: ='Missing Values & Outliers'!$E$13 -> 20798.88 | I59: 4728492 | J59: =IF(OR(I59>'Missing Values & Outliers'!$K$8,I59<'Missing Values & Outliers'!$K$9),"O","NA") -> NA | K59: 3476973 | L59: =IF(OR(K59>'Missing Values & Outliers'!$K$15,K59<'Missing Values & Outliers'!$K$16),"O","NA") -> NA | M59: 15717666 | N59: Valid
A60: Goa Tribal Festival | B60: Amritsar | C60: 45326 | D60: Classics Tour | E60: Bryan Adams | F60: Diljit Dosanjh, Ed Sheeran, DJ Snake, Honey Singh | G60: 4459 | H60: 19021.1 | I60: 9592069 | J60: =IF(OR(I60>'Missing Values & Outliers'!$K$8,I60<'Missing Values & Outliers'!$K$9),"O","NA") -> NA | K60: 3713395 | L60: =IF(OR(K60>'Missing Values & Outliers'!$K$15,K60<'Missing Values & Outliers'!$K$16),"O","NA") -> NA | M60: 99851469 | N60: Valid
A61: Ziro Festival Arunachal | B61: Jaipur | C61: 45431 | E61: Shreya Ghoshal | F61: Honey Singh, Ed Sheeran | G61: ='Missing Values & Outliers'!$E$5 -> 2910.2168 | H61: 31020 | I61: 10701900 | J61: =IF(OR(I61>'Missing Values & Outliers'!$K$8,I61<'Missing Values & Outliers'!$K$9),"O","NA") -> NA | K61: 854727 | L61: =IF(OR(K61>'Missing Values & Outliers'!$K$15,K61<'Missing Values & Outliers'!$K$16),"O","NA") -> NA | M61: 122856387 | N61: Valid
A62: Bollywood Music Project | B62: Jaipur | C62: 45583 | E62: Mika Singh | F62: DJ Snake, Arijit Singh, Shreya Ghoshal | G62: ='Missing Values & Outliers'!$E$5 -> 2910.2168 | H62: 5456 | I62: 1085744 | J62: =IF(OR(I62>'Missing Values & Outliers'!$K$8,I62<'Missing Values & Outliers'!$K$9),"O","NA") -> NA | K62: 3936852 | L62: =IF(OR(K62>'Missing Values & Outliers'!$K$15,K62<'Missing Values & Outliers'!$K$16),"O","NA") -> NA | M62: 19235476 | N62: Valid
A63: Hornbill Festival Nagaland | B63: Jaipur | C63: 45484 | D63: Soulful Nights Tour | E63: Arijit Singh | F63: Arijit Singh, DJ Snake, Mika Singh | G63: 4134 | H63: ='Missing Values & Outliers'!$E$13 -> 20798.88 | I63: 15825404 | J63: =IF(OR(I63>'Missing Values & Outliers'!$K$8,I63<'Missing Values & Outliers'!$K$9),"O","NA") -> O | K63: 3103482 | L63: =IF(OR(K63>'Missing Values & Outliers'!$K$15,K63<'Missing Values & Outliers'!$K$16),"O","NA") -> NA | M63: 184975130 | N63: Valid
A64: Bollywood Music Project | B64: Goa | C64: 45486 | E64: DJ Snake | F64: Bryan Adams, Martin Garrix | G64: 5391.4 | H64: 11355 | I64: 2305065 | J64: =IF(OR(I64>'Missing Values & Outliers'!$K$8,I64<'Missing Values & Outliers'!$K$9),"O","NA") -> NA | K64: 1958821 | L64: =IF(OR(K64>'Missing Values & Outliers'!$K$15,K64<'Missing Values & Outliers'!$K$16),"O","NA") -> NA | M64: 191967964 | N64: Valid
A65: Sunburn Goa | B65: Delhi | C65: 45457 | D65: Soulful Nights Tour | E65: Arijit Singh | F65: Martin Garrix, DJ Snake, Arijit Singh, Honey Singh | G65: ='Missing Values & Outliers'!$E$5 -> 2910.2168 | H65: ='Missing Values & Outliers'!$E$13 -> 20798.88 | I65: 3236079 | J65: =IF(OR(I65>'Missing Values & Outliers'!$K$8,I65<'Missing Values & Outliers'!$K$9),"O","NA") -> NA | K65: 3039149 | L65: =IF(OR(K65>'Missing Values & Outliers'!$K$15,K65<'Missing Values & Outliers'!$K$16),"O","NA") -> NA | M65: 24290802 | N65: Valid
A66: Goa Tribal Festival | B66: Nagpur | C66: 45292 | E66: Honey Singh | F66: DJ Snake, Bryan Adams, Martin Garrix, Badshah | G66: 3769 | H66: 35877 | I66: 5489181 | J66: =IF(OR(I66>'Missing Values & Outliers'!$K$8,I66<'Missing Values & Outliers'!$K$9),"O","NA") -> NA | K66: 8648395 | L66: =IF(OR(K66>'Missing Values & Outliers'!$K$15,K66<'Missing Values & Outliers'!$K$16),"O","NA") -> O | M66: 142439273 | N66: Valid
A67: Magnetic Fields Rajasthan | B67: Kolkata | C67: 45370 | E67: Badshah | F67: Diljit Dosanjh, Arijit Singh, Shreya Ghoshal, Mika Singh | G67: 2589 | H67: 8270 | I67: 1563030 | J67: =IF(OR(I67>'Missing Values & Outliers'!$K$8,I67<'Missing Values & Outliers'!$K$9),"O","NA") -> NA | K67: 3564057 | L67: =IF(OR(K67>'Missing Values & Outliers'!$K$15,K67<'Missing Values & Outliers'!$K$16),"O","NA") -> NA | M67: 106152468 | N67: Valid
A68: Sunburn Goa | B68: Nagpur | C68: 45616 | D68: Mathematics Tour | E68: Ed Sheeran | F68: Bryan Adams, Ed Sheeran, Badshah | G68: 1867.6 | H68: 46028 | I68: 20068208 | J68: =IF(OR(I68>'Missing Values & Outliers'!$K$8,I68<'Missing Values & Outliers'!$K$9),"O","NA") -> O | K68: 2266980 | L68: =IF(OR(K68>'Missing Values & Outliers'!$K$15,K68<'Missing Values & Outliers'!$K$16),"O","NA") -> NA | M68: 83736540 | N68: Valid
A69: Bollywood Music Project | B69: Goa | C69: 45420 | E69: Honey Singh | F69: Shreya Ghoshal, DJ Snake, Honey Singh, Bryan Adams | G69: 4078 | H69: 9560 | I69: 3795320 | J69: =IF(OR(I69>'Missing Values & Outliers'!$K$8,I69<'Missing Values & Outliers'!$K$9),"O","NA") -> NA | K69: 2303574 | L69: =IF(OR(K69>'Missing Values & Outliers'!$K$15,K69<'Missing Values & Outliers'!$K$16),"O","NA") -> NA | M69: 45084574 | N69: Valid
A70: Goa Tribal Festival | B70: Goa | C70: 45368 | D70: Soulful Nights Tour | E70: Arijit Singh | F70: Ed Sheeran, Honey Singh, Arijit Singh | G70: 1381 | H70: 13578 | I70: 5336154 | J70: =IF(OR(I70>'Missing Values & Outliers'!$K$8,I70<'Missing Values & Outliers'!$K$9),"O","NA") -> NA | K70: 1442642 | L70: =IF(OR(K70>'Missing Values & Outliers'!$K$15,K70<'Missing Values & Outliers'!$K$16),"O","NA") -> NA | M70: 25530014 | N70: Valid
A71: NH7 Pune | B71: Pune | C71: 45525 | E71: DJ Snake | F71: Bryan Adams, Honey Singh, Arijit Singh | G71: 6914.6 | H71: 40916 | I71: 19926092 | J71: =IF(OR(I71>'Missing Values & Outliers'!$K$8,I71<'Missing Values & Outliers'!$K$9),"O","NA") -> O | K71: 3643451 | L71: =IF(OR(K71>'Missing Values & Outliers'!$K$15,K71<'Missing Values & Outliers'!$K$16),"O","NA") -> NA | M71: 225653667 | N71: Valid
A72: VH1 Supersonic Delhi | B72: Chandigarh | C72: 45506 | E72: Honey Singh | F72: Arijit Singh, Badshah | G72: 2817 | H72: 13994 | I72: 6689132 | J72: =IF(OR(I72>'Missing Values & Outliers'!$K$8,I72<'Missing Values & Outliers'!$K$9),"O","NA") -> NA | K72: 3519113 | L72: =IF(OR(K72>'Missing Values & Outliers'!$K$15,K72<'Missing Values & Outliers'!$K$16),"O","NA") -> NA | M72: 49629343 | N72: Valid
A73: Goa Tribal Festival | B73: Bengaluru | C73: 45317 | E73: Badshah | F73: Bryan Adams, Honey Singh, Mika Singh | G73: 2937 | H73: 14499 | I73: 7177005 | J73: =IF(OR(I73>'Missing Values & Outliers'!$K$8,I73<'Missing Values & Outliers'!$K$9),"O","NA") -> NA | K73: 1341541 | L73: =IF(OR(K73>'Missing Values & Outliers'!$K$15,K73<'Missing Values & Outliers'!$K$16),"O","NA") -> NA | M73: 51102109 | N73: Valid
A74: Sunburn Goa | B74: Nagpur | C74: 45568 | E74: DJ Snake | F74: Ed Sheeran, Honey Singh, Badshah, Mika Singh | G74: 3235.4 | H74: 15002 | I74: 3975530 | J74: =IF(OR(I74>'Missing Values & Outliers'!$K$8,I74<'Missing Values & Outliers'!$K$9),"O","NA") -> NA | K74: 4947667 | L74: =IF(OR(K74>'Missing Values & Outliers'!$K$15,K74<'Missing Values & Outliers'!$K$16),"O","NA") -> NA | M74: 43592819 | N74: Valid
A75: NH7 Pune | B75: Goa | C75: 45339 | E75: DJ Snake | F75: Ed Sheeran, Badshah, Arijit Singh, Bryan Adams | G75: 2224.6 | H75: 23169 | I75: 5630067 | J75: =IF(OR(I75>'Missing Values & Outliers'!$K$8,I75<'Missing Values & Outliers'!$K$9),"O","NA") -> NA | K75: 4471729 | L75: =IF(OR(K75>'Missing Values & Outliers'!$K$15,K75<'Missing Values & Outliers'!$K$16),"O","NA") -> NA | M75: 46917337 | N75: Valid
A76: Supersonic Bengaluru | B76: Nagpur | C76: 45616 | E76: DJ Snake | F76: Martin Garrix, Honey Singh, DJ Snake, Arijit Singh | G76: 2679.6 | H76: ='Missing Values & Outliers'!$E$13 -> 20798.88 | I76: 1370391 | J76: =IF(OR(I76>'Missing Values & Outliers'!$K$8,I76<'Missing Values & Outliers'!$K$9),"O","NA") -> NA | K76: 1953924 | L76: =IF(OR(K76>'Missing Values & Outliers'!$K$15,K76<'Missing Values & Outliers'!$K$16),"O","NA") -> NA | M76: 23346669 | N76: Valid
A77: Magnetic Fields Rajasthan | B77: Pune | C77: 45345 | E77: Mika Singh | F77: Mika Singh, DJ Snake, Bryan Adams, Ed Sheeran | G77: 2567 | H77: 4240 | I77: 1861360 | J77: =IF(OR(I77>'Missing Values & Outliers'!$K$8,I77<'Missing Values & Outliers'!$K$9),"O","NA") -> NA | K77: 1698282 | L77: =IF(OR(K77>'Missing Values & Outliers'!$K$15,K77<'Missing Values & Outliers'!$K$16),"O","NA") -> NA | M77: 14443722 | N77: Valid
A78: Hornbill Festival Nagaland | B78: Delhi | C78: 45543 | D78: Classics Tour | E78: Bryan Adams | F78: Honey Singh, Shreya Ghoshal | G78: 6972 | H78: 21681.1 | I78: 13875904 | J78: =IF(OR(I78>'Missing Values & Outliers'!$K$8,I78<'Missing Values & Outliers'!$K$9),"O","NA") -> NA | K78: 2510128 | L78: =IF(OR(K78>'Missing Values & Outliers'!$K$15,K78<'Missing Values & Outliers'!$K$16),"O","NA") -> NA | M78: 170631572 | N78: Valid
A79: Hornbill Festival Nagaland | B79: Pune | C79: 45510 | E79: Honey Singh | F79: Martin Garrix, Bryan Adams | G79: ='Missing Values & Outliers'!$E$5 -> 2910.2168 | H79: 32900 | I79: 6777400 | J79: =IF(OR(I79>'Missing Values & Outliers'!$K$8,I79<'Missing Values & Outliers'!$K$9),"O","NA") -> NA | K79: 3584230 | L79: =IF(OR(K79>'Missing Values & Outliers'!$K$15,K79<'Missing Values & Outliers'!$K$16),"O","NA") -> NA | M79: 126301230 | N79: Valid
A80: Sunburn Goa | B80: Pune | C80: 45609 | D80: Classics Tour | E80: Bryan Adams | F80: Bryan Adams, Arijit Singh, Honey Singh | G80: 4765.6 | H80: 11366.6 | I80: 6933626 | J80: =IF(OR(I80>'Missing Values & Outliers'!$K$8,I80<'Missing Values & Outliers'!$K$9),"O","NA") -> NA | K80: 2380633 | L80: =IF(OR(K80>'Missing Values & Outliers'!$K$15,K80<'Missing Values & Outliers'!$K$16),"O","NA") -> NA | M80: 64588411 | N80: Valid
A81: Supersonic Bengaluru | B81: Delhi | C81: 45414 | E81: Shreya Ghoshal | F81: Ed Sheeran, Honey Singh, DJ Snake, Bryan Adams | G81: 3243 | H81: 5362 | I81: 739956 | J81: =IF(OR(I81>'Missing Values & Outliers'!$K$8,I81<'Missing Values & Outliers'!$K$9),"O","NA") -> NA | K81: 4259028 | L81: =IF(OR(K81>'Missing Values & Outliers'!$K$15,K81<'Missing Values & Outliers'!$K$16),"O","NA") -> NA | M81: 22387950 | N81: Valid
A82: Supersonic Bengaluru | B82: Chandigarh | C82: 45531 | E82: Martin Garrix | F82: Shreya Ghoshal, Martin Garrix | G82: 1599 | H82: 6748 | I82: 1005452 | J82: =IF(OR(I82>'Missing Values & Outliers'!$K$8,I82<'Missing Values & Outliers'!$K$9),"O","NA") -> NA | K82: 3330904 | L82: =IF(OR(K82>'Missing Values & Outliers'!$K$15,K82<'Missing Values & Outliers'!$K$16),"O","NA") -> NA | M82: 15126408 | N82: Valid
A83: Supersonic Bengaluru | B83: Jaipur | C83: 45326 | D83: Soulful Nights Tour | E83: Arijit Singh | F83: Mika Singh, Diljit Dosanjh | G83: 1180 | H83: 11979 | I83: 3114540 | J83: =IF(OR(I83>'Missing Values & Outliers'!$K$8,I83<'Missing Values & Outliers'!$K$9),"O","NA") -> NA | K83: 2375872 | L83: =IF(OR(K83>'Missing Values & Outliers'!$K$15,K83<'Missing Values & Outliers'!$K$16),"O","NA") -> NA | M83: 19625632 | N83: Valid
A84: Lollapalooza Mumbai | B84: Kolkata | C84: 45601 | D84: Born To Shine Tour | E84: Diljit Dosanjh | F84: Arijit Singh, Mika Singh | G84: 3928 | H84: 45372.6 | I84: 14623938 | J84: =IF(OR(I84>'Missing Values & Outliers'!$K$8,I84<'Missing Values & Outliers'!$K$9),"O","NA") -> NA | K84: 962979 | L84: =IF(OR(K84>'Missing Values & Outliers'!$K$15,K84<'Missing Values & Outliers'!$K$16),"O","NA") -> NA | M84: 152681973 | N84: Valid
A85: Lollapalooza Mumbai | B85: Jaipur | C85: 45401 | E85: Martin Garrix | F85: Mika Singh, Badshah, Ed Sheeran, Diljit Dosanjh | G85: 929 | H85: 17678 | I85: 4118974 | J85: =IF(OR(I85>'Missing Values & Outliers'!$K$8,I85<'Missing Values & Outliers'!$K$9),"O","NA") -> NA | K85: 3432767 | L85: =IF(OR(K85>'Missing Values & Outliers'!$K$15,K85<'Missing Values & Outliers'!$K$16),"O","NA") -> NA | M85: 23974603 | N85: Valid
A86: Lollapalooza Mumbai | B86: Bengaluru | C86: 45454 | E86: Badshah | F86: Arijit Singh, Ed Sheeran | G86: 1824 | H86: 11076 | I86: 2193048 | J86: =IF(OR(I86>'Missing Values & Outliers'!$K$8,I86<'Missing Values & Outliers'!$K$9),"O","NA") -> NA | K86: 4584685 | L86: =IF(OR(K86>'Missing Values & Outliers'!$K$15,K86<'Missing Values & Outliers'!$K$16),"O","NA") -> NA | M86: 26980357 | N86: Valid
A87: Ziro Festival Arunachal | B87: Mumbai | C87: 45385 | D87: Soulful Nights Tour | E87: Arijit Singh | F87: Honey Singh, Martin Garrix, DJ Snake, Bryan Adams | G87: 3034 | H87: 9525 | I87: 1266825 | J87: =IF(OR(I87>'Missing Values & Outliers'!$K$8,I87<'Missing Values & Outliers'!$K$9),"O","NA") -> NA | K87: 659581 | L87: =IF(OR(K87>'Missing Values & Outliers'!$K$15,K87<'Missing Values & Outliers'!$K$16),"O","NA") -> NA | M87: 30825256 | N87: Valid
A88: Sunburn Goa | B88: Amritsar | C88: 45611 | D88: Mathematics Tour | E88: Ed Sheeran | F88: Honey Singh, Bryan Adams, DJ Snake | G88: 798 | H88: ='Missing Values & Outliers'!$E$13 -> 20798.88 | I88: 4874352 | J88: =IF(OR(I88>'Missing Values & Outliers'!$K$8,I88<'Missing Values & Outliers'!$K$9),"O","NA") -> NA | K88: 1012227 | L88: =IF(OR(K88>'Missing Values & Outliers'!$K$15,K88<'Missing Values & Outliers'!$K$16),"O","NA") -> NA | M88: 16292499 | N88: Valid
A89: VH1 Supersonic Delhi | B89: Nagpur | C89: 45636 | D89: Soulful Nights Tour | E89: Arijit Singh | F89: Martin Garrix, Badshah, Honey Singh, DJ Snake | G89: 2753 | H89: 7762 | I89: 2227694 | J89: =IF(OR(I89>'Missing Values & Outliers'!$K$8,I89<'Missing Values & Outliers'!$K$9),"O","NA") -> NA | K89: 3105094 | L89: =IF(OR(K89>'Missing Values & Outliers'!$K$15,K89<'Missing Values & Outliers'!$K$16),"O","NA") -> NA | M89: 26701574 | N89: Valid
A90: Magnetic Fields Rajasthan | B90: Nagpur | C90: 45303 | D90: Soulful Nights Tour | E90: Arijit Singh | F90: Diljit Dosanjh, Mika Singh, DJ Snake | G90: 2609 | H90: 27598 | I90: 13467824 | J90: =IF(OR(I90>'Missing Values & Outliers'!$K$8,I90<'Missing Values & Outliers'!$K$9),"O","NA") -> NA | K90: 3310368 | L90: =IF(OR(K90>'Missing Values & Outliers'!$K$15,K90<'Missing Values & Outliers'!$K$16),"O","NA") -> NA | M90: 88781374 | N90: Valid
A91: Bollywood Music Project | B91: Mumbai | C91: 45324 | D91: Soulful Nights Tour | E91: Arijit Singh | F91: Martin Garrix, DJ Snake, Ed Sheeran, Mika Singh | G91: 4418 | H91: 8702 | I91: 3280654 | J91: =IF(OR(I91>'Missing Values & Outliers'!$K$8,I91<'Missing Values & Outliers'!$K$9),"O","NA") -> NA | K91: 615109 | L91: =IF(OR(K91>'Missing Values & Outliers'!$K$15,K91<'Missing Values & Outliers'!$K$16),"O","NA") -> NA | M91: 42341199 | N91: Valid
A92: VH1 Supersonic Delhi | B92: Bengaluru | C92: 45328 | E92: Shreya Ghoshal | F92: Diljit Dosanjh, Arijit Singh, DJ Snake | G92: 4849 | H92: 8214 | I92: 1667442 | J92: =IF(OR(I92>'Missing Values & Outliers'!$K$8,I92<'Missing Values & Outliers'!$K$9),"O","NA") -> NA | K92: 4255125 | L92: =IF(OR(K92>'Missing Values & Outliers'!$K$15,K92<'Missing Values & Outliers'!$K$16),"O","NA") -> NA | M92: 45752253 | N92: Valid
A93: Supersonic Bengaluru | B93: Amritsar | C93: 45639 | D93: Classics Tour | E93: Bryan Adams | F93: DJ Snake, Mika Singh | G93: 1750 | H93: ='Missing Values & Outliers'!$E$13 -> 20798.88 | I93: 4231825 | J93: =IF(OR(I93>'Missing Values & Outliers'!$K$8,I93<'Missing Values & Outliers'!$K$9),"O","NA") -> NA | K93: 3268157 | L93: =IF(OR(K93>'Missing Values & Outliers'!$K$15,K93<'Missing Values & Outliers'!$K$16),"O","NA") -> NA | M93: 21531232 | N93: Valid
A94: Sunburn Goa | B94: Jaipur | C94: 45425 | E94: DJ Snake | F94: Badshah, Bryan Adams | G94: 4279.8 | H94: 18095 | I94: 4089470 | J94: =IF(OR(I94>'Missing Values & Outliers'!$K$8,I94<'Missing Values & Outliers'!$K$9),"O","NA") -> NA | K94: 1719569 | L94: =IF(OR(K94>'Missing Values & Outliers'!$K$15,K94<'Missing Values & Outliers'!$K$16),"O","NA") -> NA | M94: 61125454 | N94: Valid
A95: Bollywood Music Project | B95: Jaipur | C95: 45481 | E95: Mika Singh | F95: Arijit Singh, Ed Sheeran, Honey Singh, Mika Singh | G95: 3586 | H95: 38295 | I95: 5476185 | J95: =IF(OR(I95>'Missing Values & Outliers'!$K$8,I95<'Missing Values & Outliers'!$K$9),"O","NA") -> NA | K95: 887815 | L95: =IF(OR(K95>'Missing Values & Outliers'!$K$15,K95<'Missing Values & Outliers'!$K$16),"O","NA") -> NA | M95: 143689870 | N95: Valid
A96: Supersonic Bengaluru | B96: Goa | C96: 45632 | E96: Mika Singh | F96: Diljit Dosanjh, Martin Garrix | G96: 3782 | H96: 39893 | I96: 6263201 | J96: =IF(OR(I96>'Missing Values & Outliers'!$K$8,I96<'Missing Values & Outliers'!$K$9),"O","NA") -> NA | K96: 6333350 | L96: =IF(OR(K96>'Missing Values & Outliers'!$K$15,K96<'Missing Values & Outliers'!$K$16),"O","NA") -> NA | M96: 158405197 | N96: Valid
A97: Bollywood Music Project | B97: Bengaluru | C97: 45507 | D97: Mathematics Tour | E97: Ed Sheeran | F97: Mika Singh, DJ Snake | G97: 4834.2 | H97: 14283 | I97: 5356125 | J97: =IF(OR(I97>'Missing Values & Outliers'!$K$8,I97<'Missing Values & Outliers'!$K$9),"O","NA") -> NA | K97: 1549672 | L97: =IF(OR(K97>'Missing Values & Outliers'!$K$15,K97<'Missing Values & Outliers'!$K$16),"O","NA") -> NA | M97: 56224996 | N97: Valid
A98: Bollywood Music Project | B98: Kolkata | C98: 45353 | E98: Badshah | F98: Honey Singh, Diljit Dosanjh, Mika Singh | G98: 4286 | H98: 8925 | I98: 2722125 | J98: =IF(OR(I98>'Missing Values & Outliers'!$K$8,I98<'Missing Values & Outliers'!$K$9),"O","NA") -> NA | K98: 896661 | L98: =IF(OR(K98>'Missing Values & Outliers'!$K$15,K98<'Missing Values & Outliers'!$K$16),"O","NA") -> NA | M98: 41871336 | N98: Valid
A99: Hornbill Festival Nagaland | B99: Delhi | C99: 45427 | D99: Soulful Nights Tour | E99: Arijit Singh | F99: Martin Garrix, Ed Sheeran, Mika Singh | G99: ='Missing Values & Outliers'!$E$5 -> 2910.2168 | H99: 4885 | I99: 1734175 | J99: =IF(OR(I99>'Missing Values & Outliers'!$K$8,I99<'Missing Values & Outliers'!$K$9),"O","NA") -> NA | K99: 4292613 | L99: =IF(OR(K99>'Missing Values & Outliers'!$K$15,K99<'Missing Values & Outliers'!$K$16),"O","NA") -> NA | M99: 23891233 | N99: Valid
A100: Hornbill Festival Nagaland | B100: Nagpur | C100: 45647 | E100: Honey Singh | F100: Mika Singh, Ed Sheeran | G100: 4529 | H100: 4425 | I100: 584100 | J100: =IF(OR(I100>'Missing Values & Outliers'!$K$8,I100<'Missing Values & Outliers'!$K$9),"O","NA") -> NA | K100: 2385440 | L100: =IF(OR(K100>'Missing Values & Outliers'!$K$15,K100<'Missing Values & Outliers'!$K$16),"O","NA") -> NA | M100: 23010365 | N100: Valid
...

Sheet Artist_Popularity_Data
A1: Artist_Name | B1: Genre | C1: Average_Ticket_Price | D1: Average_Attendance_Per_City | E1: Social_Media_Followers (millions) | F1: Streaming_Plays (millions) | G1: Merchandise_Revenue_Per_Concert (Rs) | H1: Tour_Impact | I1: Cities_Performed_In
A2: Diljit Dosanjh | B2: Punjabi | C2: 2027 | D2: 33738 | E2: 46 | F2: 116 | G2: 22334556 | H2: Yes | I2: Amritsar, Kolkata, Delhi, Mumbai, Bengaluru
A3: Honey Singh | B3: Hip-Hop | C3: 1573 | D3: 35223 | E3: 34 | F3: 430 | G3: 25360560 | H3: No | I3: Pune, Amritsar, Bengaluru
A4: Mika Singh | B4: Bollywood | C4: 1025 | D4: 11057 | E4: 12 | F4: 371 | G4: 7983154 | H4: No | I4: Delhi, Amritsar, Bengaluru, Mumbai
A5: Arijit Singh | B5: Bollywood | C5: 2437 | D5: 25729 | E5: 30 | F5: 584 | G5: 18730712 | H5: Yes | I5: Nagpur, Jaipur, Chandigarh
A6: Ed Sheeran | B6: International Pop | C6: 3436 | D6: 18609 | E6: 55 | F6: 736 | G6: 4856949 | H6: Yes | I6: Pune, Amritsar, Goa, Chandigarh
A7: Bryan Adams | B7: Rock | C7: 992 | D7: 21632.556 | E7: 30 | F7: 81 | G7: 8678356 | H7: Yes | I7: Delhi, Jaipur, Bengaluru, Mumbai
A8: DJ Snake | B8: EDM | C8: 1431 | D8: 19089 | E8: 32 | F8: 429 | G8: 10193526 | H8: No | I8: Bengaluru, Jaipur, Mumbai, Chandigarh, Kolkata, Delhi
A9: Martin Garrix | B9: EDM | C9: 2499 | D9: 11603 | E9: 43 | F9: 298 | G9: 6462871 | H9: No | I9: Chandigarh, Delhi, Pune, Nagpur, Bengaluru, Kolkata
A10: Badshah | B10: Bollywood | C10: 3351 | D10: 36448 | E10: 33 | F10: 483 | G10: 20228640 | H10: No | I10: Nagpur, Goa, Amritsar, Chandigarh, Mumbai
A11: Shreya Ghoshal | B11: Classical/Bollywood | C11: 3326 | D11: 3197 | E11: 23 | F11: 271 | G11: 792856 | H11: No | I11: Pune, Mumbai, Delhi, Bengaluru, Amritsar

Sheet Missing Values & Outliers
A1: Missing Values | G1: Outlier
A2: Ticket_Price(Rs) | B2: Total_Attendance | G2: Merchandise_Sales (Rs) | H2: Sponsorship_Revenue (Rs) | P2: Festival_Name | Q2: City | R2: Date | S2: Tour_Name | T2: Headlining_Artist | U2: Supporting_Artists | V2: Ticket_Price(Rs) | W2: Total_Attendance | X2: Merchandise_Sales (Rs) | Y2: Sponsorship_Revenue (Rs) | Z2: Total_Revenue (Rs)
A3: 1253 | B3: 6166 | G3: 1942290 | H3: 3680408 | O3: blank counts | P3: =COUNTBLANK(Music_Festival_Data!A2:A106) -> 0 | Q3: =COUNTBLANK(Music_Festival_Data!B2:B106) -> 0 | R3: =COUNTBLANK(Music_Festival_Data!C2:C106) -> 0 | S3: =COUNTBLANK(Music_Festival_Data!D2:D106) -> 63 | T3: =COUNTBLANK(Music_Festival_Data!E2:E106) -> 0 | U3: =COUNTBLANK(Music_Festival_Data!F2:F106) -> 0 | V3: =COUNTBLANK(Music_Festival_Data!G2:G106) -> 0 | W3: =COUNTBLANK(Music_Festival_Data!H2:H106) -> 0 | X3: =COUNTBLANK(Music_Festival_Data!I2:I106) -> 0 | Y3: =COUNTBLANK(Music_Festival_Data!K2:K106) -> 0 | Z3: =COUNTBLANK(Music_Festival_Data!M2:M106) -> 0
A4: 1689 | B4: 40643 | D4: Ticket Price | G4: 16622987 | H4: 2589481 | J4: Merchandise_Sales (Rs) | O4: outlier | X4: =COUNTIF(Music_Festival_Data!J2:J106,"O") -> 6 | Y4: =COUNTIF(Music_Festival_Data!L2:L106,"O") -> 2
A5: 6813.8 | B5: 17889.9 | D5: average | E5: =AVERAGE($A$3:$A$107) -> 2910.2168 | G5: 7667100 | H5: 640053 | J5: Q1 | K5: =QUARTILE($G$3:$G$107,1) -> 2722125 | O5: Outliers have been removed
A6: 2144 | B6: 14688 | D6: std | E6: =STDEV(A3:A107) -> 1468.7673 | G6: 2350080 | H6: 2712686 | J6: Q3 | K6: =QUARTILE($G$3:$G$107,3) -> 7713178
A7: 1886 | B7: 35244 | D7: std% | E7: =E6/E5*100 -> 50.469341 | G7: 6132456 | H7: 1181193 | J7: IQR | K7: =K6-K5 -> 4991053
A8: 3984 | G8: 2252122 | H8: 2302603 | J8: UL | K8: =K6+(1.5*K7) -> 15199758 | O8: International vs Local Artists
B9: 18778.2 | D9: But in problem statement it | G9: 4828680 | H9: 4948076 | J9: LL | K9: =K5-(1.5*K7) -> -4764454.5 | O9: Artists | P9: International & Local Artists
A10: 840 | B10: 33535 | D10: is asked to fill | G10: 12206740 | H10: 1201595 | O10: Badshah | P10: Local Artist
A11: 4191 | D11: missing values with mean | G11: 4279770 | H11: 3427104 | J11: Sponsorship_Revenue (Rs) | O11: Bryan Adams | P11: International
A12: 1823 | B12: 15513 | D12: Total Attendance | G12: 7539318 | H12: 3948781 | J12: Q1 | K12: =QUARTILE($H$3:$H$107,1) -> 1719569 | O12: Honey Singh | P12: Local Artist
A13: 3953.6 | B13: 21693 | D13: average | E13: =AVERAGE($B$3:$B$107) -> 20798.88 | G13: 9306297 | H13: 4798020 | J13: Q3 | K13: =QUARTILE($H$3:$H$107,3) -> 3956927 | O13: Arijit Singh | P13: Local Artist
A14: 2842 | B14: 24021 | D14: std | E14: =STDEV($B$3:$B$107) -> 12539.172 | G14: 5020389 | H14: 2851905 | J14: IQR | K14: =K13-K12 -> 2237358 | O14: Mika Singh | P14: Local Artist
A15: 528 | B15: 33241 | D15: std% | E15: =E14/E13*100 -> 60.287729 | G15: 2659280 | H15: 3167786 | J15: UL | K15: =K13+(1.5*K14) -> 7312964 | O15: Shreya Ghoshal | P15: Local Artist
A16: 1543 | B16: 19867 | G16: 2821114 | H16: 2897760 | J16: LL | K16: =K12-(1.5*K14) -> -1636468 | O16: DJ Snake | P16: International
A17: 2188 | B17: 20603 | G17: 9559792 | H17: 4600450 | O17: Diljit Dosanjh | P17: Local Artist
A18: 2217.6 | B18: 9504.6 | G18: 5892852 | H18: 795307 | O18: Martin Garrix | P18: International
A19: 5397 | B19: 9158.1 | G19: 1687707 | H19: 2188470 | O19: Ed Sheeran | P19: International
A20: 1601.6 | B20: 11790 | G20: 3030030 | H20: 3635278
A21: 4564 | B21: 31755 | G21: 6890835 | H21: 4732974
A22: 3350.2 | B22: 2975.7 | G22: 1041495 | H22: 3001940
A23: 4045 | B23: 27719 | G23: 7539568 | H23: 4670910
A24: 1008 | B24: 21142 | G24: 2558182 | H24: 1632574
A25: 2334 | B25: 16842 | G25: 6905220 | H25: 1067015
B26: 14456 | G26: 4603680 | H26: 2403962
A27: 3977 | B27: 25243 | G27: 9238938 | H27: 4689343
A28: 3449 | B28: 13539 | G28: 5672841 | H28: 3471436
A29: 3668 | B29: 36462 | G29: 5250528 | H29: 2377592
A30: 3279 | B30: 32540 | G30: 13341400 | H30: 2840750
A31: 2948 | B31: 9316 | G31: 1266976 | H31: 2704822
A32: 2749.6 | B32: 17172 | G32: 7830432 | H32: 3956927
B33: 16737 | G33: 6276375 | H33: 2726932
A34: 632 | B34: 35304 | G34: 10379376 | H34: 1590737
A35: 1932 | B35: 16841 | G35: 7713178 | H35: 4738764
A36: 1598.8 | B36: 18210.5 | G36: 7336230 | H36: 2229062
A37: 1933 | B37: 58687.2 | G37: 16296984 | H37: 1120895
B38: 7559.5 | G38: 1913135 | H38: 4680189
A39: 4452 | B39: 31745 | G39: 4412555 | H39: 4091720
A40: 2716 | B40: 12688 | G40: 2486848 | H40: 1413822
A41: 2237 | B41: 20276 | G41: 9671652 | H41: 4912334
A42: 1412 | G42: 12753000 | H42: 663225
A43: 836 | B43: 56160 | G43: 14904000 | H43: 4753926
A44: 625 | B44: 34043.1 | G44: 11705589 | H44: 2483828
A45: 4629 | B45: 34318 | G45: 5113382 | H45: 3030898
A46: 3412 | B46: 22029 | G46: 7401744 | H46: 4420985
A47: 2105 | B47: 52642.2 | G47: 15468708 | H47: 4334451
A48: 737 | B48: 28345.2 | G48: 3292404 | H48: 4566892
A49: 933 | B49: 31752 | G49: 5366088 | H49: 1334941
A50: 4503 | B50: 7651 | G50: 1361878 | H50: 2805968
A51: 2615.2 | B51: 6000 | G51: 2094000 | H51: 3409793
A52: 4046 | B52: 32925.1 | G52: 4356244 | H52: 1785594
A53: 4613 | B53: 9412.2 | G53: 5580090 | H53: 4314798
A54: 3437 | B54: 17457 | G54: 4800675 | H54: 3816903
... A58: 1244.6 | B58: 23400.3 | G58: 10463277 | H58: 1325646
A59: 4120 | G59: 4873518 | H59: 2422363
G60: 4728492 | H60: 3476973
A61: 4459 | B61: 19021.1 | G61: 9592069 | H61: 3713395
B62: 31020 | G62: 10701900 | H62: 854727
B63: 5456 | G63: 1085744 | H63: 3936852
A64: 4134 | G64: 15825404 | H64: 3103482
A65: 5391.4 | B65: 11355 | G65: 2305065 | H65: 1958821
G66: 3236079 | H66: 3039149
A67: 3769 | B67: 35877 | G67: 5489181 | H67: 8648395
A68: 2589 | B68: 8270 | G68: 1563030 | H68: 3564057
A69: 1867.6 | B69: 46028 | G69: 20068208 | H69: 2266980
A70: 4078 | B70: 9560 | G70: 3795320 | H70: 2303574
A71: 1381 | B71: 13578 | G71: 5336154 | H71: 1442642
A72: 6914.6 | B72: 40916 | G72: 19926092 | H72: 3643451
A73: 2817 | B73: 13994 | G73: 6689132 | H73: 3519113
A74: 2937 | B74: 14499 | G74: 7177005 | H74: 1341541
A75: 3235.4 | B75: 15002 | G75: 3975530 | H75: 4947667
A76: 2224.6 | B76: 23169 | G76: 5630067 | H76: 4471729
A77: 2679.6 | G77: 1370391 | H77: 1953924
A78: 2567 | B78: 4240 | G78: 1861360 | H78: 1698282
A79: 6972 | B79: 21681.1 | G79: 13875904 | H79: 2510128
B80: 32900 | G80: 6777400 | H80: 3584230
A81: 4765.6 | B81: 11366.6 | G81: 6933626 | H81: 2380633
A82: 3243 | B82: 5362 | G82: 739956 | H82: 4259028
A83: 1599 | B83: 6748 | G83: 1005452 | H83: 3330904
A84: 1180 | B84: 11979 | G84: 3114540 | H84: 2375872
A85: 3928 | B85: 45372.6 | G85: 14623938 | H85: 962979
A86: 929 | B86: 17678 | G86: 4118974 | H86: 3432767
A87: 1824 | B87: 11076 | G87: 2193048 | H87: 4584685
A88: 3034 | B88: 9525 | G88: 1266825 | H88: 659581
A89: 798 | G89: 4874352 | H89: 1012227
A90: 2753 | B90: 7762 | G90: 2227694 | H90: 3105094
A91: 2609 | B91: 27598 | G91: 13467824 | H91: 3310368
A92: 4418 | B92: 8702 | G92: 3280654 | H92: 615109
A93: 4849 | B93: 8214 | G93: 1667442 | H93: 4255125
A94: 1750 | G94: 4231825 | H94: 3268157
A95: 4279.8 | B95: 18095 | G95: 4089470 | H95: 1719569
A96: 3586 | B96: 38295 | G96: 5476185 | H96: 887815
A97: 3782 | B97: 39893 | G97: 6263201 | H97: 6333350
A98: 4834.2 | B98: 14283 | G98: 5356125 | H98: 1549672
A99: 4286 | B99: 8925 | G99: 2722125 | H99: 896661
B100: 4885 | G100: 1734175 | H100: 4292613
A101: 4529 | B101: 4425 | G101: 584100 | H101: 2385440
A102: 726 | B102: 37105 | G102: 14545160 | H102: 835232
A103: 1381 | B103: 13578 | G103: 5336154 | H103: 1442642
...

Sheet Data_Validation_Summary
A1: MUSIC FESTIVAL DATA VALIDATION REPORT
A3: 1. DATASET OVERVIEW
A4: Metric | B4: Value
A5: Total Records | B5: =COUNTA(Music_Festival_Data!A2:A106) -> 105
A6: Unique Festivals | B6: 10
A7: Unique Cities | B7: 10
A8: Unique Headlining Artists | B8: 11
A9: Date Range | B9: Jan 2024 - Dec 2024
A11: 2. DUPLICATE RECORDS ANALYSIS
A12: Duplicates Found | B12: =COUNTIF(Music_Festival_Data!N:N,"DUPLICATE - Remove") -> 5
A14: Row | B14: Festival | C14: City | D14: Date | E14: Artist | F14: Original Row
A15: 102 | B15: Goa Tribal Festival | C15: Goa | D15: 17-03-2024 | E15: Arijit Singh | F15: 70
A16: 103 | B16: Sunburn Goa | C16: Jaipur | D16: 13-05-2024 | E16: DJ Snake | F16: 94
A17: 104 | B17: NH7 Pune | C17: Chandigarh | D17: 45298 | E17: Martin Garrix | F17: 24
A18: 105 | B18: Lollapalooza Mumbai | C18: Kolkata | D18: 28-01-2024 | E18: Honey Singh | F18: 11
A19: 106 | B19: NH7 Pune | C19: Amritsar | D19: 13-12-2024 | E19: Honey Singh | F19: 30
A21: 3. MISSING VALUES ANALYSIS
A22: Column | B22: Missing Count | C22: Treatment Method | D22: Mean Value Used
A23: Tour_Name | B23: 63 | C23: Left blank (optional field) | D23: N/A
A24: Ticket_Price (Rs) | B24: 10 | C24: Filled with Mean | D24: ='Missing Values & Outliers'!E5 -> 2910.2168
A25: Total_Attendance | B25: 10 | C25: Filled with Mean | D25: ='Missing Values & Outliers'!E13 -> 20798.88
A29: 4. OUTLIER DETECTION (IQR Method)
A30: Total Outliers Flagged | B30: 8
A32: Outlier Thresholds (from Missing Values & Outliers sheet):
A33: Merchandise Sales - Upper Limit: | B33: ='Missing Values & Outliers'!K8 -> 15199758
A34: Sponsorship Revenue - Upper Limit: | B34: ='Missing Values & Outliers'!K15 -> 7312964
A37: 5. DATA QUALITY SUMMARY
A38: Issue | B38: Count | C38: Status | D38: Action Taken
A39: Duplicate Records | B39: 5 | C39: Removed | D39: Marked in Column N for removal
A40: Missing Ticket Prices | B40: 10 | C40: Resolved | D40: Imputed with mean (₹2,910.22)
A41: Missing Attendance | B41: 10 | C41: Resolved | D41: Imputed with mean (20,798.88)
A42: Outliers Detected | B42: 8 | C42: Removed | D42: Marked in Column J & L for review
A45: 6. CLEAN DATA STATISTICS
A46: Metric | B46: Value
A47: Valid Records (after removal of Duplicates and outliers) | B47: 93
A48: Total Revenue (Valid Records) | B48: =SUM('Cleaned Data'!M2:M93) -> 5964562939
A49: Total Attendance (Valid Records) | B49: =SUM('Cleaned Data'!I2:I93) -> 1802309.7
A50: Avg Ticket Price (Rs) | B50: =AVERAGE('Cleaned Data'!H2:H93) -> 2914.1931
A51: Total Merchandise Sales | B51: =SUM('Cleaned Data'!K2:K93) -> 520726263
A52: Total Sponsorship Revenue | B52: =SUM('Cleaned Data'!L2:L93) -> 268574250
A53: Total International Artists | B53: =GETPIVOTDATA("International & Local Artists",Stage4!$A$54,"International & Local Artists","International ") -> 29
A54: Total Local (Indian) Artists | B54: =GETPIVOTDATA("International & Local Artists",Stage4!$A$54,"International & Local Artists","Local Artist") -> 63

Sheet Cleaned Data
A1: Festival_Name | B1: City | C1: Date | D1: Tour_Name | E1: Headlining_Artist | F1: International & Local Artists | G1: Supporting_Artists | H1: Ticket_Price(Rs) | I1: Total_Attendance | J1: Revenue per Event | K1: Merchandise_Sales (Rs) | L1: Sponsorship_Revenue (Rs) | M1: Total_Revenue (Rs) | N1: Artist_Name | O1: Genre | P1: Average_Ticket_Price | Q1: Average_Attendance_Per_City | R1: Social_Media_Followers (millions) | S1: Streaming_Plays (millions) | T1: Merchandise_Revenue_Per_Concert (Rs) | U1: Tour_Impact | V1: Cities_Performed_In
A2: NH7 Pune | B2: Kolkata | C2: 45303 | E2: Badshah | F2: =VLOOKUP(E2,'Missing Values & Outliers'!$O$10:$P$19,2,0) -> Local Artist | G2: DJ Snake, Honey Singh | H2: 1253 | I2: 6166 | J2: =I2*H2 -> 7725998 | K2: 1942290 | L2: 3680408 | M2: 13348696 | N2: {=VLOOKUP(E2,[1]Artist_Popularity_Data!$A$2:$I$11,{1,2,3,4,5,6,7,8,9},0)} -> Badshah | O2: Bollywood | P2: 3351 | Q2: 36448 | R2: 33 | S2: 483 | T2: 20228640 | U2: No | V2: Nagpur, Goa, Amritsar, Chandigarh, Mumbai
A3: NH7 Pune | B3: Bengaluru | C3: 45553 | D3: Classics Tour | E3: Bryan Adams | F3: =VLOOKUP(E3,'Missing Values & Outliers'!$O$10:$P$19,2,0) -> International | G3: Badshah, Arijit Singh, Martin Garrix, Diljit Dosanjh | H3: 6813.8 | I3: 17889.9 | J3: =I3*H3 -> 1.218982e+08 | K3: 7667100 | L3: 640053 | M3: 132693072 | N3: {=VLOOKUP(E3,[1]Artist_Popularity_Data!$A$2:$I$11,{1,2,3,4,5,6,7,8,9},0)} -> Bryan Adams | O3: Rock | P3: 992 | Q3: 21632.556 | R3: 30 | S3: 81 | T3: 8678356 | U3: Yes | V3: Delhi, Jaipur, Bengaluru, Mumbai
A4: VH1 Supersonic Delhi | B4: Goa | C4: 45353 | E4: Honey Singh | F4: =VLOOKUP(E4,'Missing Values & Outliers'!$O$10:$P$19,2,0) -> Local Artist | G4: Martin Garrix, Badshah, Ed Sheeran, Diljit Dosanjh | H4: 2144 | I4: 14688 | J4: =I4*H4 -> 31491072 | K4: 2350080 | L4: 2712686 | M4: 36553838 | N4: {=VLOOKUP(E4,[1]Artist_Popularity_Data!$A$2:$I$11,{1,2,3,4,5,6,7,8,9},0)} -> Honey Singh | O4: Hip-Hop | P4: 1573 | Q4: 35223 | R4: 34 | S4: 430 | T4: 25360560 | U4: No | V4: Pune, Amritsar, Bengaluru
A5: Hornbill Festival Nagaland | B5: Nagpur | C5: 45454 | D5: Soulful Nights Tour | E5: Arijit Singh | F5: =VLOOKUP(E5,'Missing Values & Outliers'!$O$10:$P$19,2,0) -> Local Artist | G5: Martin Garrix, Badshah | H5: 1886 | I5: 35244 | J5: =I5*H5 -> 66470184 | K5: 6132456 | L5: 1181193 | M5: 73783833 | N5: {=VLOOKUP(E5,[1]Artist_Popularity_Data!$A$2:$I$11,{1,2,3,4,5,6,7,8,9},0)} -> Arijit Singh | O5: Bollywood | P5: 2437 | Q5: 25729 | R5: 30 | S5: 584 | T5: 18730712 | U5: Yes | V5: Nagpur, Jaipur, Chandigarh
A6: Ziro Festival Arunachal | B6: Jaipur | C6: 45437 | E6: Mika Singh | F6: =VLOOKUP(E6,'Missing Values & Outliers'!$O$10:$P$19,2,0) -> Local Artist | G6: Diljit Dosanjh, Mika Singh | H6: 3984 | I6: 20798.88 | J6: =I6*H6 -> 82862738 | K6: 2252122 | L6: 2302603 | M6: 58605653 | N6: {=VLOOKUP(E6,[1]Artist_Popularity_Data!$A$2:$I$11,{1,2,3,4,5,6,7,8,9},0)} -> Mika Singh | O6: Bollywood | P6: 1025 | Q6: 11057 | R6: 12 | S6: 371 | T6: 7983154 | U6: No | V6: Delhi, Amritsar, Bengaluru, Mumbai
A7: Ziro Festival Arunachal | B7: Goa | C7: 45371 | D7: Classics Tour | E7: Bryan Adams | F7: =VLOOKUP(E7,'Missing Values & Outliers'!$O$10:$P$19,2,0) -> International | G7: Ed Sheeran, Mika Singh, Shreya Ghoshal, Bryan Adams | H7: 2910.2168 | I7: 18778.2 | J7: =I7*H7 -> 54648634 | K7: 4828680 | L7: 4948076 | M7: 111635078 | N7: {=VLOOKUP(E7,[1]Artist_Popularity_Data!$A$2:$I$11,{1,2,3,4,5,6,7,8,9},0)} -> Bryan Adams | O7: Rock | P7: 992 | Q7: 21632.556 | R7: 30 | S7: 81 | T7: 8678356 | U7: Yes | V7: Delhi, Jaipur, Bengaluru, Mumbai
A8: NH7 Pune | B8: Nagpur | C8: 45462 | E8: Badshah | F8: =VLOOKUP(E8,'Missing Values & Outliers'!$O$10:$P$19,2,0) -> Local Artist | G8: Honey Singh, Badshah, Bryan Adams, Martin Garrix | H8: 840 | I8: 33535 | J8: =I8*H8 -> 28169400 | K8: 12206740 | L8: 1201595 | M8: 41577735 | N8: {=VLOOKUP(E8,[1]Artist_Popularity_Data!$A$2:$I$11,{1,2,3,4,5,6,7,8,9},0)} -> Badshah | O8: Bollywood | P8: 3351 | Q8: 36448 | R8: 33 | S8: 483 | T8: 20228640 | U8: No | V8: Nagpur, Goa, Amritsar, Chandigarh, Mumbai
A9: Bollywood Music Project | B9: Delhi | C9: 45440 | E9: Shreya Ghoshal | F9: =VLOOKUP(E9,'Missing Values & Outliers'!$O$10:$P$19,2,0) -> Local Artist | G9: Ed Sheeran, Shreya Ghoshal, Bryan Adams, Badshah | H9: 4191 | I9: 20798.88 | J9: =I9*H9 -> 87168106 | K9: 4279770 | L9: 3427104 | M9: 81824709 | N9: {=VLOOKUP(E9,[1]Artist_Popularity_Data!$A$2:$I$11,{1,2,3,4,5,6,7,8,9},0)} -> Shreya Ghoshal | O9: Classical/Bollywood | P9: 3326 | Q9: 3197 | R9: 23 | S9: 271 | T9: 792856 | U9: No | V9: Pune, Mumbai, Delhi, Bengaluru, Amritsar
A10: Lollapalooza Mumbai | B10: Kolkata | C10: 45319 | E10: Honey Singh | F10: =VLOOKUP(E10,'Missing Values & Outliers'!$O$10:$P$19,2,0) -> Local Artist | G10: Honey Singh, Diljit Dosanjh | H10: 1823 | I10: 15513 | J10: =I10*H10 -> 28280199 | K10: 7539318 | L10: 3948781 | M10: 39768298 | N10: {=VLOOKUP(E10,[1]Artist_Popularity_Data!$A$2:$I$11,{1,2,3,4,5,6,7,8,9},0)} -> Honey Singh | O10: Hip-Hop | P10: 1573 | Q10: 35223 | R10: 34 | S10: 430 | T10: 25360560 | U10: No | V10: Pune, Amritsar, Bengaluru
A11: Hornbill Festival Nagaland | B11: Jaipur | C11: 45462 | E11: DJ Snake | F11: =VLOOKUP(E11,'Missing Values & Outliers'!$O$10:$P$19,2,0) -> International | G11: Honey Singh, Diljit Dosanjh, Arijit Singh | H11: 3953.6 | I11: 21693 | J11: =I11*H11 -> 85765445 | K11: 9306297 | L11: 4798020 | M11: 75365349 | N11: {=VLOOKUP(E11,[1]Artist_Popularity_Data!$A$2:$I$11,{1,2,3,4,5,6,7,8,9},0)} -> DJ Snake | O11: EDM | P11: 1431 | Q11: 19089 | R11: 32 | S11: 429 | T11: 10193526 | U11: No | V11: Bengaluru, Jaipur, Mumbai, Chandigarh, Kolkata, Delhi
A12: Sunburn Goa | B12: Goa | C12: 45649 | E12: Shreya Ghoshal | F12: =VLOOKUP(E12,'Missing Values & Outliers'!$O$10:$P$19,2,0) -> Local Artist | G12: Honey Singh, Badshah, Bryan Adams | H12: 2842 | I12: 24021 | J12: =I12*H12 -> 68267682 | K12: 5020389 | L12: 2851905 | M12: 76139976 | N12: {=VLOOKUP(E12,[1]Artist_Popularity_Data!$A$2:$I$11,{1,2,3,4,5,6,7,8,9},0)} -> Shreya Ghoshal | O12: Classical/Bollywood | P12: 3326 | Q12: 3197 | R12: 23 | S12: 271 | T12: 792856 | U12: No | V12: Pune, Mumbai, Delhi, Bengaluru, Amritsar
A13: Supersonic Bengaluru | B13: Pune | C13: 45428 | D13: Born To Shine Tour | E13: Diljit Dosanjh | F13: =VLOOKUP(E13,'Missing Values & Outliers'!$O$10:$P$19,2,0) -> Local Artist | G13: Mika Singh, Ed Sheeran, Arijit Singh | H13: 528 | I13: 33241 | J13: =I13*H13 -> 17551248 | K13: 2659280 | L13: 3167786 | M13: 19328026 | N13: {=VLOOKUP(E13,[1]Artist_Popularity_Data!$A$2:$I$11,{1,2,3,4,5,6,7,8,9},0)} -> Diljit Dosanjh | O13: Punjabi | P13: 2027 | Q13: 33738 | R13: 46 | S13: 116 | T13: 22334556 | U13: Yes | V13: Amritsar, Kolkata, Delhi, Mumbai, Bengaluru
A14: Magnetic Fields Rajasthan | B14: Mumbai | C14: 45644 | E14: Martin Garrix | F14: =VLOOKUP(E14,'Missing Values & Outliers'!$O$10:$P$19,2,0) -> International | G14: Shreya Ghoshal, Ed Sheeran, Arijit Singh | H14: 1543 | I14: 19867 | J14: =I14*H14 -> 30654781 | K14: 2821114 | L14: 2897760 | M14: 36373655 | N14: {=VLOOKUP(E14,[1]Artist_Popularity_Data!$A$2:$I$11,{1,2,3,4,5,6,7,8,9},0)} -> Martin Garrix | O14: EDM | P14: 2499 | Q14: 11603 | R14: 43 | S14: 298 | T14: 6462871 | U14: No | V14: Chandigarh, Delhi, Pune, Nagpur, Bengaluru, Kolkata
A15: Hornbill Festival Nagaland | B15: Amritsar | C15: 45344 | E15: Shreya Ghoshal | F15: =VLOOKUP(E15,'Missing Values & Outliers'!$O$10:$P$19,2,0) -> Local Artist | G15: Bryan Adams, Badshah, Honey Singh | H15: 2188 | I15: 20603 | J15: =I15*H15 -> 45079364 | K15: 9559792 | L15: 4600450 | M15: 59239606 | N15: {=VLOOKUP(E15,[1]Artist_Popularity_Data!$A$2:$I$11,{1,2,3,4,5,6,7,8,9},0)} -> Shreya Ghoshal | O15: Classical/Bollywood | P15: 3326 | Q15: 3197 | R15: 23 | S15: 271 | T15: 792856 | U15: No | V15: Pune, Mumbai, Delhi, Bengaluru, Amritsar
A16: VH1 Supersonic Delhi | B16: Kolkata | C16: 45581 | D16: Classics Tour | E16: Bryan Adams | F16: =VLOOKUP(E16,'Missing Values & Outliers'!$O$10:$P$19,2,0) -> International | G16: Ed Sheeran, Shreya Ghoshal | H16: 2217.6 | I16: 9504.6 | J16: =I16*H16 -> 21077401 | K16: 5892852 | L16: 795307 | M16: 28195711 | N16: {=VLOOKUP(E16,[1]Artist_Popularity_Data!$A$2:$I$11,{1,2,3,4,5,6,7,8,9},0)} -> Bryan Adams | O16: Rock | P16: 992 | Q16: 21632.556 | R16: 30 | S16: 81 | T16: 8678356 | U16: Yes | V16: Delhi, Jaipur, Bengaluru, Mumbai
A17: Lollapalooza Mumbai | B17: Delhi | C17: 45455 | D17: Classics Tour | E17: Bryan Adams | F17: =VLOOKUP(E17,'Missing Values & Outliers'!$O$10:$P$19,2,0) -> International | G17: Martin Garrix, Mika Singh, Bryan Adams | H17: 5397 | I17: 9158.1 | J17: =I17*H17 -> 49426266 | K17: 1687707 | L17: 2188470 | M17: 54311142 | N17: {=VLOOKUP(E17,[1]Artist_Popularity_Data!$A$2:$I$11,{1,2,3,4,5,6,7,8,9},0)} -> Bryan Adams | O17: Rock | P17: 992 | Q17: 21632.556 | R17: 30 | S17: 81 | T17: 8678356 | U17: Yes | V17: Delhi, Jaipur, Bengaluru, Mumbai
A18: Ziro Festival Arunachal | B18: Pune | C18: 45384 | D18: Mathematics Tour | E18: Ed Sheeran | F18: =VLOOKUP(E18,'Missing Values & Outliers'!$O$10:$P$19,2,0) -> International | G18: Honey Singh, Ed Sheeran | H18: 1601.6 | I18: 11790 | J18: =I18*H18 -> 18882864 | K18: 3030030 | L18: 3635278 | M18: 20153068 | N18: {=VLOOKUP(E18,[1]Artist_Popularity_Data!$A$2:$I$11,{1,2,3,4,5,6,7,8,9},0)} -> Ed Sheeran | O18: International Pop | P18: 3436 | Q18: 18609 | R18: 55 | S18: 736 | T18: 4856949 | U18: Yes | V18: Pune, Amritsar, Goa, Chandigarh
A19: Ziro Festival Arunachal | B19: Delhi | C19: 45531 | E19: Shreya Ghoshal | F19: =VLOOKUP(E19,'Missing Values & Outliers'!$O$10:$P$19,2,0) -> Local Artist | G19: Honey Singh, Mika Singh, Martin Garrix, Ed Sheeran | H19: 4564 | I19: 31755 | J19: =I19*H19 -> 144929820 | K19: 6890835 | L19: 4732974 | M19: 156553629 | N19: {=VLOOKUP(E19,[1]Artist_Popularity_Data!$A$2:$I$11,{1,2,3,4,5,6,7,8,9},0)} -> Shreya Ghoshal | O19: Classical/Bollywood | P19: 3326 | Q19: 3197 | R19: 23 | S19: 271 | T19: 792856 | U19: No | V19: Pune, Mumbai, Delhi, Bengaluru, Amritsar
A20: Sunburn Goa | B20: Nagpur | C20: 45634 | D20: Classics Tour | E20: Bryan Adams | F20: =VLOOKUP(E20,'Missing Values & Outliers'!$O$10:$P$19,2,0) -> International | G20: Ed Sheeran, Mika Singh, Shreya Ghoshal, Honey Singh | H20: 3350.2 | I20: 2975.7 | J20: =I20*H20 -> 9969190.1 | K20: 1041495 | L20: 3001940 | M20: 14216078 | N20: {=VLOOKUP(E20,[1]Artist_Popularity_Data!$A$2:$I$11,{1,2,3,4,5,6,7,8,9},0)} -> Bryan Adams | O20: Rock | P20: 992 | Q20: 21632.556 | R20: 30 | S20: 81 | T20: 8678356 | U20: Yes | V20: Delhi, Jaipur, Bengaluru, Mumbai
A21: Sunburn Goa | B21: Delhi | C21: 45460 | E21: Badshah | F21: =VLOOKUP(E21,'Missing Values & Outliers'!$O$10:$P$19,2,0) -> Local Artist | G21: Shreya Ghoshal, Diljit Dosanjh, Arijit Singh | H21: 4045 | I21: 27719 | J21: =I21*H21 -> 112123355 | K21: 7539568 | L21: 4670910 | M21: 124333833 | N21: {=VLOOKUP(E21,[1]Artist_Popularity_Data!$A$2:$I$11,{1,2,3,4,5,6,7,8,9},0)} -> Badshah | O21: Bollywood | P21: 3351 | Q21: 36448 | R21: 33 | S21: 483 | T21: 20228640 | U21: No | V21: Nagpur, Goa, Amritsar, Chandigarh, Mumbai
A22: Sunburn Goa | B22: Bengaluru | C22: 45425 | D22: Soulful Nights Tour | E22: Arijit Singh | F22: =VLOOKUP(E22,'Missing Values & Outliers'!$O$10:$P$19,2,0) -> Local Artist | G22: Honey Singh, Diljit Dosanjh, Badshah | H22: 1008 | I22: 21142 | J22: =I22*H22 -> 21311136 | K22: 2558182 | L22: 1632574 | M22: 25501892 | N22: {=VLOOKUP(E22,[1]Artist_Popularity_Data!$A$2:$I$11,{1,2,3,4,5,6,7,8,9},0)} -> Arijit Singh | O22: Bollywood | P22: 2437 | Q22: 25729 | R22: 30 | S22: 584 | T22: 18730712 | U22: Yes | V22: Nagpur, Jaipur, Chandigarh
A23: NH7 Pune | B23: Chandigarh | C23: 45474 | E23: Martin Garrix | F23: =VLOOKUP(E23,'Missing Values & Outliers'!$O$10:$P$19,2,0) -> International | G23: Honey Singh, Bryan Adams, DJ Snake | H23: 2334 | I23: 16842 | J23: =I23*H23 -> 39309228 | K23: 6905220 | L23: 1067015 | M23: 47281463 | N23: {=VLOOKUP(E23,[1]Artist_Popularity_Data!$A$2:$I$11,{1,2,3,4,5,6,7,8,9},0)} -> Martin Garrix | O23: EDM | P23: 2499 | Q23: 11603 | R23: 43 | S23: 298 | T23: 6462871 | U23: No | V23: Chandigarh, Delhi, Pune, Nagpur, Bengaluru, Kolkata
A24: Goa Tribal Festival | B24: Delhi | C24: 45299 | D24: Born To Shine Tour | E24: Diljit Dosanjh | F24: =VLOOKUP(E24,'Missing Values & Outliers'!$O$10:$P$19,2,0) -> Local Artist | G24: Ed Sheeran, Diljit Dosanjh, Shreya Ghoshal, Badshah | H24: 2910.2168 | I24: 14456 | J24: =I24*H24 -> 42070095 | K24: 4603680 | L24: 2403962 | M24: 41090442 | N24: {=VLOOKUP(E24,[1]Artist_Popularity_Data!$A$2:$I$11,{1,2,3,4,5,6,7,8,9},0)} -> Diljit Dosanjh | O24: Punjabi | P24: 2027 | Q24: 33738 | R24: 46 | S24: 116 | T24: 22334556 | U24: Yes | V24: Amritsar, Kolkata, Delhi, Mumbai, Bengaluru
A25: Magnetic Fields Rajasthan | B25: Amritsar | C25: 45416 | E25: Badshah | F25: =VLOOKUP(E25,'Missing Values & Outliers'!$O$10:$P$19,2,0) -> Local Artist | G25: Mika Singh, Diljit Dosanjh, Martin Garrix | H25: 3977 | I25: 25243 | J25: =I25*H25 -> 100391411 | K25: 9238938 | L25: 4689343 | M25: 114319692 | N25: {=VLOOKUP(E25,[1]Artist_Popularity_Data!$A$2:$I$11,{1,2,3,4,5,6,7,8,9},0)} -> Badshah | O25: Bollywood | P25: 3351 | Q25: 36448 | R25: 33 | S25: 483 | T25: 20228640 | U25: No | V25: Nagpur, Goa, Amritsar, Chandigarh, Mumbai
A26: Sunburn Goa | B26: Jaipur | C26: 45407 | E26: Honey Singh | F26: =VLOOKUP(E26,'Missing Values & Outliers'!$O$10:$P$19,2,0) -> Local Artist | G26: Bryan Adams, Diljit Dosanjh, Honey Singh, Mika Singh | H26: 3449 | I26: 13539 | J26: =I26*H26 -> 46696011 | K26: 5672841 | L26: 3471436 | M26: 55840288 | N26: {=VLOOKUP(E26,[1]Artist_Popularity_Data!$A$2:$I$11,{1,2,3,4,5,6,7,8,9},0)} -> Honey Singh | O26: Hip-Hop | P26: 1573 | Q26: 35223 | R26: 34 | S26: 430 | T26: 25360560 | U26: No | V26: Pune, Amritsar, Bengaluru
A27: Hornbill Festival Nagaland | B27: Pune | C27: 45316 | E27: Badshah | F27: =VLOOKUP(E27,'Missing Values & Outliers'!$O$10:$P$19,2,0) -> Local Artist | G27: Martin Garrix, Bryan Adams, DJ Snake | H27: 3668 | I27: 36462 | J27: =I27*H27 -> 133742616 | K27: 5250528 | L27: 2377592 | M27: 141370736 | N27: {=VLOOKUP(E27,[1]Artist_Popularity_Data!$A$2:$I$11,{1,2,3,4,5,6,7,8,9},0)} -> Badshah | O27: Bollywood | P27: 3351 | Q27: 36448 | R27: 33 | S27: 483 | T27: 20228640 | U27: No | V27: Nagpur, Goa, Amritsar, Chandigarh, Mumbai
A28: NH7 Pune | B28: Goa | C28: 45539 | E28: Badshah | F28: =VLOOKUP(E28,'Missing Values & Outliers'!$O$10:$P$19,2,0) -> Local Artist | G28: Arijit Singh, Diljit Dosanjh | H28: 3279 | I28: 32540 | J28: =I28*H28 -> 106698660 | K28: 13341400 | L28: 2840750 | M28: 122880810 | N28: {=VLOOKUP(E28,[1]Artist_Popularity_Data!$A$2:$I$11,{1,2,3,4,5,6,7,8,9},0)} -> Badshah | O28: Bollywood | P28: 3351 | Q28: 36448 | R28: 33 | S28: 483 | T28: 20228640 | U28: No | V28: Nagpur, Goa, Amritsar, Chandigarh, Mumbai
A29: NH7 Pune | B29: Amritsar | C29: 45639 | E29: Honey Singh | F29: =VLOOKUP(E29,'Missing Values & Outliers'!$O$10:$P$19,2,0) -> Local Artist | G29: Diljit Dosanjh, Honey Singh, DJ Snake, Shreya Ghoshal | H29: 2948 | I29: 9316 | J29: =I29*H29 -> 27463568 | K29: 1266976 | L29: 2704822 | M29: 31435366 | N29: {=VLOOKUP(E29,[1]Artist_Popularity_Data!$A$2:$I$11,{1,2,3,4,5,6,7,8,9},0)} -> Honey Singh | O29: Hip-Hop | P29: 1573 | Q29: 35223 | R29: 34 | S29: 430 | T29: 25360560 | U29: No | V29: Pune, Amritsar, Bengaluru
A30: NH7 Pune | B30: Delhi | C30: 45647 | E30: DJ Snake | F30: =VLOOKUP(E30,'Missing Values & Outliers'!$O$10:$P$19,2,0) -> International | G30: Bryan Adams, Mika Singh, Arijit Singh | H30: 2749.6 | I30: 17172 | J30: =I30*H30 -> 47216131 | K30: 7830432 | L30: 3956927 | M30: 45513167 | N30: {=VLOOKUP(E30,[1]Artist_Popularity_Data!$A$2:$I$11,{1,2,3,4,5,6,7,8,9},0)} -> DJ Snake | O30: EDM | P30: 1431 | Q30: 19089 | R30: 32 | S30: 429 | T30: 10193526 | U30: No | V30: Bengaluru, Jaipur, Mumbai, Chandigarh, Kolkata, Delhi
A31: Ziro Festival Arunachal | B31: Bengaluru | C31: 45410 | E31: Honey Singh | F31: =VLOOKUP(E31,'Missing Values & Outliers'!$O$10:$P$19,2,0) -> Local Artist | G31: Arijit Singh, Honey Singh | H31: 2910.2168 | I31: 16737 | J31: =I31*H31 -> 48708299 | K31: 6276375 | L31: 2726932 | M31: 85424449 | N31: {=VLOOKUP(E31,[1]Artist_Popularity_Data!$A$2:$I$11,{1,2,3,4,5,6,7,8,9},0)} -> Honey Singh | O31: Hip-Hop | P31: 1573 | Q31: 35223 | R31: 34 | S31: 430 | T31: 25360560 | U31: No | V31: Pune, Amritsar, Bengaluru
A32: NH7 Pune | B32: Chandigarh | C32: 45392 | E32: Shreya Ghoshal | F32: =VLOOKUP(E32,'Missing Values & Outliers'!$O$10:$P$19,2,0) -> Local Artist | G32: Martin Garrix, Diljit Dosanjh, Badshah, Mika Singh | H32: 632 | I32: 35304 | J32: =I32*H32 -> 22312128 | K32: 10379376 | L32: 1590737 | M32: 34282241 | N32: {=VLOOKUP(E32,[1]Artist_Popularity_Data!$A$2:$I$11,{1,2,3,4,5,6,7,8,9},0)} -> Shreya Ghoshal | O32: Classical/Bollywood | P32: 3326 | Q32: 3197 | R32: 23 | S32: 271 | T32: 792856 | U32: No | V32: Pune, Mumbai, Delhi, Bengaluru, Amritsar
A33: Goa Tribal Festival | B33: Kolkata | C33: 45360 | E33: Honey Singh | F33: =VLOOKUP(E33,'Missing Values & Outliers'!$O$10:$P$19,2,0) -> Local Artist | G33: DJ Snake, Arijit Singh, Badshah, Mika Singh | H33: 1932 | I33: 16841 | J33: =I33*H33 -> 32536812 | K33: 7713178 | L33: 4738764 | M33: 44988754 | N33: {=VLOOKUP(E33,[1]Artist_Popularity_Data!$A$2:$I$11,{1,2,3,4,5,6,7,8,9},0)} -> Honey Singh | O33: Hip-Hop | P33: 1573 | Q33: 35223 | R33: 34 | S33: 430 | T33: 25360560 | U33: No | V33: Pune, Amritsar, Bengaluru
A34: Ziro Festival Arunachal | B34: Goa | C34: 45358 | D34: Classics Tour | E34: Bryan Adams | F34: =VLOOKUP(E34,'Missing Values & Outliers'!$O$10:$P$19,2,0) -> International | G34: Mika Singh, Diljit Dosanjh, Shreya Ghoshal | H34: 1598.8 | I34: 18210.5 | J34: =I34*H34 -> 29114947 | K34: 7336230 | L34: 2229062 | M34: 39274422 | N34: {=VLOOKUP(E34,[1]Artist_Popularity_Data!$A$2:$I$11,{1,2,3,4,5,6,7,8,9},0)} -> Bryan Adams | O34: Rock | P34: 992 | Q34: 21632.556 | R34: 30 | S34: 81 | T34: 8678356 | U34: Yes | V34: Delhi, Jaipur, Bengaluru, Mumbai
A35: Lollapalooza Mumbai | B35: Bengaluru | C35: 45395 | D35: Born To Shine Tour | E35: Diljit Dosanjh | F35: =VLOOKUP(E35,'Missing Values & Outliers'!$O$10:$P$19,2,0) -> Local Artist | G35: Diljit Dosanjh, DJ Snake, Honey Singh, Shreya Ghoshal | H35: 2910.2168 | I35: 7559.5 | J35: =I35*H35 -> 21999784 | K35: 1913135 | L35: 4680189 | M35: 21654174 | N35: {=VLOOKUP(E35,[1]Artist_Popularity_Data!$A$2:$I$11,{1,2,3,4,5,6,7,8,9},0)} -> Diljit Dosanjh | O35: Punjabi | P35: 2027 | Q35: 33738 | R35: 46 | S35: 116 | T35: 22334556 | U35: Yes | V35: Amritsar, Kolkata, Delhi, Mumbai, Bengaluru
A36: VH1 Supersonic Delhi | B36: Bengaluru | C36: 45509 | E36: Martin Garrix | F36: =VLOOKUP(E36,'Missing Values & Outliers'!$O$10:$P$19,2,0) -> International | G36: DJ Snake, Honey Singh, Diljit Dosanjh | H36: 4452 | I36: 31745 | J36: =I36*H36 -> 141328740 | K36: 4412555 | L36: 4091720 | M36: 149833015 | N36: {=VLOOKUP(E36,[1]Artist_Popularity_Data!$A$2:$I$11,{1,2,3,4,5,6,7,8,9},0)} -> Martin Garrix | O36: EDM | P36: 2499 | Q36: 11603 | R36: 43 | S36: 298 | T36: 6462871 | U36: No | V36: Chandigarh, Delhi, Pune, Nagpur, Bengaluru, Kolkata
A37: Bollywood Music Project | B37: Mumbai | C37: 45555 | E37: Mika Singh | F37: =VLOOKUP(E37,'Missing Values & Outliers'!$O$10:$P$19,2,0) -> Local Artist | G37: Arijit Singh, DJ Snake, Martin Garrix | H37: 2716 | I37: 12688 | J37: =I37*H37 -> 34460608 | K37: 2486848 | L37: 1413822 | M37: 38361278 | N37: {=VLOOKUP(E37,[1]Artist_Popularity_Data!$A$2:$I$11,{1,2,3,4,5,6,7,8,9},0)} -> Mika Singh | O37: Bollywood | P37: 1025 | Q37: 11057 | R37: 12 | S37: 371 | T37: 7983154 | U37: No | V37: Delhi, Amritsar, Bengaluru, Mumbai
A38: Sunburn Goa | B38: Chandigarh | C38: 45507 | E38: Mika Singh | F38: =VLOOKUP(E38,'Missing Values & Outliers'!$O$10:$P$19,2,0) -> Local Artist | G38: DJ Snake, Badshah | H38: 2237 | I38: 20276 | J38: =I38*H38 -> 45357412 | K38: 9671652 | L38: 4912334 | M38: 59941398 | N38: {=VLOOKUP(E38,[1]Artist_Popularity_Data!$A$2:$I$11,{1,2,3,4,5,6,7,8,9},0)} -> Mika Singh | O38: Bollywood | P38: 1025 | Q38: 11057 | R38: 12 | S38: 371 | T38: 7983154 | U38: No | V38: Delhi, Amritsar, Bengaluru, Mumbai
A39: Bollywood Music Project | B39: Nagpur | C39: 45468 | E39: Badshah | F39: =VLOOKUP(E39,'Missing Values & Outliers'!$O$10:$P$19,2,0) -> Local Artist | G39: DJ Snake, Honey Singh, Diljit Dosanjh | H39: 1412 | I39: 20798.88 | J39: =I39*H39 -> 29368019 | K39: 12753000 | L39: 663225 | M39: 61435521 | N39: {=VLOOKUP(E39,[1]Artist_Popularity_Data!$A$2:$I$11,{1,2,3,4,5,6,7,8,9},0)} -> Badshah | O39: Bollywood | P39: 3351 | Q39: 36448 | R39: 33 | S39: 483 | T39: 20228640 | U39: No | V39: Nagpur, Goa, Amritsar, Chandigarh, Mumbai
A40: Bollywood Music Project | B40: Goa | C40: 45654 | D40: Born To Shine Tour | E40: Diljit Dosanjh | F40: =VLOOKUP(E40,'Missing Values & Outliers'!$O$10:$P$19,2,0) -> Local Artist | G40: Diljit Dosanjh, Shreya Ghoshal, Ed Sheeran | H40: 836 | I40: 56160 | J40: =I40*H40 -> 46949760 | K40: 14904000 | L40: 4753926 | M40: 55773126 | N40: {=VLOOKUP(E40,[1]Artist_Popularity_Data!$A$2:$I$11,{1,2,3,4,5,6,7,8,9},0)} -> Diljit Dosanjh | O40: Punjabi | P40: 2027 | Q40: 33738 | R40: 46 | S40: 116 | T40: 22334556 | U40: Yes | V40: Amritsar, Kolkata, Delhi, Mumbai, Bengaluru
A41: Bollywood Music Project | B41: Chandigarh | C41: 45527 | D41: Born To Shine Tour | E41: Diljit Dosanjh | F41: =VLOOKUP(E41,'Missing Values & Outliers'!$O$10:$P$19,2,0) -> Local Artist | G41: Bryan Adams, DJ Snake, Mika Singh, Shreya Ghoshal | H41: 625 | I41: 34043.1 | J41: =I41*H41 -> 21276938 | K41: 11705589 | L41: 2483828 | M41: 30556292 | N41: {=VLOOKUP(E41,[1]Artist_Popularity_Data!$A$2:$I$11,{1,2,3,4,5,6,7,8,9},0)} -> Diljit Dosanjh | O41: Punjabi | P41: 2027 | Q41: 33738 | R41: 46 | S41: 116 | T41: 22334556 | U41: Yes | V41: Amritsar, Kolkata, Delhi, Mumbai, Bengaluru
A42: Lollapalooza Mumbai | B42: Kolkata | C42: 45555 | E42: Badshah | F42: =VLOOKUP(E42,'Missing Values & Outliers'!$O$10:$P$19,2,0) -> Local Artist | G42: Mika Singh, Arijit Singh, Ed Sheeran | H42: 4629 | I42: 34318 | J42: =I42*H42 -> 158858022 | K42: 5113382 | L42: 3030898 | M42: 167002302 | N42: {=VLOOKUP(E42,[1]Artist_Popularity_Data!$A$2:$I$11,{1,2,3,4,5,6,7,8,9},0)} -> Badshah | O42: Bollywood | P42: 3351 | Q42: 36448 | R42: 33 | S42: 483 | T42: 20228640 | U42: No | V42: Nagpur, Goa, Amritsar, Chandigarh, Mumbai
A43: Lollapalooza Mumbai | B43: Chandigarh | C43: 45524 | E43: Mika Singh | F43: =VLOOKUP(E43,'Missing Values & Outliers'!$O$10:$P$19,2,0) -> Local Artist | G43: Shreya Ghoshal, Badshah, Arijit Singh, Bryan Adams | H43: 3412 | I43: 22029 | J43: =I43*H43 -> 75162948 | K43: 7401744 | L43: 4420985 | M43: 86985677 | N43: {=VLOOKUP(E43,[1]Artist_Popularity_Data!$A$2:$I$11,{1,2,3,4,5,6,7,8,9},0)} -> Mika Singh | O43: Bollywood | P43: 1025 | Q43: 11057 | R43: 12 | S43: 371 | T43: 7983154 | U43: No | V43: Delhi, Amritsar, Bengaluru, Mumbai
A44: Ziro Festival Arunachal | B44: Mumbai | C44: 45512 | D44: Born To Shine Tour | E44: Diljit Dosanjh | F44: =VLOOKUP(E44,'Missing Values & Outliers'!$O$10:$P$19,2,0) -> Local Artist | G44: Badshah, DJ Snake, Honey Singh, Mika Singh | H44: 737 | I44: 28345.2 | J44: =I44*H44 -> 20890412 | K44: 3292404 | L44: 4566892 | M44: 23928844 | N44: {=VLOOKUP(E44,[1]Artist_Popularity_Data!$A$2:$I$11,{1,2,3,4,5,6,7,8,9},0)} -> Diljit Dosanjh | O44: Punjabi | P44: 2027 | Q44: 33738 | R44: 46 | S44: 116 | T44: 22334556 | U44: Yes | V44: Amritsar, Kolkata, Delhi, Mumbai, Bengaluru
A45: Sunburn Goa | B45: Goa | C45: 45654 | E45: Mika Singh | F45: =VLOOKUP(E45,'Missing Values & Outliers'!$O$10:$P$19,2,0) -> Local Artist | G45: Honey Singh, Shreya Ghoshal | H45: 933 | I45: 31752 | J45: =I45*H45 -> 29624616 | K45: 5366088 | L45: 1334941 | M45: 36325645 | N45: {=VLOOKUP(E45,[1]Artist_Popularity_Data!$A$2:$I$11,{1,2,3,4,5,6,7,8,9},0)} -> Mika Singh | O45: Bollywood | P45: 1025 | Q45: 11057 | R45: 12 | S45: 371 | T45: 7983154 | U45: No | V45: Delhi, Amritsar, Bengaluru, Mumbai
A46: Ziro Festival Arunachal | B46: Bengaluru | C46: 45467 | D46: Soulful Nights Tour | E46: Arijit Singh | F46: =VLOOKUP(E46,'Missing Values & Outliers'!$O$10:$P$19,2,0) -> Local Artist | G46: Ed Sheeran, Arijit Singh, Badshah | H46: 4503 | I46: 7651 | J46: =I46*H46 -> 34452453 | K46: 1361878 | L46: 2805968 | M46: 38620299 | N46: {=VLOOKUP(E46,[1]Artist_Popularity_Data!$A$2:$I$11,{1,2,3,4,5,6,7,8,9},0)} -> Arijit Singh | O46: Bollywood | P46: 2437 | Q46: 25729 | R46: 30 | S46: 584 | T46: 18730712 | U46: Yes | V46: Nagpur, Jaipur, Chandigarh
A47: Supersonic Bengaluru | B47: Chandigarh | C47: 45423 | D47: Mathematics Tour | E47: Ed Sheeran | F47: =VLOOKUP(E47,'Missing Values & Outliers'!$O$10:$P$19,2,0) -> International | G47: DJ Snake, Mika Singh | H47: 2615.2 | I47: 6000 | J47: =I47*H47 -> 15691200 | K47: 2094000 | L47: 3409793 | M47: 16711793 | N47: {=VLOOKUP(E47,[1]Artist_Popularity_Data!$A$2:$I$11,{1,2,3,4,5,6,7,8,9},0)} -> Ed Sheeran | O47: International Pop | P47: 3436 | Q47: 18609 | R47: 55 | S47: 736 | T47: 4856949 | U47: Yes | V47: Pune, Amritsar, Goa, Chandigarh
A48: Supersonic Bengaluru | B48: Jaipur | C48: 45386 | D48: Born To Shine Tour | E48: Diljit Dosanjh | F48: =VLOOKUP(E48,'Missing Values & Outliers'!$O$10:$P$19,2,0) -> Local Artist | G48: Mika Singh, Ed Sheeran | H48: 4046 | I48: 32925.1 | J48: =I48*H48 -> 1.3321495e+08 | K48: 4356244 | L48: 1785594 | M48: 108614880 | N48: {=VLOOKUP(E48,[1]Artist_Popularity_Data!$A$2:$I$11,{1,2,3,4,5,6,7,8,9},0)} -> Diljit Dosanjh | O48: Punjabi | P48: 2027 | Q48: 33738 | R48: 46 | S48: 116 | T48: 22334556 | U48: Yes | V48: Amritsar, Kolkata, Delhi, Mumbai, Bengaluru
A49: VH1 Supersonic Delhi | B49: Nagpur | C49: 45318 | D49: Classics Tour | E49: Bryan Adams | F49: =VLOOKUP(E49,'Missing Values & Outliers'!$O$10:$P$19,2,0) -> International | G49: Mika Singh, Badshah | H49: 4613 | I49: 9412.2 | J49: =I49*H49 -> 43418479 | K49: 5580090 | L49: 4314798 | M49: 54199458 | N49: {=VLOOKUP(E49,[1]Artist_Popularity_Data!$A$2:$I$11,{1,2,3,4,5,6,7,8,9},0)} -> Bryan Adams | O49: Rock | P49: 992 | Q49: 21632.556 | R49: 30 | S49: 81 | T49: 8678356 | U49: Yes | V49: Delhi, Jaipur, Bengaluru, Mumbai
A50: VH1 Supersonic Delhi | B50: Goa | C50: 45499 | D50: Soulful Nights Tour | E50: Arijit Singh | F50: =VLOOKUP(E50,'Missing Values & Outliers'!$O$10:$P$19,2,0) -> Local Artist | G50: Ed Sheeran, DJ Snake, Mika Singh | H50: 3437 | I50: 17457 | J50: =I50*H50 -> 59999709 | K50: 4800675 | L50: 3816903 | M50: 68617287 | N50: {=VLOOKUP(E50,[1]Artist_Popularity_Data!$A$2:$I$11,{1,2,3,4,5,6,7,8,9},0)} -> Arijit Singh | O50: Bollywood | P50: 2437 | Q50: 25729 | R50: 30 | S50: 584 | T50: 18730712 | U50: Yes | V50: Nagpur, Jaipur, Chandigarh
A51: Supersonic Bengaluru | B51: Jaipur | C51: 45543 | E51: Martin Garrix | F51: =VLOOKUP(E51,'Missing Values & Outliers'!$O$10:$P$19,2,0) -> International | G51: Martin Garrix, Badshah | H51: 2167 | I51: 23456 | J51: =I51*H51 -> 50829152 | K51: 8068864 | L51: 4892379 | M51: 63790395 | N51: {=VLOOKUP(E51,[1]Artist_Popularity_Data!$A$2:$I$11,{1,2,3,4,5,6,7,8,9},0)} -> Martin Garrix | O51: EDM | P51: 2499 | Q51: 11603 | R51: 43 | S51: 298 | T51: 6462871 | U51: No | V51: Chandigarh, Delhi, Pune, Nagpur, Bengaluru, Kolkata
A52: Ziro Festival Arunachal | B52: Nagpur | C52: 45635 | E52: Honey Singh | F52: =VLOOKUP(E52,'Missing Values & Outliers'!$O$10:$P$19,2,0) -> Local Artist | G52: Arijit Singh, Honey Singh, Shreya Ghoshal, Ed Sheeran | H52: 2495 | I52: 26922 | J52: =I52*H52 -> 67170390 | K52: 12868716 | L52: 4865146 | M52: 339617008 | N52: {=VLOOKUP(E52,[1]Artist_Popularity_Data!$A$2:$I$11,{1,2,3,4,5,6,7,8,9},0)} -> Honey Singh | O52: Hip-Hop | P52: 1573 | Q52: 35223 | R52: 34 | S52: 430 | T52: 25360560 | U52: No | V52: Pune, Amritsar, Bengaluru
A53: Magnetic Fields Rajasthan | B53: Nagpur | C53: 45304 | D53: Classics Tour | E53: Bryan Adams | F53: =VLOOKUP(E53,'Missing Values & Outliers'!$O$10:$P$19,2,0) -> International | G53: Arijit Singh, Diljit Dosanjh | H53: 1244.6 | I53: 23400.3 | J53: =I53*H53 -> 29124013 | K53: 10463277 | L53: 1325646 | M53: 41507304 | N53: {=VLOOKUP(E53,[1]Artist_Popularity_Data!$A$2:$I$11,{1,2,3,4,5,6,7,8,9},0)} -> Bryan Adams | O53: Rock | P53: 992 | Q53: 21632.556 | R53: 30 | S53: 81 | T53: 8678356 | U53: Yes | V53: Delhi, Jaipur, Bengaluru, Mumbai
A54: Sunburn Goa | B54: Pune | C54: 45509 | E54: Shreya Ghoshal | F54: =VLOOKUP(E54,'Missing Values & Outliers'!$O$10:$P$19,2,0) -> Local Artist | G54: DJ Snake, Shreya Ghoshal, Honey Singh, Diljit Dosanjh | H54: 4120 | I54: 20798.88 | J54: =I54*H54 -> 85691386 | K54: 4873518 | L54: 2422363 | M54: 93103121 | N54: {=VLOOKUP(E54,[1]Artist_Popularity_Data!$A$2:$I$11,{1,2,3,4,5,6,7,8,9},0)} -> Shreya Ghoshal | O54: Classical/Bollywood | P54: 3326 | Q54: 3197 | R54: 23 | S54: 271 | T54: 792856 | U54: No | V54: Pune, Mumbai, Delhi, Bengaluru, Amritsar
A55: Magnetic Fields Rajasthan | B55: Goa | C55: 45448 | E55: Shreya Ghoshal | F55: =VLOOKUP(E55,'Missing Values & Outliers'!$O$10:$P$19,2,0) -> Local Artist | G55: Martin Garrix, Badshah, Bryan Adams, Arijit Singh | H55: 2910.2168 | I55: 20798.88 | J55: =I55*H55 -> 60529251 | K55: 4728492 | L55: 3476973 | M55: 15717666 | N55: {=VLOOKUP(E55,[1]Artist_Popularity_Data!$A$2:$I$11,{1,2,3,4,5,6,7,8,9},0)} -> Shreya Ghoshal | O55: Classical/Bollywood | P55: 3326 | Q55: 3197 | R55: 23 | S55: 271 | T55: 792856 | U55: No | V55: Pune, Mumbai, Delhi, Bengaluru, Amritsar
A56: Goa Tribal Festival | B56: Amritsar | C56: 45326 | D56: Classics Tour | E56: Bryan Adams | F56: =VLOOKUP(E56,'Missing Values & Outliers'!$O$10:$P$19,2,0) -> International | G56: Diljit Dosanjh, Ed Sheeran, DJ Snake, Honey Singh | H56: 4459 | I56: 19021.1 | J56: =I56*H56 -> 84815085 | K56: 9592069 | L56: 3713395 | M56: 99851469 | N56: {=VLOOKUP(E56,[1]Artist_Popularity_Data!$A$2:$I$11,{1,2,3,4,5,6,7,8,9},0)} -> Bryan Adams | O56: Rock | P56: 992 | Q56: 21632.556 | R56: 30 | S56: 81 | T56: 8678356 | U56: Yes | V56: Delhi, Jaipur, Bengaluru, Mumbai
A57: Ziro Festival Arunachal | B57: Jaipur | C57: 45431 | E57: Shreya Ghoshal | F57: =VLOOKUP(E57,'Missing Values & Outliers'!$O$10:$P$19,2,0) -> Local Artist | G57: Honey Singh, Ed Sheeran | H57: 2910.2168 | I57: 31020 | J57: =I57*H57 -> 90274926 | K57: 10701900 | L57: 854727 | M57: 122856387 | N57: {=VLOOKUP(E57,[1]Artist_Popularity_Data!$A$2:$I$11,{1,2,3,4,5,6,7,8,9},0)} -> Shreya Ghoshal | O57: Classical/Bollywood | P57: 3326 | Q57: 3197 | R57: 23 | S57: 271 | T57: 792856 | U57: No | V57: Pune, Mumbai, Delhi, Bengaluru, Amritsar
A58: Bollywood Music Project | B58: Jaipur | C58: 45583 | E58: Mika Singh | F58: =VLOOKUP(E58,'Missing Values & Outliers'!$O$10:$P$19,2,0) -> Local Artist | G58: DJ Snake, Arijit Singh, Shreya Ghoshal | H58: 2910.2168 | I58: 5456 | J58: =I58*H58 -> 15878143 | K58: 1085744 | L58: 3936852 | M58: 19235476 | N58: {=VLOOKUP(E58,[1]Artist_Popularity_Data!$A$2:$I$11,{1,2,3,4,5,6,7,8,9},0)} -> Mika Singh | O58: Bollywood | P58: 1025 | Q58: 11057 | R58: 12 | S58: 371 | T58: 7983154 | U58: No | V58: Delhi, Amritsar, Bengaluru, Mumbai
A59: Bollywood Music Project | B59: Goa | C59: 45486 | E59: DJ Snake | F59: =VLOOKUP(E59,'Missing Values & Outliers'!$O$10:$P$19,2,0) -> International | G59: Bryan Adams, Martin Garrix | H59: 5391.4 | I59: 11355 | J59: =I59*H59 -> 61219347 | K59: 2305065 | L59: 1958821 | M59: 191967964 | N59: {=VLOOKUP(E59,[1]Artist_Popularity_Data!$A$2:$I$11,{1,2,3,4,5,6,7,8,9},0)} -> DJ Snake | O59: EDM | P59: 1431 | Q59: 19089 | R59: 32 | S59: 429 | T59: 10193526 | U59: No | V59: Bengaluru, Jaipur, Mumbai, Chandigarh, Kolkata, Delhi
A60: Sunburn Goa | B60: Delhi | C60: 45457 | D60: Soulful Nights Tour | E60: Arijit Singh | F60: =VLOOKUP(E60,'Missing Values & Outliers'!$O$10:$P$19,2,0) -> Local Artist | G60: Martin Garrix, DJ Snake, Arijit Singh, Honey Singh | H60: 2910.2168 | I60: 20798.88 | J60: =I60*H60 -> 60529251 | K60: 3236079 | L60: 3039149 | M60: 24290802 | N60: {=VLOOKUP(E60,[1]Artist_Popularity_Data!$A$2:$I$11,{1,2,3,4,5,6,7,8,9},0)} -> Arijit Singh | O60: Bollywood | P60: 2437 | Q60: 25729 | R60: 30 | S60: 584 | T60: 18730712 | U60: Yes | V60: Nagpur, Jaipur, Chandigarh
A61: Magnetic Fields Rajasthan | B61: Kolkata | C61: 45370 | E61: Badshah | F61: =VLOOKUP(E61,'Missing Values & Outliers'!$O$10:$P$19,2,0) -> Local Artist | G61: Diljit Dosanjh, Arijit Singh, Shreya Ghoshal, Mika Singh | H61: 2589 | I61: 8270 | J61: =I61*H61 -> 21411030 | K61: 1563030 | L61: 3564057 | M61: 106152468 | N61: {=VLOOKUP(E61,[1]Artist_Popularity_Data!$A$2:$I$11,{1,2,3,4,5,6,7,8,9},0)} -> Badshah | O61: Bollywood | P61: 3351 | Q61: 36448 | R61: 33 | S61: 483 | T61: 20228640 | U61: No | V61: Nagpur, Goa, Amritsar, Chandigarh, Mumbai
A62: Bollywood Music Project | B62: Goa | C62: 45420 | E62: Honey Singh | F62: =VLOOKUP(E62,'Missing Values & Outliers'!$O$10:$P$19,2,0) -> Local Artist | G62: Shreya Ghoshal, DJ Snake, Honey Singh, Bryan Adams | H62: 4078 | I62: 9560 | J62: =I62*H62 -> 38985680 | K62: 3795320 | L62: 2303574 | M62: 45084574 | N62: {=VLOOKUP(E62,[1]Artist_Popularity_Data!$A$2:$I$11,{1,2,3,4,5,6,7,8,9},0)} -> Honey Singh | O62: Hip-Hop | P62: 1573 | Q62: 35223 | R62: 34 | S62: 430 | T62: 25360560 | U62: No | V62: Pune, Amritsar, Bengaluru
A63: Goa Tribal Festival | B63: Goa | C63: 45368 | D63: Soulful Nights Tour | E63: Arijit Singh | F63: =VLOOKUP(E63,'Missing Values & Outliers'!$O$10:$P$19,2,0) -> Local Artist | G63: Ed Sheeran, Honey Singh, Arijit Singh | H63: 1381 | I63: 13578 | J63: =I63*H63 -> 18751218 | K63: 5336154 | L63: 1442642 | M63: 25530014 | N63: {=VLOOKUP(E63,[1]Artist_Popularity_Data!$A$2:$I$11,{1,2,3,4,5,6,7,8,9},0)} -> Arijit Singh | O63: Bollywood | P63: 2437 | Q63: 25729 | R63: 30 | S63: 584 | T63: 18730712 | U63: Yes | V63: Nagpur, Jaipur, Chandigarh
A64: VH1 Supersonic Delhi | B64: Chandigarh | C64: 45506 | E64: Honey Singh | F64: =VLOOKUP(E64,'Missing Values & Outliers'!$O$10:$P$19,2,0) -> Local Artist | G64: Arijit Singh, Badshah | H64: 2817 | I64: 13994 | J64: =I64*H64 -> 39421098 | K64: 6689132 | L64: 3519113 | M64: 49629343 | N64: {=VLOOKUP(E64,[1]Artist_Popularity_Data!$A$2:$I$11,{1,2,3,4,5,6,7,8,9},0)} -> Honey Singh | O64: Hip-Hop | P64: 1573 | Q64: 35223 | R64: 34 | S64: 430 | T64: 25360560 | U64: No | V64: Pune, Amritsar, Bengaluru
A65: Goa Tribal Festival | B65: Bengaluru | C65: 45317 | E65: Badshah | F65: =VLOOKUP(E65,'Missing Values & Outliers'!$O$10:$P$19,2,0) -> Local Artist | G65: Bryan Adams, Honey Singh, Mika Singh | H65: 2937 | I65: 14499 | J65: =I65*H65 -> 42583563 | K65: 7177005 | L65: 1341541 | M65: 51102109 | N65: {=VLOOKUP(E65,[1]Artist_Popularity_Data!$A$2:$I$11,{1,2,3,4,5,6,7,8,9},0)} -> Badshah | O65: Bollywood | P65: 3351 | Q65: 36448 | R65: 33 | S65: 483 | T65: 20228640 | U65: No | V65: Nagpur, Goa, Amritsar, Chandigarh, Mumbai
A66: Sunburn Goa | B66: Nagpur | C66: 45568 | E66: DJ Snake | F66: =VLOOKUP(E66,'Missing Values & Outliers'!$O$10:$P$19,2,0) -> International | G66: Ed Sheeran, Honey Singh, Badshah, Mika Singh | H66: 3235.4 | I66: 15002 | J66: =I66*H66 -> 48537471 | K66: 3975530 | L66: 4947667 | M66: 43592819 | N66: {=VLOOKUP(E66,[1]Artist_Popularity_Data!$A$2:$I$11,{1,2,3,4,5,6,7,8,9},0)} -> DJ Snake | O66: EDM | P66: 1431 | Q66: 19089 | R66: 32 | S66: 429 | T66: 10193526 | U66: No | V66: Bengaluru, Jaipur, Mumbai, Chandigarh, Kolkata, Delhi
A67: NH7 Pune | B67: Goa | C67: 45339 | E67: DJ Snake | F67: =VLOOKUP(E67,'Missing Values & Outliers'!$O$10:$P$19,2,0) -> International | G67: Ed Sheeran, Badshah, Arijit Singh, Bryan Adams | H67: 2224.6 | I67: 23169 | J67: =I67*H67 -> 51541757 | K67: 5630067 | L67: 4471729 | M67: 46917337 | N67: {=VLOOKUP(E67,[1]Artist_Popularity_Data!$A$2:$I$11,{1,2,3,4,5,6,7,8,9},0)} -> DJ Snake | O67: EDM | P67: 1431 | Q67: 19089 | R67: 32 | S67: 429 | T67: 10193526 | U67: No | V67: Bengaluru, Jaipur, Mumbai, Chandigarh, Kolkata, Delhi
A68: Supersonic Bengaluru | B68: Nagpur | C68: 45616 | E68: DJ Snake | F68: =VLOOKUP(E68,'Missing Values & Outliers'!$O$10:$P$19,2,0) -> International | G68: Martin Garrix, Honey Singh, DJ Snake, Arijit Singh | H68: 2679.6 | I68: 20798.88 | J68: =I68*H68 -> 55732679 | K68: 1370391 | L68: 1953924 | M68: 23346669 | N68: {=VLOOKUP(E68,[1]Artist_Popularity_Data!$A$2:$I$11,{1,2,3,4,5,6,7,8,9},0)} -> DJ Snake | O68: EDM | P68: 1431 | Q68: 19089 | R68: 32 | S68: 429 | T68: 10193526 | U68: No | V68: Bengaluru, Jaipur, Mumbai, Chandigarh, Kolkata, Delhi
A69: Magnetic Fields Rajasthan | B69: Pune | C69: 45345 | E69: Mika Singh | F69: =VLOOKUP(E69,'Missing Values & Outliers'!$O$10:$P$19,2,0) -> Local Artist | G69: Mika Singh, DJ Snake, Bryan Adams, Ed Sheeran | H69: 2567 | I69: 4240 | J69: =I69*H69 -> 10884080 | K69: 1861360 | L69: 1698282 | M69: 14443722 | N69: {=VLOOKUP(E69,[1]Artist_Popularity_Data!$A$2:$I$11,{1,2,3,4,5,6,7,8,9},0)} -> Mika Singh | O69: Bollywood | P69: 1025 | Q69: 11057 | R69: 12 | S69: 371 | T69: 7983154 | U69: No | V69: Delhi, Amritsar, Bengaluru, Mumbai
A70: Hornbill Festival Nagaland | B70: Delhi | C70: 45543 | D70: Classics Tour | E70: Bryan Adams | F70: =VLOOKUP(E70,'Missing Values & Outliers'!$O$10:$P$19,2,0) -> International | G70: Honey Singh, Shreya Ghoshal | H70: 6972 | I70: 21681.1 | J70: =I70*H70 -> 1.5116063e+08 | K70: 13875904 | L70: 2510128 | M70: 170631572 | N70: {=VLOOKUP(E70,[1]Artist_Popularity_Data!$A$2:$I$11,{1,2,3,4,5,6,7,8,9},0)} -> Bryan Adams | O70: Rock | P70: 992 | Q70: 21632.556 | R70: 30 | S70: 81 | T70: 8678356 | U70: Yes | V70: Delhi, Jaipur, Bengaluru, Mumbai
A71: Hornbill Festival Nagaland | B71: Pune | C71: 45510 | E71: Honey Singh | F71: =VLOOKUP(E71,'Missing Values & Outliers'!$O$10:$P$19,2,0) -> Local Artist | G71: Martin Garrix, Bryan Adams | H71: 2910.2168 | I71: 32900 | J71: =I71*H71 -> 95746134 | K71: 6777400 | L71: 3584230 | M71: 126301230 | N71: {=VLOOKUP(E71,[1]Artist_Popularity_Data!$A$2:$I$11,{1,2,3,4,5,6,7,8,9},0)} -> Honey Singh | O71: Hip-Hop | P71: 1573 | Q71: 35223 | R71: 34 | S71: 430 | T71: 25360560 | U71: No | V71: Pune, Amritsar, Bengaluru
A72: Sunburn Goa | B72: Pune | C72: 45609 | D72: Classics Tour | E72: Bryan Adams | F72: =VLOOKUP(E72,'Missing Values & Outliers'!$O$10:$P$19,2,0) -> International | G72: Bryan Adams, Arijit Singh, Honey Singh | H72: 4765.6 | I72: 11366.6 | J72: =I72*H72 -> 54168669 | K72: 6933626 | L72: 2380633 | M72: 64588411 | N72: {=VLOOKUP(E72,[1]Artist_Popularity_Data!$A$2:$I$11,{1,2,3,4,5,6,7,8,9},0)} -> Bryan Adams | O72: Rock | P72: 992 | Q72: 21632.556 | R72: 30 | S72: 81 | T72: 8678356 | U72: Yes | V72: Delhi, Jaipur, Bengaluru, Mumbai
A73: Supersonic Bengaluru | B73: Delhi | C73: 45414 | E73: Shreya Ghoshal | F73: =VLOOKUP(E73,'Missing Values & Outliers'!$O$10:$P$19,2,0) -> Local Artist | G73: Ed Sheeran, Honey Singh, DJ Snake, Bryan Adams | H73: 3243 | I73: 5362 | J73: =I73*H73 -> 17388966 | K73: 739956 | L73: 4259028 | M73: 22387950 | N73: {=VLOOKUP(E73,[1]Artist_Popularity_Data!$A$2:$I$11,{1,2,3,4,5,6,7,8,9},0)} -> Shreya Ghoshal | O73: Classical/Bollywood | P73: 3326 | Q73: 3197 | R73: 23 | S73: 271 | T73: 792856 | U73: No | V73: Pune, Mumbai, Delhi, Bengaluru, Amritsar
A74: Supersonic Bengaluru | B74: Chandigarh | C74: 45531 | E74: Martin Garrix | F74: =VLOOKUP(E74,'Missing Values & Outliers'!$O$10:$P$19,2,0) -> International | G74: Shreya Ghoshal, Martin Garrix | H74: 1599 | I74: 6748 | J74: =I74*H74 -> 10790052 | K74: 1005452 | L74: 3330904 | M74: 15126408 | N74: {=VLOOKUP(E74,[1]Artist_Popularity_Data!$A$2:$I$11,{1,2,3,4,5,6,7,8,9},0)} -> Martin Garrix | O74: EDM | P74: 2499 | Q74: 11603 | R74: 43 | S74: 298 | T74: 6462871 | U74: No | V74: Chandigarh, Delhi, Pune, Nagpur, Bengaluru, Kolkata
A75: Supersonic Bengaluru | B75: Jaipur | C75: 45326 | D75: Soulful Nights Tour | E75: Arijit Singh | F75: =VLOOKUP(E75,'Missing Values & Outliers'!$O$10:$P$19,2,0) -> Local Artist | G75: Mika Singh, Diljit Dosanjh | H75: 1180 | I75: 11979 | J75: =I75*H75 -> 14135220 | K75: 3114540 | L75: 2375872 | M75: 19625632 | N75: {=VLOOKUP(E75,[1]Artist_Popularity_Data!$A$2:$I$11,{1,2,3,4,5,6,7,8,9},0)} -> Arijit Singh | O75: Bollywood | P75: 2437 | Q75: 25729 | R75: 30 | S75: 584 | T75: 18730712 | U75: Yes | V75: Nagpur, Jaipur, Chandigarh
A76: Lollapalooza Mumbai | B76: Kolkata | C76: 45601 | D76: Born To Shine Tour | E76: Diljit Dosanjh | F76: =VLOOKUP(E76,'Missing Values & Outliers'!$O$10:$P$19,2,0) -> Local Artist | G76: Arijit Singh, Mika Singh | H76: 3928 | I76: 45372.6 | J76: =I76*H76 -> 1.7822357e+08 | K76: 14623938 | L76: 962979 | M76: 152681973 | N76: {=VLOOKUP(E76,[1]Artist_Popularity_Data!$A$2:$I$11,{1,2,3,4,5,6,7,8,9},0)} -> Diljit Dosanjh | O76: Punjabi | P76: 2027 | Q76: 33738 | R76: 46 | S76: 116 | T76: 22334556 | U76: Yes | V76: Amritsar, Kolkata, Delhi, Mumbai, Bengaluru
A77: Lollapalooza Mumbai | B77: Jaipur | C77: 45401 | E77: Martin Garrix | F77: =VLOOKUP(E77,'Missing Values & Outliers'!$O$10:$P$19,2,0) -> International | G77: Mika Singh, Badshah, Ed Sheeran, Diljit Dosanjh | H77: 929 | I77: 17678 | J77: =I77*H77 -> 16422862 | K77: 4118974 | L77: 3432767 | M77: 23974603 | N77: {=VLOOKUP(E77,[1]Artist_Popularity_Data!$A$2:$I$11,{1,2,3,4,5,6,7,8,9},0)} -> Martin Garrix | O77: EDM | P77: 2499 | Q77: 11603 | R77: 43 | S77: 298 | T77: 6462871 | U77: No | V77: Chandigarh, Delhi, Pune, Nagpur, Bengaluru, Kolkata
A78: Lollapalooza Mumbai | B78: Bengaluru | C78: 45454 | E78: Badshah | F78: =VLOOKUP(E78,'Missing Values & Outliers'!$O$10:$P$19,2,0) -> Local Artist | G78: Arijit Singh, Ed Sheeran | H78: 1824 | I78: 11076 | J78: =I78*H78 -> 20202624 | K78: 2193048 | L78: 4584685 | M78: 26980357 | N78: {=VLOOKUP(E78,[1]Artist_Popularity_Data!$A$2:$I$11,{1,2,3,4,5,6,7,8,9},0)} -> Badshah | O78: Bollywood | P78: 3351 | Q78: 36448 | R78: 33 | S78: 483 | T78: 20228640 | U78: No | V78: Nagpur, Goa, Amritsar, Chandigarh, Mumbai
A79: Ziro Festival Arunachal | B79: Mumbai | C79: 45385 | D79: Soulful Nights Tour | E79: Arijit Singh | F79: =VLOOKUP(E79,'Missing Values & Outliers'!$O$10:$P$19,2,0) -> Local Artist | G79: Honey Singh, Martin Garrix, DJ Snake, Bryan Adams | H79: 3034 | I79: 9525 | J79: =I79*H79 -> 28898850 | K79: 1266825 | L79: 659581 | M79: 30825256 | N79: {=VLOOKUP(E79,[1]Artist_Popularity_Data!$A$2:$I$11,{1,2,3,4,5,6,7,8,9},0)} -> Arijit Singh | O79: Bollywood | P79: 2437 | Q79: 25729 | R79: 30 | S79: 584 | T79: 18730712 | U79: Yes | V79: Nagpur, Jaipur, Chandigarh
A80: Sunburn Goa | B80: Amritsar | C80: 45611 | D80: Mathematics Tour | E80: Ed Sheeran | F80: =VLOOKUP(E80,'Missing Values & Outliers'!$O$10:$P$19,2,0) -> International | G80: Honey Singh, Bryan Adams, DJ Snake | H80: 798 | I80: 20798.88 | J80: =I80*H80 -> 16597506 | K80: 4874352 | L80: 1012227 | M80: 16292499 | N80: {=VLOOKUP(E80,[1]Artist_Popularity_Data!$A$2:$I$11,{1,2,3,4,5,6,7,8,9},0)} -> Ed Sheeran | O80: International Pop | P80: 3436 | Q80: 18609 | R80: 55 | S80: 736 | T80: 4856949 | U80: Yes | V80: Pune, Amritsar, Goa, Chandigarh
A81: VH1 Supersonic Delhi | B81: Nagpur | C81: 45636 | D81: Soulful Nights Tour | E81: Arijit Singh | F81: =VLOOKUP(E81,'Missing Values & Outliers'!$O$10:$P$19,2,0) -> Local Artist | G81: Martin Garrix, Badshah, Honey Singh, DJ Snake | H81: 2753 | I81: 7762 | J81: =I81*H81 -> 21368786 | K81: 2227694 | L81: 3105094 | M81: 26701574 | N81: {=VLOOKUP(E81,[1]Artist_Popularity_Data!$A$2:$I$11,{1,2,3,4,5,6,7,8,9},0)} -> Arijit Singh | O81: Bollywood | P81: 2437 | Q81: 25729 | R81: 30 | S81: 584 | T81: 18730712 | U81: Yes | V81: Nagpur, Jaipur, Chandigarh
A82: Magnetic Fields Rajasthan | B82: Nagpur | C82: 45303 | D82: Soulful Nights Tour | E82: Arijit Singh | F82: =VLOOKUP(E82,'Missing Values & Outliers'!$O$10:$P$19,2,0) -> Local Artist | G82: Diljit Dosanjh, Mika Singh, DJ Snake | H82: 2609 | I82: 27598 | J82: =I82*H82 -> 72003182 | K82: 13467824 | L82: 3310368 | M82: 88781374 | N82: {=VLOOKUP(E82,[1]Artist_Popularity_Data!$A$2:$I$11,{1,2,3,4,5,6,7,8,9},0)} -> Arijit Singh | O82: Bollywood | P82: 2437 | Q82: 25729 | R82: 30 | S82: 584 | T82: 18730712 | U82: Yes | V82: Nagpur, Jaipur, Chandigarh
A83: Bollywood Music Project | B83: Mumbai | C83: 45324 | D83: Soulful Nights Tour | E83: Arijit Singh | F83: =VLOOKUP(E83,'Missing Values & Outliers'!$O$10:$P$19,2,0) -> Local Artist | G83: Martin Garrix, DJ Snake, Ed Sheeran, Mika Singh | H83: 4418 | I83: 8702 | J83: =I83*H83 -> 38445436 | K83: 3280654 | L83: 615109 | M83: 42341199 | N83: {=VLOOKUP(E83,[1]Artist_Popularity_Data!$A$2:$I$11,{1,2,3,4,5,6,7,8,9},0)} -> Arijit Singh | O83: Bollywood | P83: 2437 | Q83: 25729 | R83: 30 | S83: 584 | T83: 18730712 | U83: Yes | V83: Nagpur, Jaipur, Chandigarh
A84: VH1 Supersonic Delhi | B84: Bengaluru | C84: 45328 | E84: Shreya Ghoshal | F84: =VLOOKUP(E84,'Missing Values & Outliers'!$O$10:$P$19,2,0) -> Local Artist | G84: Diljit Dosanjh, Arijit Singh, DJ Snake | H84: 4849 | I84: 8214 | J84: =I84*H84 -> 39829686 | K84: 1667442 | L84: 4255125 | M84: 45752253 | N84: {=VLOOKUP(E84,[1]Artist_Popularity_Data!$A$2:$I$11,{1,2,3,4,5,6,7,8,9},0)} -> Shreya Ghoshal | O84: Classical/Bollywood | P84: 3326 | Q84: 3197 | R84: 23 | S84: 271 | T84: 792856 | U84: No | V84: Pune, Mumbai, Delhi, Bengaluru, Amritsar
A85: Supersonic Bengaluru | B85: Amritsar | C85: 45639 | D85: Classics Tour | E85: Bryan Adams | F85: =VLOOKUP(E85,'Missing Values & Outliers'!$O$10:$P$19,2,0) -> International | G85: DJ Snake, Mika Singh | H85: 1750 | I85: 20798.88 | J85: =I85*H85 -> 36398040 | K85: 4231825 | L85: 3268157 | M85: 21531232 | N85: {=VLOOKUP(E85,[1]Artist_Popularity_Data!$A$2:$I$11,{1,2,3,4,5,6,7,8,9},0)} -> Bryan Adams | O85: Rock | P85: 992 | Q85: 21632.556 | R85: 30 | S85: 81 | T85: 8678356 | U85: Yes | V85: Delhi, Jaipur, Bengaluru, Mumbai
A86: Sunburn Goa | B86: Jaipur | C86: 45425 | E86: DJ Snake | F86: =VLOOKUP(E86,'Missing Values & Outliers'!$O$10:$P$19,2,0) -> International | G86: Badshah, Bryan Adams | H86: 4279.8 | I86: 18095 | J86: =I86*H86 -> 77442981 | K86: 4089470 | L86: 1719569 | M86: 61125454 | N86: {=VLOOKUP(E86,[1]Artist_Popularity_Data!$A$2:$I$11,{1,2,3,4,5,6,7,8,9},0)} -> DJ Snake | O86: EDM | P86: 1431 | Q86: 19089 | R86: 32 | S86: 429 | T86: 10193526 | U86: No | V86: Bengaluru, Jaipur, Mumbai, Chandigarh, Kolkata, Delhi
A87: Bollywood Music Project | B87: Jaipur | C87: 45481 | E87: Mika Singh | F87: =VLOOKUP(E87,'Missing Values & Outliers'!$O$10:$P$19,2,0) -> Local Artist | G87: Arijit Singh, Ed Sheeran, Honey Singh, Mika Singh | H87: 3586 | I87: 38295 | J87: =I87*H87 -> 137325870 | K87: 5476185 | L87: 887815 | M87: 143689870 | N87: {=VLOOKUP(E87,[1]Artist_Popularity_Data!$A$2:$I$11,{1,2,3,4,5,6,7,8,9},0)} -> Mika Singh | O87: Bollywood | P87: 1025 | Q87: 11057 | R87: 12 | S87: 371 | T87: 7983154 | U87: No | V87: Delhi, Amritsar, Bengaluru, Mumbai
A88: Supersonic Bengaluru | B88: Goa | C88: 45632 | E88: Mika Singh | F88: =VLOOKUP(E88,'Missing Values & Outliers'!$O$10:$P$19,2,0) -> Local Artist | G88: Diljit Dosanjh, Martin Garrix | H88: 3782 | I88: 39893 | J88: =I88*H88 -> 150875326 | K88: 6263201 | L88: 6333350 | M88: 158405197 | N88: {=VLOOKUP(E88,[1]Artist_Popularity_Data!$A$2:$I$11,{1,2,3,4,5,6,7,8,9},0)} -> Mika Singh | O88: Bollywood | P88: 1025 | Q88: 11057 | R88: 12 | S88: 371 | T88: 7983154 | U88: No | V88: Delhi, Amritsar, Bengaluru, Mumbai
A89: Bollywood Music Project | B89: Bengaluru | C89: 45507 | D89: Mathematics Tour | E89: Ed Sheeran | F89: =VLOOKUP(E89,'Missing Values & Outliers'!$O$10:$P$19,2,0) -> International | G89: Mika Singh, DJ Snake | H89: 4834.2 | I89: 14283 | J89: =I89*H89 -> 69046879 | K89: 5356125 | L89: 1549672 | M89: 56224996 | N89: {=VLOOKUP(E89,[1]Artist_Popularity_Data!$A$2:$I$11,{1,2,3,4,5,6,7,8,9},0)} -> Ed Sheeran | O89: International Pop | P89: 3436 | Q89: 18609 | R89: 55 | S89: 736 | T89: 4856949 | U89: Yes | V89: Pune, Amritsar, Goa, Chandigarh
A90: Bollywood Music Project | B90: Kolkata | C90: 45353 | E90: Badshah | F90: =VLOOKUP(E90,'Missing Values & Outliers'!$O$10:$P$19,2,0) -> Local Artist | G90: Honey Singh, Diljit Dosanjh, Mika Singh | H90: 4286 | I90: 8925 | J90: =I90*H90 -> 38252550 | K90: 2722125 | L90: 896661 | M90: 41871336 | N90: {=VLOOKUP(E90,[1]Artist_Popularity_Data!$A$2:$I$11,{1,2,3,4,5,6,7,8,9},0)} -> Badshah | O90: Bollywood | P90: 3351 | Q90: 36448 | R90: 33 | S90: 483 | T90: 20228640 | U90: No | V90: Nagpur, Goa, Amritsar, Chandigarh, Mumbai
A91: Hornbill Festival Nagaland | B91: Delhi | C91: 45427 | D91: Soulful Nights Tour | E91: Arijit Singh | F91: =VLOOKUP(E91,'Missing Values & Outliers'!$O$10:$P$19,2,0) -> Local Artist | G91: Martin Garrix, Ed Sheeran, Mika Singh | H91: 2910.2168 | I91: 4885 | J91: =I91*H91 -> 14216409 | K91: 1734175 | L91: 4292613 | M91: 23891233 | N91: {=VLOOKUP(E91,[1]Artist_Popularity_Data!$A$2:$I$11,{1,2,3,4,5,6,7,8,9},0)} -> Arijit Singh | O91: Bollywood | P91: 2437 | Q91: 25729 | R91: 30 | S91: 584 | T91: 18730712 | U91: Yes | V91: Nagpur, Jaipur, Chandigarh
A92: Hornbill Festival Nagaland | B92: Nagpur | C92: 45647 | E92: Honey Singh | F92: =VLOOKUP(E92,'Missing Values & Outliers'!$O$10:$P$19,2,0) -> Local Artist | G92: Mika Singh, Ed Sheeran | H92: 4529 | I92: 4425 | J92: =I92*H92 -> 20040825 | K92: 584100 | L92: 2385440 | M92: 23010365 | N92: {=VLOOKUP(E92,[1]Artist_Popularity_Data!$A$2:$I$11,{1,2,3,4,5,6,7,8,9},0)} -> Honey Singh | O92: Hip-Hop | P92: 1573 | Q92: 35223 | R92: 34 | S92: 430 | T92: 25360560 | U92: No | V92: Pune, Amritsar, Bengaluru
A93: Ziro Festival Arunachal | B93: Goa | C93: 45499 | E93: Mika Singh | F93: =VLOOKUP(E93,'Missing Values & Outliers'!$O$10:$P$19,2,0) -> Local Artist | G93: Shreya Ghoshal, Honey Singh, Badshah | H93: 726 | I93: 37105 | J93: =I93*H93 -> 26938230 | K93: 14545160 | L93: 835232 | M93: 42318622 | N93: {=VLOOKUP(E93,[1]Artist_Popularity_Data!$A$2:$I$11,{1,2,3,4,5,6,7,8,9},0)} -> Mika Singh | O93: Bollywood | P93: 1025 | Q93: 11057 | R93: 12 | S93: 371 | T93: 7983154 | U93: No | V93: Delhi, Amritsar, Bengaluru, Mumbai

Sheet Stage2
A1: Peak Season for Festivals in India
A3: Row Labels | B3: Sum of Total_Revenue (Rs) | C3: Sum of Total_Revenue (Rs)2
A4: Jan | B4: 471168417 | C4: 0.078994626
A5: Feb | B5: 328171218 | C5: 0.055020162
A6: Mar | B6: 406005910 | C6: 0.068069683
A7: Apr | B7: 380768959 | C7: 0.063838535
A8: May | B8: 591637363 | C8: 0.099192073
A9: Jun | B9: 536416537 | C9: 0.089933922
A10: Jul | B10: 493875206 | C10: 0.082801575
A11: Aug | B11: 848183953 | C11: 0.14220387
A12: Sep | B12: 695359429 | C12: 0.11658179
A13: Oct | B13: 91024006 | C13: 0.015260801
A14: Nov | B14: 256909552 | C14: 0.043072653
A15: Dec | B15: 865042389 | C15: 0.14503031
A16: Grand Total | B16: 5964562939 | C16: 1
A21: August and Decemeber shows the best season for Music Festivals in India.
A26: Row Labels | B26: Total_Revenue1 (Rs) | C26: Total_Attendance1
A27: Jan | B27: 471168417 | C27: 147506.5
A28: Feb | B28: 328171218 | C28: 95928.1
A29: Mar | B29: 406005910 | C29: 99290.7
A30: Apr | B30: 380768959 | C30: 145057.6
A31: May | B31: 591637363 | C31: 196145.76
A32: Jun | B32: 536416537 | C32: 208472.74
A33: Jul | B33: 493875206 | C33: 121054
A34: Aug | B34: 848183953 | C34: 256917.18
A35: Sep | B35: 695359429 | C35: 142573
A36: Oct | B36: 91024006 | C36: 29962.6
A37: Nov | B37: 256909552 | C37: 98336.96
A38: Dec | B38: 865042389 | C38: 261064.58
A39: Grand Total | B39: 5964562939 | C39: 1802309.7
A43: We can see that, seasonal trends impact attendance, making it crucial to align festival dates with periods of high demand.
A44: December is the best season for Music Festivals in India with 14.49% attendance being the highest for whole year
A49: Row Labels | B49: Total Revenue(Rs) | C49: Total Attendance
A50: Pune | B50: 479288314 | C50: 150798.48
A51: Nagpur | B51: 831769738 | C51: 227873.96
A52: Mumbai | B52: 171830232 | C52: 79127.2
A53: Kolkata | B53: 594009538 | C53: 144910.2
A54: Jaipur | B54: 752723987 | C54: 234934.98
A55: Goa | B55: 1073141556 | C55: 369065.58
A56: Delhi | B56: 744828479 | C56: 173785.96
A57: Chandigarh | B57: 340514615 | C57: 155236.1
A58: Bengaluru | B58: 633786616 | C58: 150796.4
A59: Amritsar | B59: 342669864 | C59: 115780.86
A60: Grand Total | B60: 5964562939 | C60: 1802309.7
A64: Goa has the highest attendance, being the festival hotspot and audience preference.
A65: Expansion in cities like Nagpur, Jaipur and Bengluru is possible
A70: Row Labels | B70: Sum of Total_Attendance
A71: Badshah | B71: 259551.88
A72: Diljit Dosanjh | B72: 252102.5
A73: Mika Singh | B73: 232532.88
A74: Shreya Ghoshal | B74: 218675.64
A75: Arijit Singh | B75: 186321.88
A76: Bryan Adams | B76: 182197.18
A77: Honey Singh | B77: 174435
A78: DJ Snake | B78: 127284.88
A79: Martin Garrix | B79: 116336
A80: Ed Sheeran | B80: 52871.88
A81: Grand Total | B81: 1802309.7
A86: The data is for just one year which is 2024.
A87: So as per analysis, Badshah has highest public interest in Music followed by Diljit Dosanjh
A88: Also people follow Indian Artist more than International Artist for this years data

Sheet Stage3
A1: Optimizing Ticket Pricing for Maximum Revenue
A3: Row Labels | B3: Average of Ticket_Price(Rs) | C3: Total Attendance
A4: Chandigarh | B4: 2033.9 | C4: 0.086131755
A5: Mumbai | B5: 2489.6 | C5: 0.04390322
A6: Goa | B6: 2564.8822 | C6: 0.20477367
A7: Nagpur | B7: 2637.2333 | C7: 0.12643441
A8: Amritsar | B8: 2686.6667 | C8: 0.064240268
A9: Kolkata | B9: 2832.2 | C9: 0.080402496
A10: Pune | B10: 2880.0595 | C10: 0.08366957
A11: Jaipur | B11: 3035.894 | C11: 0.13035217
A12: Bengaluru | B12: 3704.1434 | C12: 0.083668416
A13: Delhi | B13: 3989.2251 | C13: 0.096424026
A14: Grand Total | B14: 2914.1931 | C14: 1
A20: This chart clearly shows that if the price of the ticket increases, attendance decreases.
A21: Delhi & Bengluru has the highest ticket price with very low attendance whereas Goa has the highest attendance and medium ticket price
A24: Row Labels | B24: Count of Festival_Name | C24: Average of Total_Revenue (Rs) | D24: Total_Revenue (Rs)2 | E24: Total_Attendance2 | F24: Average of Total_Attendance | G24: Attedance%
A25: 500-1500 | B25: 16 | C25: 31956668 | D25: 511306692 | E25: 425026.36 | F25: 26564.147 | G25: 0.23582315
A26: 1500-2500 | B26: 17 | C26: 58795105 | D26: 999516783 | E26: 311548.98 | F26: 18326.411 | G26: 0.17286096
A27: 2500-3500 | B27: 30 | C27: 53525398 | D27: 1605761941 | E27: 458178.04 | F27: 15272.601 | G27: 0.25421715
A28: 3500-4500 | B28: 17 | C28: 99554239 | D28: 1692422060 | E28: 426047.44 | F28: 25061.614 | G28: 0.23638969
A29: 4500-5500 | B29: 10 | C29: 85223082 | D29: 852230819 | E29: 141937.9 | F29: 14193.79 | G29: 0.078753334
A30: 6500-7500 | B30: 2 | C30: 151662322 | D30: 303324644 | E30: 39571 | F30: 19785.5 | G30: 0.021955716
A31: Grand Total | B31: 92 | C31: 64832206 | D31: 5964562939 | E31: 1802309.7 | F31: 19590.323 | G31: 1
A34: Attendance Analysis:
A35: ₹2,500 - ₹3,500 range has HIGHEST ATTENDANCE (25.42% of total) with 458,178 attendees across 30 festivals
A36: ₹500 - ₹1,500 range has HIGHEST AVG ATTENDANCE per festival (26,564) - budget-friendly attracts crowds
A39: Profitability Analysis:
A40: ₹3,500 - ₹4,500 range: HIGHEST Avg Revenue per Festival- best profitability per event
A41: ₹2,500 - ₹3,500 range: HIGHEST Total Revenue (₹160.6 Cr) - volume drives overall revenue
A44: Avoid tickets above 5500 as it drastically affects the attendance
A46: Correlation of Ticket price & Total Attendance | C46: =CORREL('Cleaned Data'!H2:H93,'Cleaned Data'!I2:I93) -> -0.18753532
A48: This Correlation shows that if the value of ticket increases the attendance count goes down.
A49: Not drastically but it do affect at some point.

Sheet Stage4
A1: Impact of International vs. Local Artists on Ticket Sales
A4: Row Labels | B4: Total Revenue | C4: Total Attendance | D4: Event Count | E4: Avg Attendance/Event | F4: Avg Revenue / Event
A5: Arijit Singh | B5: 488510395 | C5: 186321.88 | D5: 12 | E5: =C5/D5 -> 15526.823 | F5: =B5/D5 -> 40709200
A6: Badshah | B6: 1012375595 | C6: 259551.88 | D6: 12 | E6: =C6/D6 -> 21629.323 | F6: =B6/D6 -> 84364633
A7: Bryan Adams | B7: 832634949 | C7: 182197.18 | D7: 12 | E7: =C7/D7 -> 15183.098 | F7: =B7/D7 -> 69386246
A8: Diljit Dosanjh | B8: 453627757 | C8: 252102.5 | D8: 8 | E8: =C8/D8 -> 31512.813 | F8: =B8/D8 -> 56703470
A9: DJ Snake | B9: 487828759 | C9: 127284.88 | D9: 7 | E9: =C9/D9 -> 18183.554 | F9: =B9/D9 -> 69689823
A10: Ed Sheeran | B10: 109382356 | C10: 52871.88 | D10: 4 | E10: =C10/D10 -> 13217.97 | F10: =B10/D10 -> 27345589
A11: Honey Singh | B11: 877653513 | C11: 174435 | D11: 11 | E11: =C11/D11 -> 15857.727 | F11: =B11/D11 -> 79786683
A12: Martin Garrix | B12: 336379539 | C12: 116336 | D12: 6 | E12: =C12/D12 -> 19389.333 | F12: =B12/D12 -> 56063256
A13: Mika Singh | B13: 658312538 | C13: 232532.88 | D13: 10 | E13: =C13/D13 -> 23253.288 | F13: =B13/D13 -> 65831254
A14: Shreya Ghoshal | B14: 707857538 | C14: 218675.64 | D14: 10 | E14: =C14/D14 -> 21867.564 | F14: =B14/D14 -> 70785754
A15: Grand Total | B15: 5964562939 | C15: 1802309.7 | D15: 92 | E15: =C15/D15 -> 19590.323 | F15: =B15/D15 -> 64832206
A19: KEY POINTS:
A20: • Badshah draws the MOST total attendees(2,59,552) - best for maximizing turnout
A21: • Badshah generates HIGHEST revenue(1,01,23,75,595) - best for revenue optimization
A22: • Diljit Dosanjh has HIGHEST per-event attendance (31,513 avg) - most consistent crowd puller
A25: STRATEGIC RECOMMENDATIONS:
A26: • For MAX TURNOUT: Book Badshah, Diljit Dosanjh, or Mika Singh as headliners
A27: • For MAX REVENUE: Prioritize Badshah, Honey Singh or Bryan Adams
A28: • For BALANCED PERFORMANCE: Honey Singh, Shreya Ghoshal offer good attendance + revenue mix
A30: INSIGHT | B30: ARTIST | C30: VALUE(Rs) | D30: IMPLICATION
A31: Top Attendance Driver | B31: Badshah | C31: 259551.88 | D31: Best for maximizing crowd size
A32: Top Revenue Driver | B32: Badshah | C32: 1012375595 | D32: Best for maximizing festival income
A33: Best Per-Event Avg Attendance | B33: Diljit Dosanjh | C33: 31512.813 | D33: Most consistent crowd pull per show
A38: Row Labels | B38: Total Revenue | C38: Total Attendance | D38: Average of Total_Attendance
A39: Bollywood | B39: 2159198528 | C39: 678406.64 | D39: 19953.136
A40: Classical/Bollywood | B40: 707857538 | C40: 218675.64 | D40: 21867.564
A41: EDM | B41: 824208298 | C41: 243620.88 | D41: 18740.068
A42: Hip-Hop | B42: 877653513 | C42: 174435 | D42: 15857.727
A43: International Pop | B43: 109382356 | C43: 52871.88 | D43: 13217.97
A44: Punjabi | B44: 453627757 | C44: 252102.5 | D44: 31512.813
A45: Rock | B45: 832634949 | C45: 182197.18 | D45: 15183.098
A46: Grand Total | B46: 5964562939 | C46: 1802309.7 | D46: 19590.323
A49: KEY POINTS:
A50: Genre-Bollywood is the music style which attracts the largest crowd
A51: Punjabi has the highest Avg Attendance which means Festival-goers generally prefer this genre.
A54: Row Labels | B54: Total Events | C54: Total Attendance3 | D54: Total Revenue3 | E54: Average of Ticket_Price(Rs) | F54: Revenue/Attendance
A55: International | B55: 29 | C55: 478689.94 | D55: 1766225603 | E55: 3223.4075 | F55: =D55/C55 -> 3689.707
A56: Local Artist | B56: 63 | C56: 1323619.8 | D56: 4198337336 | E56: 2771.8564 | F56: =D56/C56 -> 3171.8605
A57: Grand Total | B57: 92 | C57: 1802309.7 | D57: 5964562939 | E57: 2914.1931 | F57: =F56+F55 -> 6861.5675
A59: Revenue Efficiency | B59: International | C59: Local Artist
A60: Revenue/Attendance(Rs) | B60: =F55 -> 3689.707 | C60: =F56 -> 3171.8605
A61: Avg Ticket price(Rs) | B61: =GETPIVOTDATA("Average of Ticket_Price(Rs)",$A$54,"International & Local Artists","International ") -> 3223.4075 | C61: =GETPIVOTDATA("Average of Ticket_Price(Rs)",$A$54,"International & Local Artists","Local Artist") -> 2771.8564
A64: ATTENDANCE INSIGHTS:
A65: Local artists account for a significantly larger share of total attendance(13,23,620)
A66: Diljit Dosanjh has the highest average attendance per event(31,513) among all artists
A68: REVENUE INSIGHTS:
A69: Local artists generate higher total revenue due to more events
A70: Badshah leads in total revenue generation among all artists
A72: ROI INSIGHTS:
A73: • Local artists provide better ROI with lower perceived costs and higher volume
A74: • International artists may have higher per-event costs (flights, visas, accommodation)
A77: We can say that :Invest in Local Artists than International

Sheet Stage5
A1: The Role of Sponsorship and Merchandise in Festival Profitability
B4: Row Labels | C4: Total Sponsorship Revenue(Rs) | D4: Total Merchandise Revenue(Rs) | E4: Total Revenue(Rs) | F4: Sponsorship_Revenue % | G4: Merchandise_Revenue % | H4: Spon+Merch
B5: Bollywood Music Project | C5: 24890409 | D5: 70150425 | E5: 808366341 | F5: =$C5/$E5 -> 0.030791001 | G5: =$D5/$E5 -> 0.086780487 | H5: =G5+F5 -> 0.11757149
B6: Goa Tribal Festival | C6: 13640304 | D6: 34422086 | E6: 262562788 | F6: =$C6/$E6 -> 0.051950637 | G6: =$D6/$E6 -> 0.1311004 | H6: =G6+F6 -> 0.18305103
B7: Hornbill Festival Nagaland | C7: 25729666 | D7: 53220652 | E7: 693593924 | F7: =$C7/$E7 -> 0.037096153 | G7: =$D7/$E7 -> 0.076731716 | H7: =G7+F7 -> 0.11382787
B8: Lollapalooza Mumbai | C8: 27249754 | D8: 44591246 | E8: 573358526 | F8: =$C8/$E8 -> 0.047526552 | G8: =$D8/$E8 -> 0.077772012 | H8: =G8+F8 -> 0.12529856
B9: Magnetic Fields Rajasthan | C9: 20962429 | D9: 44144035 | E9: 417295881 | F9: =$C9/$E9 -> 0.050233971 | G9: =$D9/$E9 -> 0.10578594 | H9: =G9+F9 -> 0.15601991
B10: NH7 Pune | C10: 22154036 | D10: 67169601 | E10: 515929887 | F10: =$C10/$E10 -> 0.042940013 | G10: =$D10/$E10 -> 0.13019134 | H10: =G10+F10 -> 0.17313135
B11: Sunburn Goa | C11: 37397648 | D11: 64852790 | E11: 695292216 | F11: =$C11/$E11 -> 0.05378695 | G11: =$D11/$E11 -> 0.093274149 | H11: =G11+F11 -> 0.1470611
B12: Supersonic Bengaluru | C12: 34776787 | D12: 33903753 | E12: 468868182 | F12: =$C12/$E12 -> 0.074171779 | G12: =$D12/$E12 -> 0.072309776 | H12: =G12+F12 -> 0.14648155
B13: VH1 Supersonic Delhi | C13: 26610746 | D13: 33620520 | E13: 459482479 | F13: =$C13/$E13 -> 0.057914604 | G13: =$D13/$E13 -> 0.073170407 | H13: =G13+F13 -> 0.13108501
B14: Ziro Festival Arunachal | C14: 35162471 | D14: 74651155 | E14: 1069812715 | F14: =$C14/$E14 -> 0.032867875 | G14: =$D14/$E14 -> 0.069779648 | H14: =G14+F14 -> 0.10264752
B15: Grand Total | C15: 268574250 | D15: 520726263 | E15: 5964562939 | F15: =$C15/$E15 -> 0.04502832 | G15: =$D15/$E15 -> 0.087303339 | H15: =G15+F15 -> 0.13233166
B17: The reliability of Festivals on Sponsorship
B18: Average contribution of Sponsorship from Total Revenue | D18: =F15 -> 0.04502832
B19: Highest Sponsorship | C19: =INDEX(B5:B14,MATCH(MAX(F5:F14),Stage5!F5:F14,0)) -> Supersonic Bengaluru | D19: =INDEX(F5:F14,MATCH(C19,B5:B14,0)) -> 0.074171779
B20: Lowest Sponsorship | C20: =INDEX(B5:B14,MATCH(MIN(F5:F14),F5:F14,0)) -> Bollywood Music Project | D20: =INDEX(F5:F14,MATCH(C20,B5:B14,0)) -> 0.030791001
B25: Row Labels | C25: Average of Ticket_Price(Rs) | D25: Total number of events | E25: Total Sponsorship Revenue4 | F25: Total Attendance4 | G25: Sponsorship per attendee | H25: Tier Classification
B26: Bollywood Music Project | C26: 3273.6514 | D26: 12 | E26: 24890409 | F26: 241064.86 | G26: =E26/F26 -> 103.25192 | H26: =IF($C26>$C$36,"Premium Tier", "General Tier") -> Premium Tier
B27: Goa Tribal Festival | C27: 2723.8434 | D27: 5 | E27: 13640304 | F27: 78395.1 | G27: =E27/F27 -> 173.99434 | H27: =IF($C27>$C$36,"Premium Tier", "General Tier") -> General Tier
B28: Hornbill Festival Nagaland | C28: 3627.1292 | D28: 8 | E28: 25729666 | F28: 177893.1 | G28: =E28/F28 -> 144.63555 | H28: =IF($C28>$C$36,"Premium Tier", "General Tier") -> Premium Tier
B29: Lollapalooza Mumbai | C29: 3106.5271 | D29: 8 | E29: 27249754 | F29: 162704.2 | G29: =E29/F29 -> 167.48034 | H29: =IF($C29>$C$36,"Premium Tier", "General Tier") -> Premium Tier
B30: Magnetic Fields Rajasthan | C30: 2491.4024 | D30: 7 | E30: 20962429 | F30: 129417.18 | G30: =E30/F30 -> 161.97563 | H30: =IF($C30>$C$36,"Premium Tier", "General Tier") -> General Tier
B31: NH7 Pune | C31: 2563.7778 | D31: 9 | E31: 22154036 | F31: 191933.9 | G31: =E31/F31 -> 115.42534 | H31: =IF($C31>$C$36,"Premium Tier", "General Tier") -> General Tier
B32: Sunburn Goa | C32: 2921.0167 | D32: 13 | E32: 37397648 | F32: 248284.94 | G32: =E32/F32 -> 150.62391 | H32: =IF($C32>$C$36,"Premium Tier", "General Tier") -> Premium Tier
B33: Supersonic Bengaluru | C33: 2358.98 | D33: 10 | E33: 34776787 | F33: 201201.86 | G33: =E33/F33 -> 172.84526 | H33: =IF($C33>$C$36,"Premium Tier", "General Tier") -> General Tier
B34: VH1 Supersonic Delhi | C34: 3410.325 | D34: 8 | E34: 26610746 | F34: 112776.8 | G34: =E34/F34 -> 235.9594 | H34: =IF($C34>$C$36,"Premium Tier", "General Tier") -> Premium Tier
B35: Ziro Festival Arunachal | C35: 2664.5042 | D35: 12 | E35: 35162471 | F35: 258637.78 | G35: =E35/F35 -> 135.95257 | H35: =IF($C35>$C$36,"Premium Tier", "General Tier") -> General Tier
B36: Grand Total | C36: 2914.1931 | D36: 92 | E36: 268574250 | F36: 1802309.7 | G36: =E36/F36 -> 149.0167 | H36: =IF($C36>$C$36,"Premium Tier", "General Tier") -> General Tier
B38: Premium-Tier - Ticket price>Avg Ticket price(2914)
B39: General Ticket - Ticket price<=Avg Ticket price(2914)
B41: Comparison for General vs Premium
C42: Total Events | D42: Total Sponsorship(Rs) | E42: Average Sponsorship/Event | F42: Average Sponsorship per attendee(Rs)
B43: Premium | C43: =SUMIF($H$26:$H$35,"Premium Tier",$D$26:$D$35) -> 49 | D43: =SUMIF($H$26:$H$35,"Premium Tier",$E$26:$E$35) -> 141878223 | E43: =D43/C43 -> 2895473.9 | F43: =AVERAGEIF($H$26:$H$35,"Premium Tier",$G$26:$G$35) -> 160.39022
B44: General | C44: =SUMIF($H$26:$H$35,"General Tier",$D$26:$D$35) -> 43 | D44: =SUMIF($H$26:$H$35,"General Tier",$E$26:$E$35) -> 126696027 | E44: =D44/C44 -> 2946419.2 | F44: =AVERAGEIF($H$26:$H$35,"General Tier",$G$26:$G$35) -> 152.03863
B46: Spnsorship Analysis:
B47: Premium(Avg Sponsorship/Event) | C47: =E43 -> 2895473.9
B48: General(Avg Sponsorship/Event) | C48: =E44 -> 2946419.2
B49: Premium Advantage | C49: =C47-C48 -> -50945.294
B50: Higher Sponsor Tier | C50: =IF(E43>E44,"Premium Tier", "General Tier") -> General Tier
B51: Sponsor Difference | C51: =C48-C47 -> 50945.294
B53: Premium festivals has higher avg price for ticket
B54: Higher end festivals may suggest Premium Tickets
B58: Row Labels | C58: Total number of events | D58: Total Merchandise(Rs) | E58: Total Revenue(Rs) | F58: Total Attendance4 | G58: Merchandise per attendee | H58: Merchandise per event | I58: Merchandise %
B59: Bollywood Music Project | C59: 12 | D59: 70150425 | E59: 808366341 | F59: 241064.86 | G59: =$D59/$F59 -> 291.00228 | H59: =$D59/$C59 -> 5845868.8 | I59: =D59/E59 -> 0.086780487
B60: Goa Tribal Festival | C60: 5 | D60: 34422086 | E60: 262562788 | F60: 78395.1 | G60: =$D60/$F60 -> 439.08466 | H60: =$D60/$C60 -> 6884417.2 | I60: =D60/E60 -> 0.1311004
B61: Hornbill Festival Nagaland | C61: 8 | D61: 53220652 | E61: 693593924 | F61: 177893.1 | G61: =$D61/$F61 -> 299.1721 | H61: =$D61/$C61 -> 6652581.5 | I61: =D61/E61 -> 0.076731716
B62: Lollapalooza Mumbai | C62: 8 | D62: 44591246 | E62: 573358526 | F62: 162704.2 | G62: =$D62/$F62 -> 274.06328 | H62: =$D62/$C62 -> 5573905.8 | I62: =D62/E62 -> 0.077772012
B63: Magnetic Fields Rajasthan | C63: 7 | D63: 44144035 | E63: 417295881 | F63: 129417.18 | G63: =$D63/$F63 -> 341.09872 | H63: =$D63/$C63 -> 6306290.7 | I63: =D63/E63 -> 0.10578594
B64: NH7 Pune | C64: 9 | D64: 67169601 | E64: 515929887 | F64: 191933.9 | G64: =$D64/$F64 -> 349.96215 | H64: =$D64/$C64 -> 7463289 | I64: =D64/E64 -> 0.13019134
B65: Sunburn Goa | C65: 13 | D65: 64852790 | E65: 695292216 | F65: 248284.94 | G65: =$D65/$F65 -> 261.20308 | H65: =$D65/$C65 -> 4988676.2 | I65: =D65/E65 -> 0.093274149
B66: Supersonic Bengaluru | C66: 10 | D66: 33903753 | E66: 468868182 | F66: 201201.86 | G66: =$D66/$F66 -> 168.50616 | H66: =$D66/$C66 -> 3390375.3 | I66: =D66/E66 -> 0.072309776
B67: VH1 Supersonic Delhi | C67: 8 | D67: 33620520 | E67: 459482479 | F67: 112776.8 | G67: =$D67/$F67 -> 298.11557 | H67: =$D67/$C67 -> 4202565 | I67: =D67/E67 -> 0.073170407
B68: Ziro Festival Arunachal | C68: 12 | D68: 74651155 | E68: 1069812715 | F68: 258637.78 | G68: =$D68/$F68 -> 288.63206 | H68: =$D68/$C68 -> 6220929.6 | I68: =D68/E68 -> 0.069779648
B69: Grand Total | C69: 92 | D69: 520726263 | E69: 5964562939 | F69: 1802309.7 | G69: =$D69/$F69 -> 288.92163 | H69: =$D69/$C69 -> 5660068.1 | I69: =D69/E69 -> 0.087303339
B72: Merchandise Analysis:-
B73: Merchandise Sales contribution towards Total Revenue
B74: Average contribution of Merchandise from Total Revenue | D74: =G15 -> 0.087303339
B75: Highest Merchandise | C75: =INDEX(B59:B68,MATCH(MAX(G59:G68),Stage5!G59:G68,0)) -> Goa Tribal Festival | D75: =INDEX(I59:I68,MATCH(C75,B59:B68,0)) -> 0.1311004
B76: Lowest Merchandise | C76: =INDEX(B59:B68,MATCH(MIN(G59:G68),G59:G68,0)) -> Supersonic Bengaluru | D76: =INDEX(I59:I68,MATCH(C76,B59:B68,0)) -> 0.072309776
B77: Total Merchandise Revenue | D77: =GETPIVOTDATA("Total Merchandise(Rs)",$B$58) -> 520726263
B79: Merchandise per attendee shows attendee engagement and spending pattern
B80: Merchandise stratergy can be key point for festival profitability
B83: Overall
B84: Total Revenue | C84: =GETPIVOTDATA("Total Revenue(Rs)",$B$4) -> 5964562939 | D84: 1
B85: Sponsorship Revenue | C85: =GETPIVOTDATA("Total Sponsorship Revenue(Rs)",$B$4) -> 268574250 | D85: =C85/C84 -> 0.04502832
B86: Merchandise Revenue | C86: =GETPIVOTDATA("Total Merchandise Revenue(Rs)",$B$4) -> 520726263 | D86: =C86/C84 -> 0.087303339
B87: Combined(Spon+Merch) | C87: =C86+C85 -> 789300513 | D87: =D86+D85 -> 0.13233166
B88: Revenue remained | C88: =C84-(C85+C86) -> 5175262426 | D88: =D84-D87 -> 0.86766834

Sheet Stage6
A1: Regional Preferences and Expansion Opportunities
B3: Count of Genre | C3: Column Labels
B4: Row Labels | C4: Bollywood | D4: Classical/Bollywood | E4: EDM | F4: Hip-Hop | G4: International Pop | H4: Punjabi | I4: Rock | J4: Total Events | K4: Dominant Genre
B5: Amritsar | C5: 1 | D5: 1 | F5: 1 | G5: 1 | I5: 2 | J5: 6 | K5: =INDEX($C$4:$I$4,MATCH(MAX(C5:I5),C5:I5,0)) -> Rock
B6: Bengaluru | C6: 4 | D6: 1 | E6: 1 | F6: 1 | G6: 1 | H6: 1 | I6: 1 | J6: 10 | K6: =INDEX($C$4:$I$4,MATCH(MAX(C6:I6),C6:I6,0)) -> Bollywood
B7: Chandigarh | C7: 2 | D7: 1 | E7: 2 | F7: 1 | G7: 1 | H7: 1 | J7: 8 | K7: =INDEX($C$4:$I$4,MATCH(MAX(C7:I7),C7:I7,0)) -> Bollywood
B8: Delhi | C8: 3 | D8: 3 | E8: 1 | H8: 1 | I8: 2 | J8: 10 | K8: =INDEX($C$4:$I$4,MATCH(MAX(C8:I8),C8:I8,0)) -> Bollywood
B9: Goa | C9: 6 | D9: 2 | E9: 2 | F9: 2 | H9: 1 | I9: 2 | J9: 15 | K9: =INDEX($C$4:$I$4,MATCH(MAX(C9:I9),C9:I9,0)) -> Bollywood
B10: Jaipur | C10: 4 | D10: 1 | E10: 4 | F10: 1 | H10: 1 | J10: 11 | K10: =INDEX($C$4:$I$4,MATCH(MAX(C10:I10),C10:I10,0)) -> Bollywood
B11: Kolkata | C11: 4 | F11: 2 | H11: 1 | I11: 1 | J11: 8 | K11: =INDEX($C$4:$I$4,MATCH(MAX(C11:I11),C11:I11,0)) -> Bollywood
B12: Mumbai | C12: 3 | E12: 1 | H12: 1 | J12: 5 | K12: =INDEX($C$4:$I$4,MATCH(MAX(C12:I12),C12:I12,0)) -> Bollywood
B13: Nagpur | C13: 5 | E13: 2 | F13: 2 | I13: 3 | J13: 12 | K13: =INDEX($C$4:$I$4,MATCH(MAX(C13:I13),C13:I13,0)) -> Bollywood
B14: Pune | C14: 2 | D14: 1 | F14: 1 | G14: 1 | H14: 1 | I14: 1 | J14: 7 | K14: =INDEX($C$4:$I$4,MATCH(MAX(C14:I14),C14:I14,0)) -> Bollywood
B15: Total Events | C15: 34 | D15: 10 | E15: 13 | F15: 11 | G15: 4 | H15: 8 | I15: 12 | J15: 92
B20: Sum of Total_Attendance | C20: Column Labels
B21: Row Labels | C21: Bollywood | D21: Classical/Bollywood | E21: EDM | F21: Hip-Hop | G21: International Pop | H21: Punjabi | I21: Rock | J21: Total Attendance | K21: Dominant Genre
B22: Amritsar | C22: 25243 | D22: 20603 | F22: 9316 | G22: 20798.88 | I22: 39819.98 | J22: 115780.86 | K22: =INDEX($C$21:$I$21,MATCH(MAX(C22:I22),C22:I22,0)) -> Rock
B23: Bengaluru | C23: 54368 | D23: 8214 | E23: 31745 | F23: 16737 | G23: 14283 | H23: 7559.5 | I23: 17889.9 | J23: 150796.4 | K23: =INDEX($C$21:$I$21,MATCH(MAX(C23:I23),C23:I23,0)) -> Bollywood
B24: Chandigarh | C24: 42305 | D24: 35304 | E24: 23590 | F24: 13994 | G24: 6000 | H24: 34043.1 | J24: 155236.1 | K24: =INDEX($C$21:$I$21,MATCH(MAX(C24:I24),C24:I24,0)) -> Bollywood
B25: Delhi | C25: 53402.88 | D25: 57915.88 | E25: 17172 | H25: 14456 | I25: 30839.2 | J25: 173785.96 | K25: =INDEX($C$21:$I$21,MATCH(MAX(C25:I25),C25:I25,0)) -> Classical/Bollywood
B26: Goa | C26: 172325 | D26: 44819.88 | E26: 34524 | F26: 24248 | H26: 56160 | I26: 36988.7 | J26: 369065.58 | K26: =INDEX($C$21:$I$21,MATCH(MAX(C26:I26),C26:I26,0)) -> Bollywood
B27: Jaipur | C27: 76528.88 | D27: 31020 | E27: 80922 | F27: 13539 | H27: 32925.1 | J27: 234934.98 | K27: =INDEX($C$21:$I$21,MATCH(MAX(C27:I27),C27:I27,0)) -> EDM
B28: Kolkata | C28: 57679 | F28: 32354 | H28: 45372.6 | I28: 9504.6 | J28: 144910.2 | K28: =INDEX($C$21:$I$21,MATCH(MAX(C28:I28),C28:I28,0)) -> Bollywood
B29: Mumbai | C29: 30915 | E29: 19867 | H29: 28345.2 | J29: 79127.2 | K29: =INDEX($C$21:$I$21,MATCH(MAX(C29:I29),C29:I29,0)) -> Bollywood
B30: Nagpur | C30: 124937.88 | E30: 35800.88 | F30: 31347 | I30: 35788.2 | J30: 227873.96 | K30: =INDEX($C$21:$I$21,MATCH(MAX(C30:I30),C30:I30,0)) -> Bollywood
B31: Pune | C31: 40702 | D31: 20798.88 | F31: 32900 | G31: 11790 | H31: 33241 | I31: 11366.6 | J31: 150798.48 | K31: =INDEX($C$21:$I$21,MATCH(MAX(C31:I31),C31:I31,0)) -> Bollywood
B32: Total Attendance | C32: 678406.64 | D32: 218675.64 | E32: 243620.88 | F32: 174435 | G32: 52871.88 | H32: 252102.5 | I32: 182197.18 | J32: 1802309.7
B38: City | C38: Most Events Genre | D38: Most Attendance Genre | E38: AvgAttendance per event | F38: Genre Aligned
B39: Amritsar | C39: =K5 -> Rock | D39: =K22 -> Rock | E39: =J22/J5 -> 19296.81 | F39: =IF(D39=C39, "Aligned","Not Aligned") -> Aligned
B40: Bengaluru | C40: =K6 -> Bollywood | D40: =K23 -> Bollywood | E40: =J23/J6 -> 15079.64 | F40: =IF(D40=C40, "Aligned","Not Aligned") -> Aligned
B41: Chandigarh | C41: =K7 -> Bollywood | D41: =K24 -> Bollywood | E41: =J24/J7 -> 19404.513 | F41: =IF(D41=C41, "Aligned","Not Aligned") -> Aligned
B42: Delhi | C42: =K8 -> Bollywood | D42: =K25 -> Classical/Bollywood | E42: =J25/J8 -> 17378.596 | F42: =IF(D42=C42, "Aligned","Not Aligned") -> Not Aligned
B43: Goa | C43: =K9 -> Bollywood | D43: =K26 -> Bollywood | E43: =J26/J9 -> 24604.372 | F43: =IF(D43=C43, "Aligned","Not Aligned") -> Aligned
B44: Jaipur | C44: =K10 -> Bollywood | D44: =K27 -> EDM | E44: =J27/J10 -> 21357.725 | F44: =IF(D44=C44, "Aligned","Not Aligned") -> Not Aligned
B45: Kolkata | C45: =K11 -> Bollywood | D45: =K28 -> Bollywood | E45: =J28/J11 -> 18113.775 | F45: =IF(D45=C45, "Aligned","Not Aligned") -> Aligned
B46: Mumbai | C46: =K12 -> Bollywood | D46: =K29 -> Bollywood | E46: =J29/J12 -> 15825.44 | F46: =IF(D46=C46, "Aligned","Not Aligned") -> Aligned
B47: Nagpur | C47: =K13 -> Bollywood | D47: =K30 -> Bollywood | E47: =J30/J13 -> 18989.497 | F47: =IF(D47=C47, "Aligned","Not Aligned") -> Aligned
B48: Pune | C48: =K14 -> Bollywood | D48: =K31 -> Bollywood | E48: =J31/J14 -> 21542.64 | F48: =IF(D48=C48, "Aligned","Not Aligned") -> Aligned
B51: Bollywood dominates most cities as preferred genre with highest count
B52: Goa has the most genre with strong Bollywood, EDM, Hip hop and Rock presence
B53: City like Goa has the most events with different genre with perfect market fit(Most Attendance and Most Genre)
B56: How does total revenue correlate with with Total Attendees across different cities?
B58: City | C58: Total Events | D58: Total Revenue | E58: Total Attendance | F58: Avg Revenue/Event | G58: Revenue per attendee | H58: Performance Tier
B59: Amritsar | C59: =J5 -> 6 | D59: =SUMIF('Cleaned Data'!B2:B93,B59,'Cleaned Data'!M2:M93) -> 342669864 | E59: =SUMIF('Cleaned Data'!B2:B93,Stage6!B59,'Cleaned Data'!I2:I93) -> 115780.86 | F59: =D59/C59 -> 57111644 | G59: =D59/E59 -> 2959.6417 | H59: =IF(G59>AVERAGE(G59:G68),"High Performer","Standard") -> Standard
B60: Bengaluru | C60: =J6 -> 10 | D60: =SUMIF('Cleaned Data'!B3:B94,B60,'Cleaned Data'!M3:M94) -> 633786616 | E60: =SUMIF('Cleaned Data'!B3:B94,Stage6!B60,'Cleaned Data'!I3:I94) -> 150796.4 | F60: =D60/C60 -> 63378662 | G60: =D60/E60 -> 4202.9294 | H60: =IF(G60>AVERAGE(G60:G69),"High Performer","Standard") -> High Performer
B61: Chandigarh | C61: =J7 -> 8 | D61: =SUMIF('Cleaned Data'!B4:B95,B61,'Cleaned Data'!M4:M95) -> 340514615 | E61: =SUMIF('Cleaned Data'!B4:B95,Stage6!B61,'Cleaned Data'!I4:I95) -> 155236.1 | F61: =D61/C61 -> 42564327 | G61: =D61/E61 -> 2193.5272 | H61: =IF(G61>AVERAGE(G61:G70),"High Performer","Standard") -> Standard
B62: Delhi | C62: =J8 -> 10 | D62: =SUMIF('Cleaned Data'!B5:B96,B62,'Cleaned Data'!M5:M96) -> 744828479 | E62: =SUMIF('Cleaned Data'!B5:B96,Stage6!B62,'Cleaned Data'!I5:I96) -> 173785.96 | F62: =D62/C62 -> 74482848 | G62: =D62/E62 -> 4285.8956 | H62: =IF(G62>AVERAGE(G62:G71),"High Performer","Standard") -> High Performer
B63: Goa | C63: =J9 -> 15 | D63: =SUMIF('Cleaned Data'!B6:B97,B63,'Cleaned Data'!M6:M97) -> 1036587718 | E63: =SUMIF('Cleaned Data'!B6:B97,Stage6!B63,'Cleaned Data'!I6:I97) -> 354377.58 | F63: =D63/C63 -> 69105848 | G63: =D63/E63 -> 2925.094 | H63: =IF(G63>AVERAGE(G63:G72),"High Performer","Standard") -> Standard
B64: Jaipur | C64: =J10 -> 11 | D64: =SUMIF('Cleaned Data'!B7:B98,B64,'Cleaned Data'!M7:M98) -> 694118334 | E64: =SUMIF('Cleaned Data'!B7:B98,Stage6!B64,'Cleaned Data'!I7:I98) -> 214136.1 | F64: =D64/C64 -> 63101667 | G64: =D64/E64 -> 3241.4821 | H64: =IF(G64>AVERAGE(G64:G73),"High Performer","Standard") -> Standard
B65: Kolkata | C65: =J11 -> 8 | D65: =SUMIF('Cleaned Data'!B8:B99,B65,'Cleaned Data'!M8:M99) -> 580660842 | E65: =SUMIF('Cleaned Data'!B8:B99,Stage6!B65,'Cleaned Data'!I8:I99) -> 138744.2 | F65: =D65/C65 -> 72582605 | G65: =D65/E65 -> 4185.118 | H65: =IF(G65>AVERAGE(G65:G74),"High Performer","Standard") -> High Performer
B66: Mumbai | C66: =J12 -> 5 | D66: =SUMIF('Cleaned Data'!B9:B100,B66,'Cleaned Data'!M9:M100) -> 171830232 | E66: =SUMIF('Cleaned Data'!B9:B100,Stage6!B66,'Cleaned Data'!I9:I100) -> 79127.2 | F66: =D66/C66 -> 34366046 | G66: =D66/E66 -> 2171.5697 | H66: =IF(G66>AVERAGE(G66:G75),"High Performer","Standard") -> Standard
B67: Nagpur | C67: =J13 -> 12 | D67: =SUMIF('Cleaned Data'!B10:B101,B67,'Cleaned Data'!M10:M101) -> 716408170 | E67: =SUMIF('Cleaned Data'!B10:B101,Stage6!B67,'Cleaned Data'!I10:I101) -> 159094.96 | F67: =D67/C67 -> 59700681 | G67: =D67/E67 -> 4503.0224 | H67: =IF(G67>AVERAGE(G67:G76),"High Performer","Standard") -> High Performer
B68: Pune | C68: =J14 -> 7 | D68: =SUMIF('Cleaned Data'!B11:B102,B68,'Cleaned Data'!M11:M102) -> 479288314 | E68: =SUMIF('Cleaned Data'!B11:B102,Stage6!B68,'Cleaned Data'!I11:I102) -> 150798.48 | F68: =D68/C68 -> 68469759 | G68: =D68/E68 -> 3178.3365 | H68: =IF(G68>AVERAGE(G68:G77),"High Performer","Standard") -> Standard
B71: Correlation of Revenue and Attendance | E71: =CORREL(D59:D68,E59:E68) -> 0.85943128 | F71: Strong Correlation
B74: Highest Revenue Per Attendee | F74: Highest Total Revenue
B75: Rank | C75: City | D75: Revenue/Attendee | F75: Rank | G75: City | H75: Total Revenue
B76: 1 | C76: =INDEX($B$59:$B$68,MATCH(LARGE($G$59:$G$68,1),$G$59:$G$68,0)) -> Nagpur | D76: =LARGE(G59:G68,1) -> 4503.0224 | F76: 1 | G76: =INDEX($B$59:$B$68,MATCH(LARGE($D$59:$D$68,1),$D$59:$D$68,0)) -> Goa | H76: =LARGE($D$59:$D$68,1) -> 1036587718
B77: 2 | C77: =INDEX($B$59:$B$68,MATCH(LARGE($G$59:$G$68,2),$G$59:$G$68,0)) -> Delhi | D77: =LARGE(G60:G69,2) -> 4285.8956 | F77: 2 | G77: =INDEX($B$59:$B$68,MATCH(LARGE($D$59:$D$68,2),$D$59:$D$68,0)) -> Delhi | H77: =LARGE($D$59:$D$68,2) -> 744828479
B78: 3 | C78: =INDEX($B$59:$B$68,MATCH(LARGE($G$59:$G$68,3),$G$59:$G$68,0)) -> Bengaluru | D78: =LARGE(G61:G70,3) -> 4185.118 | F78: 3 | G78: =INDEX($B$59:$B$68,MATCH(LARGE($D$59:$D$68,3),$D$59:$D$68,0)) -> Nagpur | H78: =LARGE($D$59:$D$68,3) -> 716408170
B79: 4 | C79: =INDEX($B$59:$B$68,MATCH(LARGE($G$59:$G$68,4),$G$59:$G$68,0)) -> Kolkata | D79: =LARGE(G62:G71,4) -> 3241.4821 | F79: 4 | G79: =INDEX($B$59:$B$68,MATCH(LARGE($D$59:$D$68,4),$D$59:$D$68,0)) -> Jaipur | H79: =LARGE($D$59:$D$68,4) -> 694118334
B80: 5 | C80: =INDEX($B$59:$B$68,MATCH(LARGE($G$59:$G$68,5),$G$59:$G$68,0)) -> Jaipur | D80: =LARGE(G63:G72,5) -> 2925.094 | F80: 5 | G80: =INDEX($B$59:$B$68,MATCH(LARGE($D$59:$D$68,5),$D$59:$D$68,0)) -> Bengaluru | H80: =LARGE($D$59:$D$68,5) -> 633786616
D83: Highest Total Attendance
D84: Rank | E84: City | F84: Total Attendance
D85: 1 | E85: =INDEX($B$59:$B$68,MATCH(LARGE($E$59:$E$68,1),$E$59:$E$68,0)) -> Goa | F85: =LARGE($E$59:$E$68,1) -> 354377.58
D86: 2 | E86: =INDEX($B$59:$B$68,MATCH(LARGE($E$59:$E$68,2),$E$59:$E$68,0)) -> Jaipur | F86: =LARGE($E$59:$E$68,2) -> 214136.1
D87: 3 | E87: =INDEX($B$59:$B$68,MATCH(LARGE($E$59:$E$68,3),$E$59:$E$68,0)) -> Delhi | F87: =LARGE($E$59:$E$68,3) -> 173785.96
D88: 4 | E88: =INDEX($B$59:$B$68,MATCH(LARGE($E$59:$E$68,4),$E$59:$E$68,0)) -> Nagpur | F88: =LARGE($E$59:$E$68,4) -> 159094.96
D89: 5 | E89: =INDEX($B$59:$B$68,MATCH(LARGE($E$59:$E$68,5),$E$59:$E$68,0)) -> Chandigarh | F89: =LARGE($E$59:$E$68,5) -> 155236.1
B92: Revenue and Attendee correlation:-
B93: HIGHEST REVENUE PER ATTENDEE cities are the most profitable per person
B94: Cities with HIGH TOTAL REVENUE but LOW Revenue/Attendee indicate volume-driven markets (mass appeal, lower ticket prices)
B95: A POSITIVE CORRELATION between Revenue and Attendance confirms that drawing more crowds leads to higher revenue

Sheet Dashboard
A1: INDIA MUSIC FESTIVAL ANALYTICS DASHBOARD 2024
A3: KEY PERFORMANCE METRICS | F3: TOP 5 SPONSORSHIP & MERCHANDISE CONTRIBUTION (Stage5)
A4: Total Revenue | B4: Total Attendance | C4: Total Events | D4: Avg Ticket Price | F4: Festival | G4: Sponsorship % | H4: Merch % | I4: Total Revenue(Spon+Merch)
A5: =Stage2!B16 -> 5964562939 | B5: =Stage2!C39 -> 1802309.7 | C5: =Stage4!B57 -> 92 | D5: =Stage3!B14 -> 2914.1931 | F5: Supersonic Bengaluru | G5: =Stage5!F12 -> 0.074171779 | H5: =Stage5!G12 -> 0.072309776 | I5: =Stage5!E12 -> 468868182
F6: Ziro Festival | G6: =Stage5!F14 -> 0.032867875 | H6: =Stage5!G14 -> 0.069779648 | I6: =Stage5!E14 -> 1069812715
A7: PEAK SEASON ANALYSIS (Stage2) | F7: Sunburn Goa | G7: =Stage5!F11 -> 0.05378695 | H7: =Stage5!G11 -> 0.093274149 | I7: =Stage5!E11 -> 695292216
A8: Month | B8: Revenue | C8: Attendance | D8: % of Total | F8: VH1 Supersonic Delhi | G8: =Stage5!F13 -> 0.057914604 | H8: =Stage5!G13 -> 0.073170407 | I8: =Stage5!E13 -> 459482479
A9: December | B9: =Stage2!B15 -> 865042389 | C9: =Stage2!C38 -> 261064.58 | D9: =Stage2!C15 -> 0.14503031 | F9: Magnetic Fields | G9: =Stage5!F9 -> 0.050233971 | H9: =Stage5!G9 -> 0.10578594 | I9: =Stage5!E9 -> 417295881
A10: August | B10: =Stage2!B11 -> 848183953 | C10: =Stage2!C34 -> 256917.18 | D10: =Stage2!C11 -> 0.14220387 | F10: Avg Sponsorship: | G10: =Stage5!D18 -> 0.04502832 | H10: =Stage5!G15 -> 0.087303339
A11: September | B11: =Stage2!B12 -> 695359429 | C11: =Stage2!C35 -> 142573 | D11: =Stage2!C12 -> 0.11658179 | F11: Sponsorship avg 4.5% of revenue; Merch avg 8.73%
A12: Dec & Aug are best months (14.5% & 14.2% revenue share) | F12: STRATEGIC RECOMMENDATIONS
F13: TIMING: Focus on December & August for maximum revenue
A14: TOP 5 CITIES BY PERFORMANCE(Stage2) | F14: LOCATION: Goa is the festival hotspot; expand in Nagpur, Jaipur
A15: City | B15: Revenue | C15: Attedance | D15: Rank | F15: PRICING: Optimal ticket range ₹2,500-3,500 (25% attendance)
A16: Goa | B16: =Stage2!B55 -> 1073141556 | C16: =Stage2!C55 -> 369065.58 | D16: 1 | F16: ARTISTS: Book Badshah/Diljit for max turnout & revenue
A17: Jaipur | B17: =Stage2!B54 -> 752723987 | C17: =Stage2!C54 -> 234934.98 | D17: 2 | F17: GENRE: Bollywood dominates; add EDM for Jaipur
A18: Nagpur | B18: =Stage2!B51 -> 831769738 | C18: =Stage2!C51 -> 227873.96 | D18: 3 | F18: SPONSORSHIP: Premium festivals attract higher sponsorship/attendee
A19: Delhi | B19: =Stage2!B56 -> 744828479 | C19: =Stage2!C56 -> 173785.96 | D19: 4 | F19: ₹2,500-3,500 is optimal (highest attendance 25.42%)
A20: Chandigarh | B20: =Stage2!B57 -> 340514615 | C20: =Stage2!C57 -> 155236.1 | D20: 5
A21: Goa leads with highest attendance - festival hotspot
A22: TOP 5 ARTISTS PERFORMANCE (Stage4)
A23: Artist | B23: =Stage4!F4 -> Avg Revenue / Event | C23: =Stage4!E4 -> Avg Attendance/Event | D23: Count of Events
A24: Badshah | B24: =INDEX(Stage4!$F$5:$F$14,MATCH(Dashboard!A24,Stage4!$A$5:$A$14,0)) -> 84364633 | C24: =INDEX(Stage4!$E$5:$E$14,MATCH(Dashboard!A24,Stage4!$A$5:$A$14,0)) -> 21629.323 | D24: =Stage4!D6 -> 12
A25: Honey Singh | B25: =INDEX(Stage4!$F$5:$F$14,MATCH(Dashboard!A25,Stage4!$A$5:$A$14,0)) -> 79786683 | C25: =INDEX(Stage4!$E$5:$E$14,MATCH(Dashboard!A25,Stage4!$A$5:$A$14,0)) -> 15857.727 | D25: =Stage4!D11 -> 11
A26: Bryan Adams | B26: =INDEX(Stage4!$F$5:$F$14,MATCH(Dashboard!A26,Stage4!$A$5:$A$14,0)) -> 69386246 | C26: =INDEX(Stage4!$E$5:$E$14,MATCH(Dashboard!A26,Stage4!$A$5:$A$14,0)) -> 15183.098 | D26: =Stage4!D7 -> 12
A27: Shreya Ghoshal | B27: =INDEX(Stage4!$F$5:$F$14,MATCH(Dashboard!A27,Stage4!$A$5:$A$14,0)) -> 70785754 | C27: =INDEX(Stage4!$E$5:$E$14,MATCH(Dashboard!A27,Stage4!$A$5:$A$14,0)) -> 21867.564 | D27: =Stage4!D14 -> 10
A28: Diljit Dosanjh | B28: =INDEX(Stage4!$F$5:$F$14,MATCH(Dashboard!A28,Stage4!$A$5:$A$14,0)) -> 56703470 | C28: =INDEX(Stage4!$E$5:$E$14,MATCH(Dashboard!A28,Stage4!$A$5:$A$14,0)) -> 31512.813 | D28: =Stage4!D8 -> 8
A29: Badshah = Top revenue; Diljit = Best per-event avg (31,513)
A32: INTERNATIONAL VS LOCAL ARTISTS (Stage4)
A33: Category | B33: Events | C33: Attendance | D33: Avg Ticket Price
A34: International | B34: =Stage4!B55 -> 29 | C34: =Stage4!C55 -> 478689.94 | D34: =Stage4!E55 -> 3223.4075
A35: Local Artist | B35: =Stage4!B56 -> 63 | C35: =Stage4!C56 -> 1323619.8 | D35: =Stage4!E56 -> 2771.8564
A36: Local artists = 2.8x more events; International = Higher ticket price
A40: Dashboard consolidates key insights from Stage2 (Seasonality & Cities), Stage3 (Pricing), Stage4 (Artists & Genre), Stage5 (Sponsorship), Stage6 (Regional Preferences)
A41: The data used in this project is purely for demonstration purposes and does not represent real-world information.

Sheet Thumbnail
A1: INDIA MUSIC FESTIVAL ANALYTICS (2024)
